Workbook

Sheet Sheet1
B1: place_id | C1: author | D1: join_col | E1: rating | F1: date | G1: text | H1: place_name | I1: index | J1: date_parsed | K1: ABSA_manual | L1: atepc_json | M1: flag | N1: len_manual | O1: len_atepc | P1: len_g1 | Q1: len_g2 | R1: len_g3 | S1: len_g4 | T1: diff_g1 | U1: diff_g2 | V1: diff_g3 | W1: diff_g4 | X1: xgn | AH1: gj
A2: 255 | B2: ChIJ3SGSkBkFkWsR6tKcdeWSRZA | C2: Chloe Ramsdale | D2: ChIJ3SGSkBkFkWsR6tKcdeWSRZAChloe Ramsdale | E2: 1 | F2: a year ago | G2: Waste of money. Room is tiny and filled with plastic ice, random decor and a few games to try entertain... Felt very awkward and rushed. Not allowed to take your own photos and half of the cameras in there were broken, which was just met … | H2: IceBar Surfers | I2: 15776 | J2: 2024-10-10 | K2: {"overall_sentiment":"negative","aspects":[{"aspect":"room","category":"space","sentiment":"negative","evidence_span":"Room is tiny"},{"aspect":"decor","category":"ambience","sentiment":"negative","evidence_span":"random decor"},{"aspect":"photo policy","category":"policy","sentiment":"negative","evidence_span":"Not allowed"},{"aspect":"cameras","category":"equipment","sentiment":"negative","evidence_span":"were broken"}, {'aspect': 'games',"category":"entertainment", 'opinion': 'few', 'sentiment': 'negative'}, {'aspect': 'value for money',"category":"price", 'opinion': 'waste of money', 'sentiment': 'negative'}, {'aspect': 'experience',"category":"experience", 'opinion': 'awkward', 'sentiment': 'negative'}]} | L2: {'sentence': 'Waste of money . Room is tiny and filled with plastic ice , random decor and a few games to try entertain . . . Felt very awkward and rushed . Not allowed to take your own photos and half of the cameras in there were broken , which was just met …', 'IOB': ['O', 'O', 'O', 'O', 'O', 'O', 'O', 'O', 'O', 'O', 'O', 'O', 'O', 'O', 'B-ASP', 'O', 'O', 'O', 'B-ASP', 'O', 'O', 'O', 'O', 'O', 'O', 'O', 'O', 'O', 'O', 'O', 'O', 'O', 'O', 'O', 'O', 'O', 'O', 'O', 'O', 'O', 'O', 'O', 'O', 'O', 'O', 'O', 'O', 'O', 'O', 'O', 'O', 'O', 'O'], 'tokens': ['Waste', 'of', 'money', '.', 'Room', 'is', 'tiny', 'and', 'filled', 'with', 'plastic', 'ice', ',', 'random', 'decor', 'and', 'a', 'few', 'games', 'to', 'try', 'entertain', '.', '.', '.', 'Felt', 'very', 'awkward', 'and', 'rushed', '.', 'Not', 'allowed', 'to', 'take', 'your', 'own', 'photos', 'and', 'half', 'of', 'the', 'cameras', 'in', 'there', 'were', 'broken', ',', 'which', 'was', 'just', 'met', '…'], 'aspect': ['decor', 'games'], 'position': [[14], [18]], 'sentiment': ['Negative', 'Negative'], 'probs': [[0.971028208732605, 0.028118714690208435, 0.0008530318737030029], [0.6798680424690247, 0.31912750005722046, 0.0010044979862868786]], 'confidence': [0.971, 0.6799]} | M2: 1 | N2: =LEN(K2)-LEN(SUBSTITUTE(K2,"{",""))-1 -> 7 | O2: 2 | P2: =_xlfn.XLOOKUP(B2,'g1'!B:B,'g1'!R:R) -> 8 | Q2: =_xlfn.XLOOKUP(B2,'g2'!B:B,'g2'!U:U) -> 7 | R2: =_xlfn.XLOOKUP(B2,'g3'!B:B,'g3'!R:R) -> 6 | S2: =_xlfn.XLOOKUP(D2,'g4'!D:D,'g4'!N:N) -> 8 | T2: =$N2-P2 -> -1 | U2: =$N2-Q2 -> 0 | V2: =$N2-R2 -> 1 | W2: =$N2-S2 -> -1 | X2: [{'aspect': 'room', 'opinion': 'tiny', 'sentiment': 'negative'}, {'aspect': 'ice', 'opinion': 'plastic', 'sentiment': 'negative'}, {'aspect': 'decor', 'opinion': 'random', 'sentiment': 'negative'}, {'aspect': 'games', 'opinion': 'few', 'sentiment': 'negative'}, {'aspect': 'photo policy', 'opinion': 'not allowed to take your own photos', 'sentiment': 'negative'}, {'aspect': 'cameras', 'opinion': 'half of the cameras in there were broken', 'sentiment': 'negative'}, {'aspect': 'value for money', 'opinion': 'waste of money', 'sentiment': 'negative'}, {'aspect': 'experience', 'opinion': 'awkward', 'sentiment': 'negative'}] | Y2: =FIND("[{",K2) -> 43 | Z2: =FIND("category",K2) -> 62 | AA2: =Z2-Y2-2 -> 17 | AB2: room | AD2: =FIND("[{",X2) -> 1 | AE2: =FIND("opinion",X2) -> 22 | AF2: =AE2-AD2-2 -> 19 | AG2: room | AH2: =AB2=AG2 -> TRUE
A3: 1480 | B3: ChIJoWNwIKNQkWsRoLkh11ujAg8 | C3: Colin wick | D3: ChIJoWNwIKNQkWsRoLkh11ujAg8Colin wick | E3: 4 | F3: a year ago | G3: Great spirit from both visitors and stall holders - very vibrant yet peaceful environment. I purchased fresh flowers, fruit & veg and bakery products. Coffee and fresh juice was very good. Prices were generally good with fresh products … | H3: The West End Markets | I3: 434 | J3: 2024-10-10 | K3: {"overall_sentiment":"positive","aspects":[{"aspect":"spirit","category":"atmosphere","sentiment":"positive","evidence_span":"Great spirit"},{"aspect":"environment","category":"atmosphere","sentiment":"positive","evidence_span":"peaceful environment"},{"aspect":"coffee","category":"beverage","sentiment":"positive","evidence_span":"very good"},{"aspect":"fresh juice","category":"beverage","sentiment":"positive","evidence_span":"very good"},{"aspect":"prices","category":"pricing","sentiment":"positive","evidence_span":"generally good"}]} | L3: {'sentence': 'Great spirit from both visitors and stall holders - very vibrant yet peaceful environment . I purchased fresh flowers , fruit & veg and bakery products . Coffee and fresh juice was very good . Prices were generally good with fresh products …', 'IOB': ['O', 'O', 'O', 'O', 'O', 'O', 'B-ASP', 'I-ASP', 'O', 'O', 'O', 'O', 'O', 'B-ASP', 'O', 'O', 'O', 'O', 'O', 'O', 'O', 'O', 'O', 'O', 'O', 'O', 'O', 'B-ASP', 'O', 'O', 'B-ASP', 'O', 'O', 'O', 'O', 'B-ASP', 'O', 'O', 'O', 'O', 'O', 'O', 'O'], 'tokens': ['Great', 'spirit', 'from', 'both', 'visitors', 'and', 'stall', 'holders', '-', 'very', 'vibrant', 'yet', 'peaceful', 'environment', '.', 'I', 'purchased', 'fresh', 'flowers', ',', 'fruit', '&', 'veg', 'and', 'bakery', 'products', '.', 'Coffee', 'and', 'fresh', 'juice', 'was', 'very', 'good', '.', 'Prices', 'were', 'generally', 'good', 'with', 'fresh', 'products', '…'], 'aspect': ['stall holders', 'environment', 'Coffee', 'juice', 'Prices'], 'position': [[6, 7], [13], [27], [30], [35]], 'sentiment': ['Positive', 'Positive', 'Positive', 'Positive', 'Positive'], 'probs': [[0.0002124903112417087, 0.000311657931888476, 0.99947589635849], [0.00018766136781778187, 0.0004186705918982625, 0.9993937015533447], [0.0002741042117122561, 0.0005672599072568119, 0.9991586208343506], [0.0002939401601906866, 0.000521963054779917, 0.9991840720176697], [0.0002796389744617045, 0.0004245512536726892, 0.9992958307266235]], 'confidence': [0.9995, 0.9994, 0.9992, 0.9992, 0.9993]} | N3: =LEN(K3)-LEN(SUBSTITUTE(K3,"{",""))-1 -> 5 | O3: 5 | P3: =_xlfn.XLOOKUP(B3,'g1'!B:B,'g1'!R:R) -> 9 | Q3: =_xlfn.XLOOKUP(B3,'g2'!B:B,'g2'!U:U) -> 9 | R3: =_xlfn.XLOOKUP(B3,'g3'!B:B,'g3'!R:R) -> 5 | S3: =_xlfn.XLOOKUP(D3,'g4'!D:D,'g4'!N:N) -> 7 | T3: =$N3-P3 -> -4 | U3: =$N3-Q3 -> -4 | V3: =$N3-R3 -> 0 | W3: =$N3-S3 -> -2 | X3: [{'aspect': 'fresh flowers', 'opinion': 'fresh', 'sentiment': 'neutral'}, {'aspect': 'fruit & veg', 'opinion': 'fresh', 'sentiment': 'neutral'}, {'aspect': 'bakery products', 'opinion': 'fresh', 'sentiment': 'neutral'}, {'aspect': 'coffee', 'opinion': 'very good', 'sentiment': 'positive'}, {'aspect': 'fresh juice', 'opinion': 'very good', 'sentiment': 'positive'}, {'aspect': 'environment', 'opinion': 'very vibrant', 'sentiment': 'positive'}, {'aspect': 'prices', 'opinion': 'good', 'sentiment': 'positive'}] | Y3: =FIND("[{",K3) -> 43 | Z3: =FIND("category",K3) -> 64 | AA3: =Z3-Y3-2 -> 19 | AB3: spirit | AD3: =FIND("[{",X3) -> 1 | AE3: =FIND("opinion",X3) -> 31 | AF3: =AE3-AD3-2 -> 28 | AG3: fresh flowers | AH3: =AB3=AG3 -> FALSE
A4: 1504 | B4: ChIJP7OFsOzvkGsRcMf9c7UJBg8 | C4: Jack Hamers | D4: ChIJP7OFsOzvkGsRcMf9c7UJBg8Jack Hamers | E4: 2 | F4: 7 years ago | G4: Bar service was excellent. Food service was great but the food really let's down the club. Expensive and it is either deep fried fast food or flavorless a really disappointment for the club. Awesome Raffles! | H4: Murwillumbah Golf Club | I4: 7671 | J4: 2018-10-12 | K4: {"overall_sentiment":"negative","aspects":[{"aspect":"bar service","category":"service","sentiment":"positive","evidence_span":"was excellent"},{"aspect":"food service","category":"service","sentiment":"positive","evidence_span":"was great"},{"aspect":"food","category":"food","sentiment":"negative","evidence_span":"let's down"},{"aspect":"price","category":"price","sentiment":"negative","evidence_span":"Expensive"},{"aspect":"Raffles","category":"entertainment","sentiment":"positive","evidence_span":"Awesome Raffles!"}]} | L4: {'sentence': "Bar service was excellent . Food service was great but the food really let ' s down the club . Expensive and it is either deep fried fast food or flavorless a really disappointment for the club . Awesome Raffles !", 'IOB': ['B-ASP', 'I-ASP', 'O', 'O', 'O', 'B-ASP', 'I-ASP', 'O', 'O', 'O', 'O', 'B-ASP', 'O', 'O', 'O', 'O', 'O', 'O', 'O', 'O', 'O', 'O', 'O', 'O', 'O', 'O', 'O', 'O', 'O', 'O', 'O', 'O', 'O', 'O', 'O', 'O', 'O', 'O', 'O', 'O', 'O'], 'tokens': ['Bar', 'service', 'was', 'excellent', '.', 'Food', 'service', 'was', 'great', 'but', 'the', 'food', 'really', 'let', "'", 's', 'down', 'the', 'club', '.', 'Expensive', 'and', 'it', 'is', 'either', 'deep', 'fried', 'fast', 'food', 'or', 'flavorless', 'a', 'really', 'disappointment', 'for', 'the', 'club', '.', 'Awesome', 'Raffles', '!'], 'aspect': ['Bar service', 'Food service', 'food'], 'position': [[0, 1], [5, 6], [11]], 'sentiment': ['Positive', 'Positive', 'Negative'], 'probs': [[0.015679549425840378, 0.0008737363386899233, 0.9834467768669128], [0.02416217513382435, 0.0008892863988876343, 0.974948525428772], [0.8960981965065002, 0.014301101677119732, 0.08960071206092834]], 'confidence': [0.9834, 0.9749, 0.8961]} | M4: 1 | N4: =LEN(K4)-LEN(SUBSTITUTE(K4,"{",""))-1 -> 5 | O4: 3 | P4: =_xlfn.XLOOKUP(B4,'g1'!B:B,'g1'!R:R) -> 5 | Q4: =_xlfn.XLOOKUP(B4,'g2'!B:B,'g2'!U:U) -> 5 | R4: =_xlfn.XLOOKUP(B4,'g3'!B:B,'g3'!R:R) -> 4 | S4: =_xlfn.XLOOKUP(D4,'g4'!D:D,'g4'!N:N) -> 7 | T4: =$N4-P4 -> 0 | U4: =$N4-Q4 -> 0 | V4: =$N4-R4 -> 1 | W4: =$N4-S4 -> -2 | X4: [{'aspect': 'bar service', 'opinion': 'excellent', 'sentiment': 'positive'}, {'aspect': 'food service', 'opinion': 'great', 'sentiment': 'positive'}, {'aspect': 'food', 'opinion': 'let down', 'sentiment': 'negative'}, {'aspect': 'food', 'opinion': 'expensive', 'sentiment': 'negative'}, {'aspect': 'food', 'opinion': 'flavorless', 'sentiment': 'negative'}, {'aspect': 'food', 'opinion': 'disappointment', 'sentiment': 'negative'}, {'aspect': 'raffles', 'opinion': 'awesome', 'sentiment': 'positive'}] | Y4: =FIND("[{",K4) -> 43 | Z4: =FIND("category",K4) -> 69 | AA4: =Z4-Y4-2 -> 24 | AB4: bar service | AD4: =FIND("[{",X4) -> 1 | AE4: =FIND("opinion",X4) -> 29 | AF4: =AE4-AD4-2 -> 26 | AG4: bar service | AH4: =AB4=AG4 -> TRUE
A5: 1087 | B5: ChIJaezMtIGAvmsRbLcaWOBK59o | C5: mark brinkhuizen | D5: ChIJaezMtIGAvmsRbLcaWOBK59omark brinkhuizen | E5: 3 | F5: 10 months ago | G5: Stayed here 2 nights. Excellent flush toilets. There is no power or water but plenty of space and level sites. There is a creek you can swim in. We enjoyed our stay | H5: Chinchilla Weir Camping | I5: 7914 | J5: 2024-12-14 | K5: {"overall_sentiment":"positive","aspects":[{"aspect":"flush toilets","category":"facilities","sentiment":"positive","evidence_span":"Excellent flush toilets"},{"aspect":"power","category":"utilities","sentiment":"negative","evidence_span":"no power"},{"aspect":"water","category":"utilities","sentiment":"negative","evidence_span":"no water"},{"aspect":"space","category":"space","sentiment":"positive","evidence_span":"plenty of space"},{"aspect":"sites","category":"site","sentiment":"positive","evidence_span":"level sites"}, {'aspect': 'creek',"category":"creek", 'opinion': 'can swim in', 'sentiment': 'positive'}]} | L5: {'sentence': 'Stayed here 2 nights . Excellent flush toilets . There is no power or water but plenty of space and level sites . There is a creek you can swim in . We enjoyed our stay', 'IOB': ['O', 'O', 'O', 'O', 'O', 'O', 'O', 'B-ASP', 'O', 'O', 'O', 'O', 'O', 'O', 'O', 'O', 'O', 'O', 'O', 'O', 'O', 'O', 'O', 'O', 'O', 'O', 'O', 'O', 'O', 'O', 'O', 'O', 'O', 'O', 'O', 'O'], 'tokens': ['Stayed', 'here', '2', 'nights', '.', 'Excellent', 'flush', 'toilets', '.', 'There', 'is', 'no', 'power', 'or', 'water', 'but', 'plenty', 'of', 'space', 'and', 'level', 'sites', '.', 'There', 'is', 'a', 'creek', 'you', 'can', 'swim', 'in', '.', 'We', 'enjoyed', 'our', 'stay'], 'aspect': ['toilets'], 'position': [[7]], 'sentiment': ['Positive'], 'probs': [[0.0007605825085192919, 0.0005012063775211573, 0.9987382292747498]], 'confidence': [0.9987]} | M5: 1 | N5: =LEN(K5)-LEN(SUBSTITUTE(K5,"{",""))-1 -> 6 | O5: 1 | P5: =_xlfn.XLOOKUP(B5,'g1'!B:B,'g1'!R:R) -> 7 | Q5: =_xlfn.XLOOKUP(B5,'g2'!B:B,'g2'!U:U) -> 7 | R5: =_xlfn.XLOOKUP(B5,'g3'!B:B,'g3'!R:R) -> 6 | S5: =_xlfn.XLOOKUP(D5,'g4'!D:D,'g4'!N:N) -> 7 | T5: =$N5-P5 -> -1 | U5: =$N5-Q5 -> -1 | V5: =$N5-R5 -> 0 | W5: =$N5-S5 -> -1 | X5: [{'aspect': 'flush toilets', 'opinion': 'Excellent', 'sentiment': 'positive'}, {'aspect': 'sites', 'opinion': 'level', 'sentiment': 'positive'}, {'aspect': 'power', 'opinion': 'no', 'sentiment': 'negative'}, {'aspect': 'water', 'opinion': 'no', 'sentiment': 'negative'}, {'aspect': 'space', 'opinion': 'plenty', 'sentiment': 'positive'}, {'aspect': 'creek', 'opinion': 'can swim in', 'sentiment': 'positive'}, {'aspect': 'stay', 'opinion': 'enjoyed', 'sentiment': 'positive'}] | Y5: =FIND("[{",K5) -> 43 | Z5: =FIND("category",K5) -> 71 | AA5: =Z5-Y5-2 -> 26 | AB5: toilets | AD5: =FIND("[{",X5) -> 1 | AE5: =FIND("opinion",X5) -> 31 | AF5: =AE5-AD5-2 -> 28 | AG5: flush toilets | AH5: =AB5=AG5 -> FALSE
A6: 943 | B6: ChIJpRd2-64P1moRNjJXWrrA53k | C6: Darren Lawson | D6: ChIJpRd2-64P1moRNjJXWrrA53kDarren Lawson | E6: 4 | F6: a year ago | G6: Nice atmosphere, lots of different types of entertainment from sports betting, horse racing, greyhound racing, pokies, bingo and more. … | H6: Trios Sports Club | I6: 2800 | J6: 2024-10-10 | K6: {"overall_sentiment":"positive","aspects":[{"aspect":"atmosphere","category":"ambience","sentiment":"positive","evidence_span":"Nice atmosphere"},{'aspect': 'sports betting', 'opinion': 'lots of different types of entertainment', 'sentiment': 'positive'}, {'aspect': 'horse racing', 'opinion': 'lots of different types of entertainment', 'sentiment': 'positive'}, {'aspect': 'greyhound racing', 'opinion': 'lots of different types of entertainment', 'sentiment': 'positive'}, {'aspect': 'pokies', 'opinion': 'lots of different types of entertainment', 'sentiment': 'positive'}, {'aspect': 'bingo', 'opinion': 'lots of different types of entertainment', 'sentiment': 'positive'}]} | L6: {'sentence': 'Nice atmosphere , lots of different types of entertainment from sports betting , horse racing , greyhound racing , pokies , bingo and more . …', 'IOB': ['O', 'B-ASP', 'O', 'O', 'O', 'O', 'O', 'O', 'B-ASP', 'O', 'O', 'O', 'O', 'O', 'O', 'O', 'O', 'O', 'O', 'O', 'O', 'O', 'O', 'O', 'O', 'O'], 'tokens': ['Nice', 'atmosphere', ',', 'lots', 'of', 'different', 'types', 'of', 'entertainment', 'from', 'sports', 'betting', ',', 'horse', 'racing', ',', 'greyhound', 'racing', ',', 'pokies', ',', 'bingo', 'and', 'more', '.', '…'], 'aspect': ['atmosphere', 'entertainment'], 'position': [[1], [8]], 'sentiment': ['Positive', 'Positive'], 'probs': [[0.0006744035053998232, 0.00046974350698292255, 0.9988558292388916], [0.0003576667804736644, 0.00231339898891747, 0.9973289966583252]], 'confidence': [0.9989, 0.9973]} | N6: =LEN(K6)-LEN(SUBSTITUTE(K6,"{",""))-1 -> 6 | O6: 2 | P6: =_xlfn.XLOOKUP(B6,'g1'!B:B,'g1'!R:R) -> 2 | Q6: =_xlfn.XLOOKUP(B6,'g2'!B:B,'g2'!U:U) -> 2 | R6: =_xlfn.XLOOKUP(B6,'g3'!B:B,'g3'!R:R) -> 2 | S6: =_xlfn.XLOOKUP(D6,'g4'!D:D,'g4'!N:N) -> 6 | T6: =$N6-P6 -> 4 | U6: =$N6-Q6 -> 4 | V6: =$N6-R6 -> 4 | W6: =$N6-S6 -> 0 | X6: [{'aspect': 'atmosphere', 'opinion': 'Nice atmosphere', 'sentiment': 'positive'}, {'aspect': 'sports betting', 'opinion': 'lots of different types of entertainment', 'sentiment': 'positive'}, {'aspect': 'horse racing', 'opinion': 'lots of different types of entertainment', 'sentiment': 'positive'}, {'aspect': 'greyhound racing', 'opinion': 'lots of different types of entertainment', 'sentiment': 'positive'}, {'aspect': 'pokies', 'opinion': 'lots of different types of entertainment', 'sentiment': 'positive'}, {'aspect': 'bingo', 'opinion': 'lots of different types of entertainment', 'sentiment': 'positive'}] | Y6: =FIND("[{",K6) -> 43 | Z6: =FIND("category",K6) -> 68 | AA6: =Z6-Y6-2 -> 23 | AB6: atmosphere | AD6: =FIND("[{",X6) -> 1 | AE6: =FIND("opinion",X6) -> 28 | AF6: =AE6-AD6-2 -> 25 | AG6: atmosphere | AH6: =AB6=AG6 -> TRUE
A7: 1032 | B7: ChIJX4rMQkgX1GoR0HEyBXZWBA8 | C7: Luke k | D7: ChIJX4rMQkgX1GoR0HEyBXZWBA8Luke k | E7: 3 | F7: 5 days ago | G7: The facility itself is great with good infrastructure and modern amenities. Unfortunately, the customer service really lets it down, staff don’t pay attention to queries and the training team comes across as highly unprofessional. With better service, this place could be excellent. | H7: Norlane ARC | I7: 6706 | J7: 2025-10-05 | K7: {"overall_sentiment":"negative","aspects":[{"aspect":"facility","category":"facility","sentiment":"positive","evidence_span":"great"},{"aspect":"infrastructure","category":"infrastructure","sentiment":"positive","evidence_span":"good infrastructure"},{"aspect":"amenities","category":"amenities","sentiment":"positive","evidence_span":"modern amenities"},{"aspect":"customer service","category":"service","sentiment":"negative","evidence_span":"lets it down"},{"aspect":"training team","category":"staff","sentiment":"negative","evidence_span":"highly unprofessional"}]} | L7: {'sentence': 'The facility itself is great with good infrastructure and modern amenities . Unfortunately , the customer service really lets it down , staff don ’ t pay attention to queries and the training team comes across as highly unprofessional . With better service , this place could be excellent .', 'IOB': ['O', 'B-ASP', 'O', 'O', 'O', 'O', 'O', 'B-ASP', 'O', 'O', 'B-ASP', 'O', 'O', 'O', 'O', 'B-ASP', 'I-ASP', 'O', 'O', 'O', 'O', 'O', 'B-ASP', 'O', 'O', 'O', 'O', 'O', 'O', 'O', 'O', 'O', 'O', 'O', 'O', 'O', 'O', 'O', 'O', 'O', 'O', 'O', 'O', 'O', 'O', 'O', 'O', 'O', 'O', 'O'], 'tokens': ['The', 'facility', 'itself', 'is', 'great', 'with', 'good', 'infrastructure', 'and', 'modern', 'amenities', '.', 'Unfortunately', ',', 'the', 'customer', 'service', 'really', 'lets', 'it', 'down', ',', 'staff', 'don', '’', 't', 'pay', 'attention', 'to', 'queries', 'and', 'the', 'training', 'team', 'comes', 'across', 'as', 'highly', 'unprofessional', '.', 'With', 'better', 'service', ',', 'this', 'place', 'could', 'be', 'excellent', '.'], 'aspect': ['facility', 'infrastructure', 'amenities', 'customer service', 'staff'], 'position': [[1], [7], [10], [15, 16], [22]], 'sentiment': ['Positive', 'Positive', 'Positive', 'Negative', 'Negative'], 'probs': [[0.006587614770978689, 0.0003718012885656208, 0.9930405616760254], [0.0012611483689397573, 0.00026064837584272027, 0.9984782338142395], [0.0016403849003836513, 0.0002667618391569704, 0.9980928301811218], [0.999022364616394, 0.000625345972366631, 0.0003523131017573178], [0.9939771890640259, 0.005713719874620438, 0.00030897592660039663]], 'confidence': [0.993, 0.9985, 0.9981, 0.999, 0.994]} | M7: 0 | N7: =LEN(K7)-LEN(SUBSTITUTE(K7,"{",""))-1 -> 5 | O7: 5 | P7: =_xlfn.XLOOKUP(B7,'g1'!B:B,'g1'!R:R) -> 6 | Q7: =_xlfn.XLOOKUP(B7,'g2'!B:B,'g2'!U:U) -> 6 | R7: =_xlfn.XLOOKUP(B7,'g3'!B:B,'g3'!R:R) -> 2 | S7: =_xlfn.XLOOKUP(D7,'g4'!D:D,'g4'!N:N) -> 6 | T7: =$N7-P7 -> -1 | U7: =$N7-Q7 -> -1 | V7: =$N7-R7 -> 3 | W7: =$N7-S7 -> -1 | X7: [{'aspect': 'facility', 'opinion': 'great', 'sentiment': 'positive'}, {'aspect': 'infrastructure', 'opinion': 'good', 'sentiment': 'positive'}, {'aspect': 'amenities', 'opinion': 'modern', 'sentiment': 'positive'}, {'aspect': 'customer service', 'opinion': 'really lets it down', 'sentiment': 'negative'}, {'aspect': 'staff', 'opinion': 'don’t pay attention', 'sentiment': 'negative'}, {'aspect': 'training team', 'opinion': 'highly unprofessional', 'sentiment': 'negative'}] | Y7: =FIND("[{",K7) -> 43 | Z7: =FIND("category",K7) -> 66 | AA7: =Z7-Y7-2 -> 21 | AB7: facility | AD7: =FIND("[{",X7) -> 1 | AE7: =FIND("opinion",X7) -> 26 | AF7: =AE7-AD7-2 -> 23 | AG7: facility | AH7: =AB7=AG7 -> TRUE
A8: 1135 | B8: ChIJW5rqSjUR1moRqbEWJXj9SnI | C8: Jamil Zaman | D8: ChIJW5rqSjUR1moRqbEWJXj9SnIJamil Zaman | E8: 1 | F8: 2 years ago | G8: Terrible palace and not community center at all. Staff is untrained and unprofessional. Pools are dirty. No place for swimming as if you do not pay for private lessons your kids are pushed into pool corner together with all other kids. … | H8: Freeway Fitness | I8: 3540 | J8: 2023-10-11 | K8: {"overall_sentiment":"negative","aspects":[{"aspect":"place","category":"facility","sentiment":"negative","evidence_span":"Terrible palace"},{"aspect":"community center","category":"facility","sentiment":"negative","evidence_span":"not community center"},{"aspect":"staff","category":"service","sentiment":"negative","evidence_span":"untrained and unprofessional"},{"aspect":"pools","category":"facility","sentiment":"negative","evidence_span":"dirty"},{"aspect":"private lessons","category":"service","sentiment":"negative","evidence_span":"private lessons"}]} | L8: {'sentence': 'Terrible palace and not community center at all . Staff is untrained and unprofessional . Pools are dirty . No place for swimming as if you do not pay for private lessons your kids are pushed into pool corner together with all other kids . …', 'IOB': ['O', 'O', 'O', 'O', 'O', 'O', 'O', 'O', 'O', 'B-ASP', 'O', 'O', 'O', 'O', 'O', 'B-ASP', 'O', 'O', 'O', 'O', 'O', 'O', 'O', 'O', 'O', 'O', 'O', 'O', 'O', 'O', 'O', 'O', 'O', 'O', 'O', 'O', 'O', 'O', 'O', 'O', 'O', 'O', 'O', 'O', 'O', 'O'], 'tokens': ['Terrible', 'palace', 'and', 'not', 'community', 'center', 'at', 'all', '.', 'Staff', 'is', 'untrained', 'and', 'unprofessional', '.', 'Pools', 'are', 'dirty', '.', 'No', 'place', 'for', 'swimming', 'as', 'if', 'you', 'do', 'not', 'pay', 'for', 'private', 'lessons', 'your', 'kids', 'are', 'pushed', 'into', 'pool', 'corner', 'together', 'with', 'all', 'other', 'kids', '.', '…'], 'aspect': ['Staff', 'Pools'], 'position': [[9], [15]], 'sentiment': ['Negative', 'Negative'], 'probs': [[0.9983999133110046, 0.001339769922196865, 0.0002603467146400362], [0.9972741007804871, 0.0024882492143660784, 0.00023768332903273404]], 'confidence': [0.9984, 0.9973]} | M8: 1 | N8: =LEN(K8)-LEN(SUBSTITUTE(K8,"{",""))-1 -> 5 | O8: 2 | P8: =_xlfn.XLOOKUP(B8,'g1'!B:B,'g1'!R:R) -> 5 | Q8: =_xlfn.XLOOKUP(B8,'g2'!B:B,'g2'!U:U) -> 5 | R8: =_xlfn.XLOOKUP(B8,'g3'!B:B,'g3'!R:R) -> 4 | S8: =_xlfn.XLOOKUP(D8,'g4'!D:D,'g4'!N:N) -> 6 | T8: =$N8-P8 -> 0 | U8: =$N8-Q8 -> 0 | V8: =$N8-R8 -> 1 | W8: =$N8-S8 -> -1 | X8: [{'aspect': 'place', 'opinion': 'terrible', 'sentiment': 'negative'}, {'aspect': 'place', 'opinion': 'not community center', 'sentiment': 'negative'}, {'aspect': 'staff', 'opinion': 'untrained', 'sentiment': 'negative'}, {'aspect': 'staff', 'opinion': 'unprofessional', 'sentiment': 'negative'}, {'aspect': 'pools', 'opinion': 'dirty', 'sentiment': 'negative'}, {'aspect': 'public swimming', 'opinion': 'no space', 'sentiment': 'negative'}] | Y8: =FIND("[{",K8) -> 43 | Z8: =FIND("category",K8) -> 63 | AA8: =Z8-Y8-2 -> 18 | AB8: palace | AD8: =FIND("[{",X8) -> 1 | AE8: =FIND("opinion",X8) -> 23 | AF8: =AE8-AD8-2 -> 20 | AG8: place | AH8: =AB8=AG8 -> FALSE
A9: 1711 | B9: ChIJj-pnCuH0OSoR78MktwDsRpg | C9: Marie Armistead | D9: ChIJj-pnCuH0OSoR78MktwDsRpgMarie Armistead | E9: 3 | F9: 7 years ago | G9: Only flat space for a couple of larger caravans but plenty smaller or tent sites. Both flushing toilets and longdrops depending where you camp. Cold showers, no potable water. | H9: Lake Poorrarecup campsite | I9: 32952 | J9: 2018-10-12 | K9: {"overall_sentiment":"negative","aspects":[{"aspect":"larger caravan space","category":"space","sentiment":"negative","evidence_span":"a couple"},{"aspect":"tent sites","category":"space","sentiment":"positive","evidence_span":"plenty"},{"aspect":"toilets","category":"amenities","sentiment":"neutral","evidence_span":"flushing toilets"},{"aspect":"showers","category":"amenities","sentiment":"negative","evidence_span":"Cold showers"},{"aspect":"water","category":"amenities","sentiment":"negative","evidence_span":"no potable water"}]} | L9: {'sentence': 'Only flat space for a couple of larger caravans but plenty smaller or tent sites . Both flushing toilets and longdrops depending where you camp . Cold showers , no potable water .', 'IOB': ['O', 'O', 'O', 'O', 'O', 'O', 'O', 'O', 'O', 'O', 'O', 'O', 'O', 'O', 'O', 'O', 'O', 'O', 'B-ASP', 'O', 'O', 'O', 'O', 'O', 'O', 'O', 'O', 'B-ASP', 'O', 'O', 'O', 'B-ASP', 'O'], 'tokens': ['Only', 'flat', 'space', 'for', 'a', 'couple', 'of', 'larger', 'caravans', 'but', 'plenty', 'smaller', 'or', 'tent', 'sites', '.', 'Both', 'flushing', 'toilets', 'and', 'longdrops', 'depending', 'where', 'you', 'camp', '.', 'Cold', 'showers', ',', 'no', 'potable', 'water', '.'], 'aspect': ['toilets', 'showers', 'water'], 'position': [[18], [27], [31]], 'sentiment': ['Neutral', 'Negative', 'Negative'], 'probs': [[0.017098605632781982, 0.9823619723320007, 0.0005393867613747716], [0.998066246509552, 0.0013780453009530902, 0.000555767968762666], [0.9972375631332397, 0.0024370152968913317, 0.00032533612102270126]], 'confidence': [0.9824, 0.9981, 0.9972]} | M9: 1 | N9: =LEN(K9)-LEN(SUBSTITUTE(K9,"{",""))-1 -> 5 | O9: 3 | P9: =_xlfn.XLOOKUP(B9,'g1'!B:B,'g1'!R:R) -> 5 | Q9: =_xlfn.XLOOKUP(B9,'g2'!B:B,'g2'!U:U) -> 5 | R9: =_xlfn.XLOOKUP(B9,'g3'!B:B,'g3'!R:R) -> 4 | S9: =_xlfn.XLOOKUP(D9,'g4'!D:D,'g4'!N:N) -> 6 | T9: =$N9-P9 -> 0 | U9: =$N9-Q9 -> 0 | V9: =$N9-R9 -> 1 | W9: =$N9-S9 -> -1 | X9: [{'aspect': 'larger caravan sites', 'opinion': 'Only flat space for a couple of larger caravans', 'sentiment': 'negative'}, {'aspect': 'smaller/tent sites', 'opinion': 'plenty smaller or tent sites', 'sentiment': 'positive'}, {'aspect': 'flushing toilets', 'opinion': 'Both flushing toilets and longdrops depending where you camp', 'sentiment': 'neutral'}, {'aspect': 'longdrops', 'opinion': 'Both flushing toilets and longdrops depending where you camp', 'sentiment': 'neutral'}, {'aspect': 'cold showers', 'opinion': 'Cold showers', 'sentiment': 'negative'}, {'aspect': 'potable water', 'opinion': 'no potable water', 'sentiment': 'negative'}] | Y9: =FIND("[{",K9) -> 43 | Z9: =FIND("category",K9) -> 78 | AA9: =Z9-Y9-2 -> 33 | AB9: caravan space | AD9: =FIND("[{",X9) -> 1 | AE9: =FIND("opinion",X9) -> 38 | AF9: =AE9-AD9-2 -> 35 | AG9: larger caravan sites | AH9: =AB9=AG9 -> FALSE
A10: 644 | B10: ChIJXTcb9KJbkWsRUAoi11ujAg8 | C10: JG R | D10: ChIJXTcb9KJbkWsRUAoi11ujAg8JG R | E10: 5 | F10: a year ago | G10: Favorite spot to do some trail runs. Beautiful, quiet and near the city. Love it. Lots of wildlife, too :koala::Tongue_sticking_out_cheeky_playful_or_blowing_a_raspberry:ir:Tongue_sticking_out_cheeky_playful_or_blowing_a_raspberry::parrot: … | H10: Whites Hill Reserve | I10: 1842 | J10: 2024-10-10 | K10: {"overall_sentiment":"positive","aspects":[{"aspect":"trail","category":"activity","sentiment":"positive","evidence_span":"trail runs"},{"aspect":"scenery","category":"environment","sentiment":"positive","evidence_span":"Beautiful"},{"aspect":"quiet","category":"ambiance","sentiment":"positive","evidence_span":"quiet"},{"aspect":"location","category":"location","sentiment":"positive","evidence_span":"near the city"},{"aspect":"wildlife","category":"nature","sentiment":"positive","evidence_span":"wildlife"}]} | L10: {'sentence': 'Favorite spot to do some trail runs . Beautiful , quiet and near the city . Love it . Lots of wildlife , too : koala : : Tongue _ sticking _ out _ cheeky _ playful _ or _ blowing _ a _ raspberry : ir : Tongue _ sticking _ out _ cheeky _ playful _ or _ blowing _ a _ raspberry : : parrot : …', 'IOB': ['O', 'B-ASP', 'O', 'O', 'O', 'O', 'O', 'O', 'O', 'O', 'O', 'O', 'O', 'O', 'O', 'O', 'O', 'O', 'O', 'O', 'O', 'O', 'O', 'O', 'O', 'O', 'O', 'O', 'O', 'O', 'O', 'O', 'O', 'O', 'O', 'O', 'O', 'O', 'O', 'O', 'O', 'O', 'O', 'O', 'O', 'O', 'O', 'O', 'O', 'O', 'O', 'O', 'O', 'O', 'O', 'O', 'O', 'O', 'O', 'O', 'O', 'O', 'O', 'O', 'O', 'O', 'O', 'O', 'O', 'O'], 'tokens': ['Favorite', 'spot', 'to', 'do', 'some', 'trail', 'runs', '.', 'Beautiful', ',', 'quiet', 'and', 'near', 'the', 'city', '.', 'Love', 'it', '.', 'Lots', 'of', 'wildlife', ',', 'too', ':', 'koala', ':', ':', 'Tongue', '_', 'sticking', '_', 'out', '_', 'cheeky', '_', 'playful', '_', 'or', '_', 'blowing', '_', 'a', '_', 'raspberry', ':', 'ir', ':', 'Tongue', '_', 'sticking', '_', 'out', '_', 'cheeky', '_', 'playful', '_', 'or', '_', 'blowing', '_', 'a', '_', 'raspberry', ':', ':', 'parrot', ':', '…'], 'aspect': ['spot'], 'position': [[1]], 'sentiment': ['Positive'], 'probs': [[0.0003489186055958271, 0.0006280795205384493, 0.9990229606628418]], 'confidence': [0.999]} | M10: 1 | N10: =LEN(K10)-LEN(SUBSTITUTE(K10,"{",""))-1 -> 5 | O10: 1 | P10: =_xlfn.XLOOKUP(B10,'g1'!B:B,'g1'!R:R) -> 5 | Q10: =_xlfn.XLOOKUP(B10,'g2'!B:B,'g2'!U:U) -> 5 | R10: =_xlfn.XLOOKUP(B10,'g3'!B:B,'g3'!R:R) -> 4 | S10: =_xlfn.XLOOKUP(D10,'g4'!D:D,'g4'!N:N) -> 6 | T10: =$N10-P10 -> 0 | U10: =$N10-Q10 -> 0 | V10: =$N10-R10 -> 1 | W10: =$N10-S10 -> -1 | X10: [{'aspect': 'trails', 'opinion': 'favorite', 'sentiment': 'positive'}, {'aspect': 'wildlife', 'opinion': 'lots of', 'sentiment': 'positive'}, {'aspect': 'scenery', 'opinion': 'beautiful', 'sentiment': 'positive'}, {'aspect': 'ambience', 'opinion': 'quiet', 'sentiment': 'positive'}, {'aspect': 'location', 'opinion': 'near the city', 'sentiment': 'positive'}, {'aspect': 'overall experience', 'opinion': 'love it', 'sentiment': 'positive'}] | Y10: =FIND("[{",K10) -> 43 | Z10: =FIND("category",K10) -> 63 | AA10: =Z10-Y10-2 -> 18 | AB10: trail runs | AD10: =FIND("[{",X10) -> 1 | AE10: =FIND("opinion",X10) -> 24 | AF10: =AE10-AD10-2 -> 21 | AG10: trails | AH10: =AB10=AG10 -> FALSE
A11: 679 | B11: ChIJS9ZKpBU81moRtCCzzU2_fcA | C11: Daniel YANG | D11: ChIJS9ZKpBU81moRtCCzzU2_fcADaniel YANG | E11: 3 | F11: 7 years ago | G11: Not great place for kids birthday party. The host is not experienced for kids party, everything is very slow, food, party organize, birthday cake serve. Very noisy in function room, it's a big function room to share with other parties, one … | H11: Zone Bowling Castle Hill | I11: 1374 | J11: 2018-10-12 | K11: {"overall_sentiment":"negative","aspects":[{"aspect":"host","category":"service","sentiment":"negative","evidence_span":"not experienced"},{"aspect":"food","category":"food","sentiment":"negative","evidence_span":"food"},{"aspect":"organization","category":"service","sentiment":"negative","evidence_span":"party organize"},{"aspect":"cake serve","category":"food","sentiment":"negative","evidence_span":"birthday cake serve"},{"aspect":"noise","category":"ambience","sentiment":"negative","evidence_span":"Very noisy"}]} | L11: {'sentence': "Not great place for kids birthday party . The host is not experienced for kids party , everything is very slow , food , party organize , birthday cake serve . Very noisy in function room , it ' s a big function room to share with other parties , one …", 'IOB': ['O', 'O', 'O', 'O', 'O', 'O', 'O', 'O', 'O', 'B-ASP', 'O', 'O', 'O', 'O', 'O', 'O', 'O', 'O', 'O', 'O', 'O', 'O', 'B-ASP', 'O', 'O', 'O', 'O', 'O', 'O', 'O', 'O', 'O', 'O', 'O', 'O', 'B-ASP', 'O', 'O', 'O', 'O', 'O', 'O', 'O', 'O', 'O', 'O', 'O', 'O', 'O', 'O', 'O', 'O'], 'tokens': ['Not', 'great', 'place', 'for', 'kids', 'birthday', 'party', '.', 'The', 'host', 'is', 'not', 'experienced', 'for', 'kids', 'party', ',', 'everything', 'is', 'very', 'slow', ',', 'food', ',', 'party', 'organize', ',', 'birthday', 'cake', 'serve', '.', 'Very', 'noisy', 'in', 'function', 'room', ',', 'it', "'", 's', 'a', 'big', 'function', 'room', 'to', 'share', 'with', 'other', 'parties', ',', 'one', '…'], 'aspect': ['host', 'food', 'room'], 'position': [[9], [22], [35]], 'sentiment': ['Negative', 'Negative', 'Negative'], 'probs': [[0.9945231676101685, 0.005103238858282566, 0.0003736235958058387], [0.8989600539207458, 0.10058768838644028, 0.0004521906084846705], [0.9865661263465881, 0.011451512575149536, 0.0019823985639959574]], 'confidence': [0.9945, 0.899, 0.9866]} | M11: 1 | N11: =LEN(K11)-LEN(SUBSTITUTE(K11,"{",""))-1 -> 5 | O11: 3 | P11: =_xlfn.XLOOKUP(B11,'g1'!B:B,'g1'!R:R) -> 6 | Q11: =_xlfn.XLOOKUP(B11,'g2'!B:B,'g2'!U:U) -> 6 | R11: =_xlfn.XLOOKUP(B11,'g3'!B:B,'g3'!R:R) -> 4 | S11: =_xlfn.XLOOKUP(D11,'g4'!D:D,'g4'!N:N) -> 6 | T11: =$N11-P11 -> -1 | U11: =$N11-Q11 -> -1 | V11: =$N11-R11 -> 1 | W11: =$N11-S11 -> -1 | X11: [{'aspect': 'host', 'opinion': 'not experienced', 'sentiment': 'negative'}, {'aspect': 'service speed', 'opinion': 'very slow', 'sentiment': 'negative'}, {'aspect': 'function room', 'opinion': 'very noisy', 'sentiment': 'negative'}, {'aspect': 'kids birthday party', 'opinion': 'not great', 'sentiment': 'negative'}, {'aspect': 'party organization', 'opinion': 'very slow', 'sentiment': 'negative'}, {'aspect': 'birthday cake service', 'opinion': 'very slow', 'sentiment': 'negative'}] | Y11: =FIND("[{",K11) -> 43 | Z11: =FIND("category",K11) -> 62 | AA11: =Z11-Y11-2 -> 17 | AB11: host | AD11: =FIND("[{",X11) -> 1 | AE11: =FIND("opinion",X11) -> 22 | AF11: =AE11-AD11-2 -> 19 | AG11: host | AH11: =AB11=AG11 -> TRUE
A12: 698 | B12: ChIJ16bsf211wmsRULU9xLIf--A | C12: Sam “Sam” Sam | D12: ChIJ16bsf211wmsRULU9xLIf--ASam “Sam” Sam | E12: 3 | F12: 5 years ago | G12: Very beautiful and clean. Almost, covered with huge trees. Not recommended dusk time, as mosquitos are very active specially when it's not breezy. Good for family and friends gathering. Spacious car park. | H12: Barney Point Beach | I12: 13063 | J12: 2020-10-11 | K12: {"overall_sentiment":"positive","aspects":[{"aspect":"beauty","category":"aesthetics","sentiment":"positive","evidence_span":"beautiful"},{"aspect":"cleanliness","category":"cleanliness","sentiment":"positive","evidence_span":"clean"},{"aspect":"mosquitos","category":"pests","sentiment":"negative","evidence_span":"mosquitos"},{"aspect":"family gatherings","category":"suitability","sentiment":"positive","evidence_span":"Good for family"},{"aspect":"parking","category":"parking","sentiment":"positive","evidence_span":"Spacious car park"}]} | L12: {'sentence': "Very beautiful and clean . Almost , covered with huge trees . Not recommended dusk time , as mosquitos are very active specially when it ' s not breezy . Good for family and friends gathering . Spacious car park .", 'IOB': ['O', 'O', 'O', 'O', 'O', 'O', 'O', 'O', 'O', 'O', 'O', 'O', 'O', 'O', 'O', 'O', 'O', 'O', 'O', 'O', 'O', 'O', 'O', 'O', 'O', 'O', 'O', 'O', 'O', 'O', 'O', 'O', 'O', 'O', 'O', 'O', 'O', 'O', 'O', 'B-ASP', 'O'], 'tokens': ['Very', 'beautiful', 'and', 'clean', '.', 'Almost', ',', 'covered', 'with', 'huge', 'trees', '.', 'Not', 'recommended', 'dusk', 'time', ',', 'as', 'mosquitos', 'are', 'very', 'active', 'specially', 'when', 'it', "'", 's', 'not', 'breezy', '.', 'Good', 'for', 'family', 'and', 'friends', 'gathering', '.', 'Spacious', 'car', 'park', '.'], 'aspect': ['park'], 'position': [[39]], 'sentiment': ['Positive'], 'probs': [[0.00037158484337851405, 0.0003445502952672541, 0.9992839694023132]], 'confidence': [0.9993]} | M12: 1 | N12: 5 | O12: 1 | P12: =_xlfn.XLOOKUP(B12,'g1'!B:B,'g1'!R:R) -> 8 | Q12: =_xlfn.XLOOKUP(B12,'g2'!B:B,'g2'!U:U) -> 8 | R12: =_xlfn.XLOOKUP(B12,'g3'!B:B,'g3'!R:R) -> 5 | S12: =_xlfn.XLOOKUP(D12,'g4'!D:D,'g4'!N:N) -> 6 | T12: =$N12-P12 -> -3 | U12: =$N12-Q12 -> -3 | V12: =$N12-R12 -> 0 | W12: =$N12-S12 -> -1 | X12: [{'aspect': 'beauty', 'opinion': 'Very beautiful', 'sentiment': 'positive'}, {'aspect': 'clean', 'opinion': 'clean', 'sentiment': 'positive'}, {'aspect': 'trees', 'opinion': 'covered with huge trees', 'sentiment': 'positive'}, {'aspect': 'mosquitoes', 'opinion': "very active specially when it's not breezy", 'sentiment': 'negative'}, {'aspect': 'family and friends gathering', 'opinion': 'Good for', 'sentiment': 'positive'}, {'aspect': 'car park', 'opinion': 'Spacious', 'sentiment': 'positive'}] | Y12: =FIND("[{",K12) -> 43 | Z12: =FIND("category",K12) -> 64 | AA12: =Z12-Y12-2 -> 19 | AB12: beauty | AD12: =FIND("[{",X12) -> 1 | AE12: =FIND("opinion",X12) -> 24 | AF12: =AE12-AD12-2 -> 21 | AG12: beauty | AH12: =AB12=AG12 -> TRUE
A13: 744 | B13: ChIJT6u_11tRDWsR8Jzy-Wh9AQ8 | C13: Milena Lozanova | D13: ChIJT6u_11tRDWsR8Jzy-Wh9AQ8Milena Lozanova | E13: 5 | F13: 7 years ago | G13: Love hiking there - the bushland meets rivers and creeks makes for great views and variety! Plenty of bushwalking tracks. | H13: Ku-ring-gai Chase National Park | I13: 426 | J13: 2018-10-12 | K13: {"overall_sentiment":"positive","aspects":[{"aspect":"hiking","category":"activity","sentiment":"positive","evidence_span":"Love hiking"},{"aspect":"views","category":"scenery","sentiment":"positive","evidence_span":"great views"},{"aspect":"variety","category":"diversity","sentiment":"positive","evidence_span":"variety"},{"aspect":"tracks","category":"trail","sentiment":"positive","evidence_span":"bushwalking tracks"}]} | L13: {'sentence': 'Love hiking there - the bushland meets rivers and creeks makes for great views and variety ! Plenty of bushwalking tracks .', 'IOB': ['O', 'O', 'O', 'O', 'O', 'O', 'O', 'O', 'O', 'O', 'O', 'O', 'O', 'B-ASP', 'O', 'O', 'O', 'O', 'O', 'O', 'O', 'O'], 'tokens': ['Love', 'hiking', 'there', '-', 'the', 'bushland', 'meets', 'rivers', 'and', 'creeks', 'makes', 'for', 'great', 'views', 'and', 'variety', '!', 'Plenty', 'of', 'bushwalking', 'tracks', '.'], 'aspect': ['views'], 'position': [[13]], 'sentiment': ['Positive'], 'probs': [[0.00015378743410110474, 0.0007074762252159417, 0.9991387128829956]], 'confidence': [0.9991]} | M13: 1 | N13: =LEN(K13)-LEN(SUBSTITUTE(K13,"{",""))-1 -> 4 | O13: 1 | P13: =_xlfn.XLOOKUP(B13,'g1'!B:B,'g1'!R:R) -> 4 | Q13: =_xlfn.XLOOKUP(B13,'g2'!B:B,'g2'!U:U) -> 4 | R13: =_xlfn.XLOOKUP(B13,'g3'!B:B,'g3'!R:R) -> 2 | S13: =_xlfn.XLOOKUP(D13,'g4'!D:D,'g4'!N:N) -> 6 | T13: =$N13-P13 -> 0 | U13: =$N13-Q13 -> 0 | V13: =$N13-R13 -> 2 | W13: =$N13-S13 -> -2 | X13: [{'aspect': 'hiking', 'opinion': 'Love hiking', 'sentiment': 'positive'}, {'aspect': 'bushland, rivers and creeks', 'opinion': 'meets rivers and creeks makes for great views and variety', 'sentiment': 'positive'}, {'aspect': 'bushland', 'opinion': 'meets rivers and creeks makes for great views and variety', 'sentiment': 'positive'}, {'aspect': 'rivers', 'opinion': 'meets rivers and creeks makes for great views and variety', 'sentiment': 'positive'}, {'aspect': 'creeks', 'opinion': 'meets rivers and creeks makes for great views and variety', 'sentiment': 'positive'}, {'aspect': 'bushwalking tracks', 'opinion': 'Plenty of bushwalking tracks', 'sentiment': 'positive'}] | Y13: =FIND("[{",K13) -> 43 | Z13: =FIND("category",K13) -> 64 | AA13: =Z13-Y13-2 -> 19 | AB13: hiking | AD13: =FIND("[{",X13) -> 1 | AE13: =FIND("opinion",X13) -> 24 | AF13: =AE13-AD13-2 -> 21 | AG13: hiking | AH13: =AB13=AG13 -> TRUE
A14: 1030 | B14: ChIJYdTsfgysEmsR183dKkF4AGs | C14: XOZTCATPREZ | D14: ChIJYdTsfgysEmsR183dKkF4AGsXOZTCATPREZ | E14: 3 | F14: 6 years ago | G14: Toxicly busy and shocking parking, especially the cost. Go to a good beach with waves instead. So much money for flat water....... It's like alcohol free beer! Totally overrated! | H14: Balmoral Beach | I14: 446 | J14: 2019-10-12 | K14: {"overall_sentiment":"negative","aspects":[{"aspect":"crowd","category":"crowding","sentiment":"negative","evidence_span":"Toxicly busy"},{"aspect":"parking","category":"parking","sentiment":"negative","evidence_span":"shocking parking"},{"aspect":"cost","category":"price","sentiment":"negative","evidence_span":"cost"},{"aspect":"water","category":"water quality","sentiment":"negative","evidence_span":"flat water"}]} | L14: {'sentence': "Toxicly busy and shocking parking , especially the cost . Go to a good beach with waves instead . So much money for flat water . . . . . . . It ' s like alcohol free beer ! Totally overrated !", 'IOB': ['O', 'O', 'O', 'O', 'O', 'O', 'O', 'O', 'B-ASP', 'O', 'O', 'O', 'O', 'O', 'O', 'O', 'O', 'O', 'O', 'O', 'O', 'B-ASP', 'O', 'O', 'O', 'O', 'O', 'O', 'O', 'O', 'O', 'O', 'O', 'O', 'O', 'O', 'O', 'O', 'O', 'O', 'O', 'O', 'O'], 'tokens': ['Toxicly', 'busy', 'and', 'shocking', 'parking', ',', 'especially', 'the', 'cost', '.', 'Go', 'to', 'a', 'good', 'beach', 'with', 'waves', 'instead', '.', 'So', 'much', 'money', 'for', 'flat', 'water', '.', '.', '.', '.', '.', '.', '.', 'It', "'", 's', 'like', 'alcohol', 'free', 'beer', '!', 'Totally', 'overrated', '!'], 'aspect': ['cost', 'money'], 'position': [[8], [21]], 'sentiment': ['Negative', 'Negative'], 'probs': [[0.990211009979248, 0.001981730107218027, 0.007807331159710884], [0.9891184568405151, 0.0011727664386853576, 0.009708747267723083]], 'confidence': [0.9902, 0.9891]} | M14: 1 | N14: =LEN(K14)-LEN(SUBSTITUTE(K14,"{",""))-1 -> 4 | O14: 2 | P14: =_xlfn.XLOOKUP(B14,'g1'!B:B,'g1'!R:R) -> 5 | Q14: =_xlfn.XLOOKUP(B14,'g2'!B:B,'g2'!U:U) -> 3 | R14: =_xlfn.XLOOKUP(B14,'g3'!B:B,'g3'!R:R) -> 3 | S14: =_xlfn.XLOOKUP(D14,'g4'!D:D,'g4'!N:N) -> 6 | T14: =$N14-P14 -> -1 | U14: =$N14-Q14 -> 1 | V14: =$N14-R14 -> 1 | W14: =$N14-S14 -> -2 | X14: [{'aspect': 'busy', 'opinion': 'Toxicly busy', 'sentiment': 'negative'}, {'aspect': 'parking', 'opinion': 'shocking parking', 'sentiment': 'negative'}, {'aspect': 'cost', 'opinion': 'so much money', 'sentiment': 'negative'}, {'aspect': 'water', 'opinion': 'flat water', 'sentiment': 'neutral'}, {'aspect': 'waves', 'opinion': 'no waves', 'sentiment': 'neutral'}, {'aspect': 'value', 'opinion': 'Totally overrated', 'sentiment': 'negative'}] | Y14: =FIND("[{",K14) -> 43 | Z14: =FIND("category",K14) -> 63 | AA14: =Z14-Y14-2 -> 18 | AB14: crowd | AD14: =FIND("[{",X14) -> 1 | AE14: =FIND("opinion",X14) -> 22 | AF14: =AE14-AD14-2 -> 19 | AG14: busy | AH14: =AB14=AG14 -> FALSE
A15: 1195 | B15: ChIJe2yce2nOpWsRavwI_SaXFNM | C15: Athfos | D15: ChIJe2yce2nOpWsRavwI_SaXFNMAthfos | E15: 3 | F15: 2 years ago | G15: A nice complex of pools and grassed outdoors area with one small Great Artesian Basin pool. Nice temperature around 40 degrees but was probably a little less. Not a completely natural water feed as the water is filtered and chlorinated because of the safety police. Opens 7.30am to Noon weekdays only. | H15: Mungindi Swimming Pool | I15: 39615 | J15: 2023-10-11 | K15: {"overall_sentiment":"positive","aspects":[{"aspect":"pool complex","category":"amenities","sentiment":"positive","evidence_span":"nice complex"},{"aspect":"temperature","category":"comfort","sentiment":"positive","evidence_span":"Nice temperature"},{"aspect":"water","category":"hygiene","sentiment":"negative","evidence_span":"filtered and chlorinated"},{"aspect":"hours","category":"access","sentiment":"neutral","evidence_span":"weekdays only"}]} | L15: {'sentence': 'A nice complex of pools and grassed outdoors area with one small Great Artesian Basin pool . Nice temperature around 40 degrees but was probably a little less . Not a completely natural water feed as the water is filtered and chlorinated because of the safety police . Opens 7 . 30am to Noon weekdays only .', 'IOB': ['O', 'O', 'O', 'O', 'O', 'O', 'O', 'O', 'B-ASP', 'O', 'O', 'O', 'O', 'O', 'O', 'O', 'O', 'O', 'B-ASP', 'O', 'O', 'O', 'O', 'O', 'O', 'O', 'O', 'O', 'O', 'O', 'O', 'O', 'O', 'O', 'O', 'O', 'O', 'O', 'O', 'O', 'O', 'O', 'O', 'O', 'O', 'O', 'O', 'O', 'O', 'O', 'O', 'O', 'O', 'O', 'O', 'O', 'O'], 'tokens': ['A', 'nice', 'complex', 'of', 'pools', 'and', 'grassed', 'outdoors', 'area', 'with', 'one', 'small', 'Great', 'Artesian', 'Basin', 'pool', '.', 'Nice', 'temperature', 'around', '40', 'degrees', 'but', 'was', 'probably', 'a', 'little', 'less', '.', 'Not', 'a', 'completely', 'natural', 'water', 'feed', 'as', 'the', 'water', 'is', 'filtered', 'and', 'chlorinated', 'because', 'of', 'the', 'safety', 'police', '.', 'Opens', '7', '.', '30am', 'to', 'Noon', 'weekdays', 'only', '.'], 'aspect': ['area', 'temperature'], 'position': [[8], [18]], 'sentiment': ['Neutral', 'Positive'], 'probs': [[0.0023743740748614073, 0.5699761509895325, 0.42764949798583984], [0.02284722961485386, 0.001875527435913682, 0.9752771854400635]], 'confidence': [0.57, 0.9753]} | M15: 1 | N15: 4 | O15: 2 | P15: =_xlfn.XLOOKUP(B15,'g1'!B:B,'g1'!R:R) -> 6 | Q15: =_xlfn.XLOOKUP(B15,'g2'!B:B,'g2'!U:U) -> 8 | R15: =_xlfn.XLOOKUP(B15,'g3'!B:B,'g3'!R:R) -> 4 | S15: =_xlfn.XLOOKUP(D15,'g4'!D:D,'g4'!N:N) -> 6 | T15: =$N15-P15 -> -2 | U15: =$N15-Q15 -> -4 | V15: =$N15-R15 -> 0 | W15: =$N15-S15 -> -2 | X15: [{'aspect': 'pool complex', 'opinion': 'A nice complex of pools', 'sentiment': 'positive'}, {'aspect': 'grassed outdoors area', 'opinion': 'nice grassed outdoors area', 'sentiment': 'positive'}, {'aspect': 'Great Artesian Basin pool', 'opinion': 'one small Great Artesian Basin pool', 'sentiment': 'neutral'}, {'aspect': 'water quality', 'opinion': 'water is filtered and chlorinated because of the safety police', 'sentiment': 'negative'}, {'aspect': 'operating hours', 'opinion': 'Opens 7.30am to Noon weekdays only', 'sentiment': 'negative'}, {'aspect': 'temperature', 'opinion': 'Nice temperature around 40 degrees but was probably a little less', 'sentiment': 'positive'}] | Y15: =FIND("[{",K15) -> 43 | Z15: =FIND("category",K15) -> 70 | AA15: =Z15-Y15-2 -> 25 | AB15: complex | AD15: =FIND("[{",X15) -> 1 | AE15: =FIND("opinion",X15) -> 30 | AF15: =AE15-AD15-2 -> 27 | AG15: pool complex | AH15: =AB15=AG15 -> FALSE
A16: 1367 | B16: ChIJBZmFK_tDkWsRb6hNhBgbJ-U | C16: Syed | D16: ChIJBZmFK_tDkWsRb6hNhBgbJ-USyed | E16: 5 | F16: 7 years ago | G16: Amazing place for people from any faith, colour or background. A very multi cultural environment. Buzzing with youth and kids. A great place for learning and development. A venue for humanitarian and social work. A unity centre in true sense. | H16: Australian Centre for Unity: Slacks Creek Mosque - IPDC QLD | I16: 15206 | J16: 2018-10-12 | K16: {"overall_sentiment":"positive","aspects":[{"aspect":"inclusivity","category":"culture","sentiment":"positive","evidence_span":"any faith"},{"aspect":"environment","category":"ambiance","sentiment":"positive","evidence_span":"multi cultural environment"},{"aspect":"youth","category":"audience","sentiment":"positive","evidence_span":"youth and kids"},{"aspect":"unity centre","category":"venue","sentiment":"positive","evidence_span":"unity centre"}]} | L16: {'sentence': 'Amazing place for people from any faith , colour or background . A very multi cultural environment . Buzzing with youth and kids . A great place for learning and development . A venue for humanitarian and social work . A unity centre in true sense .', 'IOB': ['O', 'B-ASP', 'O', 'O', 'O', 'O', 'O', 'O', 'O', 'O', 'O', 'O', 'O', 'O', 'O', 'O', 'B-ASP', 'O', 'O', 'O', 'O', 'O', 'O', 'O', 'O', 'O', 'O', 'O', 'O', 'O', 'O', 'O', 'O', 'O', 'O', 'O', 'O', 'O', 'O', 'O', 'O', 'O', 'O', 'O', 'O', 'O', 'O'], 'tokens': ['Amazing', 'place', 'for', 'people', 'from', 'any', 'faith', ',', 'colour', 'or', 'background', '.', 'A', 'very', 'multi', 'cultural', 'environment', '.', 'Buzzing', 'with', 'youth', 'and', 'kids', '.', 'A', 'great', 'place', 'for', 'learning', 'and', 'development', '.', 'A', 'venue', 'for', 'humanitarian', 'and', 'social', 'work', '.', 'A', 'unity', 'centre', 'in', 'true', 'sense', '.'], 'aspect': ['place', 'environment'], 'position': [[1], [16]], 'sentiment': ['Positive', 'Positive'], 'probs': [[0.00046748650493100286, 0.00039927742909640074, 0.999133288860321], [0.00022772210650146008, 0.00037490681279450655, 0.9993973970413208]], 'confidence': [0.9991, 0.9994]} | M16: 1 | N16: =LEN(K16)-LEN(SUBSTITUTE(K16,"{",""))-1 -> 4 | O16: 2 | P16: =_xlfn.XLOOKUP(B16,'g1'!B:B,'g1'!R:R) -> 6 | Q16: =_xlfn.XLOOKUP(B16,'g2'!B:B,'g2'!U:U) -> 5 | R16: =_xlfn.XLOOKUP(B16,'g3'!B:B,'g3'!R:R) -> 6 | S16: =_xlfn.XLOOKUP(D16,'g4'!D:D,'g4'!N:N) -> 6 | T16: =$N16-P16 -> -2 | U16: =$N16-Q16 -> -1 | V16: =$N16-R16 -> -2 | W16: =$N16-S16 -> -2 | X16: [{'aspect': 'inclusivity', 'opinion': 'Amazing place for people from any faith, colour or background', 'sentiment': 'positive'}, {'aspect': 'multicultural environment', 'opinion': 'A very multi cultural environment', 'sentiment': 'positive'}, {'aspect': 'youth and kids', 'opinion': 'Buzzing with youth and kids', 'sentiment': 'positive'}, {'aspect': 'learning and development', 'opinion': 'a great place for learning and development', 'sentiment': 'positive'}, {'aspect': 'humanitarian and social work', 'opinion': 'a venue for humanitarian and social work', 'sentiment': 'positive'}, {'aspect': 'unity centre', 'opinion': 'A unity centre in true sense', 'sentiment': 'positive'}] | Y16: =FIND("[{",K16) -> 43 | Z16: =FIND("category",K16) -> 69 | AA16: =Z16-Y16-2 -> 24 | AB16: diversity | AD16: =FIND("[{",X16) -> 1 | AE16: =FIND("opinion",X16) -> 29 | AF16: =AE16-AD16-2 -> 26 | AG16: inclusivity | AH16: =AB16=AG16 -> FALSE
A17: 1870 | B17: ChIJN0j6yrJQkWsR14GqlOLB00E | C17: Amanda Maslin | D17: ChIJN0j6yrJQkWsR14GqlOLB00EAmanda Maslin | E17: 3 | F17: 6 years ago | G17: A funky place and byo snacks and wine. Not a lot of space for either alongside paint/brushes. Also for $50, I would expect more instruction on how and what to paint. It's a very free-form, hands-off experience. The focus is more on socialising and listening to music/drinking while painting. | H17: Brush & Barrel | I17: 26184 | J17: 2019-10-12 | K17: {"overall_sentiment":"negative","aspects":[{"aspect":"ambiance","category":"ambiance","sentiment":"positive","evidence_span":"funky place"},{"aspect":"space","category":"facility","sentiment":"negative","evidence_span":"Not a lot"},{"aspect":"instruction","category":"service","sentiment":"negative","evidence_span":"more instruction"},{"aspect":"experience","category":"format","sentiment":"negative","evidence_span":"hands-off"}]} | L17: {'sentence': "A funky place and byo snacks and wine . Not a lot of space for either alongside paint / brushes . Also for $ 50 , I would expect more instruction on how and what to paint . It ' s a very free - form , hands - off experience . The focus is more on socialising and listening to music / drinking while painting .", 'IOB': ['O', 'O', 'B-ASP', 'O', 'O', 'O', 'O', 'B-ASP', 'O', 'O', 'O', 'O', 'O', 'O', 'O', 'O', 'O', 'O', 'O', 'O', 'O', 'O', 'O', 'O', 'O', 'O', 'O', 'O', 'O', 'O', 'O', 'O', 'O', 'O', 'O', 'O', 'O', 'O', 'O', 'O', 'O', 'O', 'O', 'O', 'O', 'O', 'O', 'O', 'O', 'O', 'O', 'O', 'O', 'O', 'O', 'O', 'O', 'O', 'O', 'O', 'O', 'O', 'O', 'O', 'O', 'O', 'O'], 'tokens': ['A', 'funky', 'place', 'and', 'byo', 'snacks', 'and', 'wine', '.', 'Not', 'a', 'lot', 'of', 'space', 'for', 'either', 'alongside', 'paint', '/', 'brushes', '.', 'Also', 'for', '$', '50', ',', 'I', 'would', 'expect', 'more', 'instruction', 'on', 'how', 'and', 'what', 'to', 'paint', '.', 'It', "'", 's', 'a', 'very', 'free', '-', 'form', ',', 'hands', '-', 'off', 'experience', '.', 'The', 'focus', 'is', 'more', 'on', 'socialising', 'and', 'listening', 'to', 'music', '/', 'drinking', 'while', 'painting', '.'], 'aspect': ['place', 'wine'], 'position': [[2], [7]], 'sentiment': ['Positive', 'Neutral'], 'probs': [[0.0022751218639314175, 0.002708323998376727, 0.9950165152549744], [0.002928764559328556, 0.9933831095695496, 0.003688059514388442]], 'confidence': [0.995, 0.9934]} | M17: 1 | N17: =LEN(K17)-LEN(SUBSTITUTE(K17,"{",""))-1 -> 4 | O17: 2 | P17: =_xlfn.XLOOKUP(B17,'g1'!B:B,'g1'!R:R) -> 7 | Q17: =_xlfn.XLOOKUP(B17,'g2'!B:B,'g2'!U:U) -> 6 | R17: =_xlfn.XLOOKUP(B17,'g3'!B:B,'g3'!R:R) -> 6 | S17: =_xlfn.XLOOKUP(D17,'g4'!D:D,'g4'!N:N) -> 6 | T17: =$N17-P17 -> -3 | U17: =$N17-Q17 -> -2 | V17: =$N17-R17 -> -2 | W17: =$N17-S17 -> -2 | X17: [{'aspect': 'ambiance', 'opinion': 'funky', 'sentiment': 'positive'}, {'aspect': 'space', 'opinion': 'not a lot of space', 'sentiment': 'negative'}, {'aspect': 'instruction', 'opinion': 'more instruction on how and what to paint', 'sentiment': 'negative'}, {'aspect': 'experience', 'opinion': 'very free-form, hands-off experience', 'sentiment': 'negative'}, {'aspect': 'BYO policy', 'opinion': 'byo snacks and wine', 'sentiment': 'positive'}, {'aspect': 'price', 'opinion': '$50', 'sentiment': 'negative'}] | Y17: =FIND("[{",K17) -> 43 | Z17: =FIND("category",K17) -> 66 | AA17: =Z17-Y17-2 -> 21 | AB17: ambiance | AD17: =FIND("[{",X17) -> 1 | AE17: =FIND("opinion",X17) -> 26 | AF17: =AE17-AD17-2 -> 23 | AG17: ambiance | AH17: =AB17=AG17 -> TRUE
A18: 636 | B18: ChIJp4-myXZKzWoRhOrDuoaamaY | C18: Dawn Elizabeth Anderson | D18: ChIJp4-myXZKzWoRhOrDuoaamaYDawn Elizabeth Anderson | E18: 5 | F18: 6 years ago | G18: Beautiful nature walks, we saw baby emu's, koalas and a snake! Vegetation and sounds of the bush were lovely. | H18: Tower Hill Park Boundary | I18: 35482 | J18: 2019-10-12 | K18: {"overall_sentiment":"positive","aspects":[{'aspect': "baby emu's","category":"environment", 'opinion': 'saw', 'sentiment': 'positive'}, {'aspect': 'koalas',"category":"environment", 'opinion': 'saw', 'sentiment': 'positive'}, {'aspect': 'a snake',"category":"environment", 'opinion': 'saw', 'sentiment': 'positive'},{"aspect":"nature walks","category":"activities","sentiment":"positive","evidence_span":"Beautiful nature walks"},{"aspect":"vegetation","category":"environment","sentiment":"positive","evidence_span":"were lovely"},{"aspect":"sounds","category":"ambiance","sentiment":"positive","evidence_span":"were lovely"}]} | L18: {'sentence': "Beautiful nature walks , we saw baby emu ' s , koalas and a snake ! Vegetation and sounds of the bush were lovely .", 'IOB': ['O', 'B-ASP', 'O', 'O', 'O', 'O', 'O', 'O', 'O', 'O', 'O', 'O', 'O', 'O', 'B-ASP', 'O', 'O', 'O', 'B-ASP', 'O', 'O', 'O', 'O', 'O', 'O'], 'tokens': ['Beautiful', 'nature', 'walks', ',', 'we', 'saw', 'baby', 'emu', "'", 's', ',', 'koalas', 'and', 'a', 'snake', '!', 'Vegetation', 'and', 'sounds', 'of', 'the', 'bush', 'were', 'lovely', '.'], 'aspect': ['nature', 'snake', 'sounds'], 'position': [[1], [14], [18]], 'sentiment': ['Positive', 'Neutral', 'Positive'], 'probs': [[0.0002940867852885276, 0.0002645606582518667, 0.9994413256645203], [0.0002947285247500986, 0.9736195802688599, 0.026085680350661278], [0.0003183631633874029, 0.019295671954751015, 0.980385959148407]], 'confidence': [0.9994, 0.9736, 0.9804]} | N18: =LEN(K18)-LEN(SUBSTITUTE(K18,"{",""))-1 -> 6 | O18: 3 | P18: =_xlfn.XLOOKUP(B18,'g1'!B:B,'g1'!R:R) -> 3 | Q18: =_xlfn.XLOOKUP(B18,'g2'!B:B,'g2'!U:U) -> 3 | R18: =_xlfn.XLOOKUP(B18,'g3'!B:B,'g3'!R:R) -> 3 | S18: =_xlfn.XLOOKUP(D18,'g4'!D:D,'g4'!N:N) -> 6 | T18: =$N18-P18 -> 3 | U18: =$N18-Q18 -> 3 | V18: =$N18-R18 -> 3 | W18: =$N18-S18 -> 0 | X18: [{'aspect': "baby emu's", 'opinion': 'saw', 'sentiment': 'positive'}, {'aspect': 'koalas', 'opinion': 'saw', 'sentiment': 'positive'}, {'aspect': 'a snake', 'opinion': 'saw', 'sentiment': 'positive'}, {'aspect': 'vegetation', 'opinion': 'lovely', 'sentiment': 'positive'}, {'aspect': 'sounds of the bush', 'opinion': 'lovely', 'sentiment': 'positive'}, {'aspect': 'nature walks', 'opinion': 'Beautiful', 'sentiment': 'positive'}] | Y18: =FIND("[{",K18) -> 43 | Z18: =FIND("category",K18) -> 69 | AA18: =Z18-Y18-2 -> 24 | AB18: nature walks | AD18: =FIND("[{",X18) -> 1 | AE18: =FIND("opinion",X18) -> 28 | AF18: =AE18-AD18-2 -> 25 | AG18: baby emu's | AH18: =AB18=AG18 -> FALSE
A19: 1837 | B19: ChIJj_UC5JnPsGoRQOi5RVU2Aw8 | C19: Vahid Ch. | D19: ChIJj_UC5JnPsGoRQOi5RVU2Aw8Vahid Ch. | E19: 4 | F19: 3 years ago | G19: Nice small park in a quiet neighbourhood, one BBQ, toilet and sitting area for small gatherings. Fenced playground for your peace of mind and your little ones | H19: Everard Park Reserve | I19: 30637 | J19: 2022-10-11 | K19: {"overall_sentiment":"positive","aspects":[{"aspect":"park","category":"environment","sentiment":"positive","evidence_span":"Nice small park"},{"aspect":"neighbourhood","category":"location","sentiment":"positive","evidence_span":"quiet neighbourhood"},{"aspect":"playground","category":"safety","sentiment":"positive","evidence_span":"Fenced playground"}, {'aspect': 'sitting area',"category":'facility', 'opinion': 'for small gatherings', 'sentiment': 'neutral'}, {'aspect': 'BBQ',"category":'facility', 'opinion': 'one BBQ', 'sentiment': 'neutral'}, {'aspect': 'toilet',"category":'facility', 'opinion': 'toilet', 'sentiment': 'neutral'}]} | L19: {'sentence': 'Nice small park in a quiet neighbourhood , one BBQ , toilet and sitting area for small gatherings . Fenced playground for your peace of mind and your little ones', 'IOB': ['O', 'O', 'B-ASP', 'O', 'O', 'O', 'O', 'O', 'O', 'B-ASP', 'O', 'B-ASP', 'O', 'O', 'B-ASP', 'O', 'O', 'O', 'O', 'O', 'B-ASP', 'O', 'O', 'O', 'O', 'O', 'O', 'O', 'O', 'O'], 'tokens': ['Nice', 'small', 'park', 'in', 'a', 'quiet', 'neighbourhood', ',', 'one', 'BBQ', ',', 'toilet', 'and', 'sitting', 'area', 'for', 'small', 'gatherings', '.', 'Fenced', 'playground', 'for', 'your', 'peace', 'of', 'mind', 'and', 'your', 'little', 'ones'], 'aspect': ['park', 'BBQ', 'toilet', 'area', 'playground'], 'position': [[2], [9], [11], [14], [20]], 'sentiment': ['Positive', 'Neutral', 'Neutral', 'Neutral', 'Neutral'], 'probs': [[0.0013663839781656861, 0.0001918409689096734, 0.998441755771637], [0.0004520551301538944, 0.9741700887680054, 0.025377783924341202], [0.00041303879697807133, 0.9986251592636108, 0.0009618206531740725], [0.0006251587183214724, 0.998891294002533, 0.00048357335617765784], [0.00036160449963063, 0.9991689920425415, 0.00046939204912632704]], 'confidence': [0.9984, 0.9742, 0.9986, 0.9989, 0.9992]} | M19: 1 | N19: =LEN(K19)-LEN(SUBSTITUTE(K19,"{",""))-1 -> 6 | O19: 5 | P19: =_xlfn.XLOOKUP(B19,'g1'!B:B,'g1'!R:R) -> 6 | Q19: =_xlfn.XLOOKUP(B19,'g2'!B:B,'g2'!U:U) -> 6 | R19: =_xlfn.XLOOKUP(B19,'g3'!B:B,'g3'!R:R) -> 3 | S19: =_xlfn.XLOOKUP(D19,'g4'!D:D,'g4'!N:N) -> 6 | T19: =$N19-P19 -> 0 | U19: =$N19-Q19 -> 0 | V19: =$N19-R19 -> 3 | W19: =$N19-S19 -> 0 | X19: [{'aspect': 'park', 'opinion': 'Nice small', 'sentiment': 'positive'}, {'aspect': 'neighbourhood', 'opinion': 'quiet', 'sentiment': 'positive'}, {'aspect': 'sitting area', 'opinion': 'for small gatherings', 'sentiment': 'neutral'}, {'aspect': 'BBQ', 'opinion': 'one BBQ', 'sentiment': 'neutral'}, {'aspect': 'toilet', 'opinion': 'toilet', 'sentiment': 'neutral'}, {'aspect': 'playground', 'opinion': 'Fenced playground', 'sentiment': 'positive'}] | Y19: =FIND("[{",K19) -> 43 | Z19: =FIND("category",K19) -> 62 | AA19: =Z19-Y19-2 -> 17 | AB19: park | AD19: =FIND("[{",X19) -> 1 | AE19: =FIND("opinion",X19) -> 22 | AF19: =AE19-AD19-2 -> 19 | AG19: park | AH19: =AB19=AG19 -> TRUE
A20: 627 | B20: ChIJQZVwKfMPkWsRNsBv56xfPsM | C20: Nicholas Abela | D20: ChIJQZVwKfMPkWsRNsBv56xfPsMNicholas Abela | E20: 1 | F20: 2 years ago | G20: Staff attitude was horrible as was service. Atmosphere was just horrid. It was like being in a huge food hall at local shopping centre. On a better note the food i had was not bade but expensive. | H20: SOPO | I20: 1371 | J20: 2023-10-11 | K20: {"overall_sentiment":"negative","aspects":[{"aspect":"staff attitude","category":"service","sentiment":"negative","evidence_span":"horrible"},{"aspect":"service","category":"service","sentiment":"negative","evidence_span":"as was service"},{"aspect":"atmosphere","category":"ambience","sentiment":"negative","evidence_span":"horrid"},{"aspect":"food","category":"food","sentiment":"positive","evidence_span":"not bad"},{"aspect":"price","category":"price","sentiment":"negative","evidence_span":"expensive"}]} | L20: {'sentence': 'Staff attitude was horrible as was service . Atmosphere was just horrid . It was like being in a huge food hall at local shopping centre . On a better note the food i had was not bade but expensive .', 'IOB': ['B-ASP', 'I-ASP', 'O', 'O', 'O', 'O', 'B-ASP', 'O', 'B-ASP', 'O', 'O', 'O', 'O', 'O', 'O', 'O', 'O', 'O', 'O', 'O', 'B-ASP', 'I-ASP', 'O', 'O', 'O', 'O', 'O', 'O', 'O', 'O', 'O', 'O', 'B-ASP', 'O', 'O', 'O', 'O', 'O', 'O', 'O', 'O'], 'tokens': ['Staff', 'attitude', 'was', 'horrible', 'as', 'was', 'service', '.', 'Atmosphere', 'was', 'just', 'horrid', '.', 'It', 'was', 'like', 'being', 'in', 'a', 'huge', 'food', 'hall', 'at', 'local', 'shopping', 'centre', '.', 'On', 'a', 'better', 'note', 'the', 'food', 'i', 'had', 'was', 'not', 'bade', 'but', 'expensive', '.'], 'aspect': ['Staff attitude', 'service', 'Atmosphere', 'food hall', 'food'], 'position': [[0, 1], [6], [8], [20, 21], [32]], 'sentiment': ['Negative', 'Negative', 'Negative', 'Negative', 'Negative'], 'probs': [[0.9970870614051819, 0.002694027731195092, 0.00021899155399296433], [0.856944739818573, 0.13668952882289886, 0.006365782115608454], [0.8827004432678223, 0.11120660603046417, 0.006092906929552555], [0.9777281284332275, 0.0011842437088489532, 0.021087653934955597], [0.8227041959762573, 0.12092027813196182, 0.05637552589178085]], 'confidence': [0.9971, 0.8569, 0.8827, 0.9777, 0.8227]} | N20: 5 | O20: 5 | P20: =_xlfn.XLOOKUP(B20,'g1'!B:B,'g1'!R:R) -> 5 | Q20: =_xlfn.XLOOKUP(B20,'g2'!B:B,'g2'!U:U) -> 5 | R20: =_xlfn.XLOOKUP(B20,'g3'!B:B,'g3'!R:R) -> 5 | S20: =_xlfn.XLOOKUP(D20,'g4'!D:D,'g4'!N:N) -> 5 | T20: =$N20-P20 -> 0 | U20: =$N20-Q20 -> 0 | V20: =$N20-R20 -> 0 | W20: =$N20-S20 -> 0 | X20: [{'aspect': 'staff attitude', 'opinion': 'horrible', 'sentiment': 'negative'}, {'aspect': 'service', 'opinion': 'horrible', 'sentiment': 'negative'}, {'aspect': 'atmosphere', 'opinion': 'horrid', 'sentiment': 'negative'}, {'aspect': 'food', 'opinion': 'not bade', 'sentiment': 'positive'}, {'aspect': 'price', 'opinion': 'expensive', 'sentiment': 'negative'}] | Y20: =FIND("[{",K20) -> 43 | Z20: =FIND("category",K20) -> 72 | AA20: =Z20-Y20-2 -> 27 | AB20: staff attitude | AD20: =FIND("[{",X20) -> 1 | AE20: =FIND("opinion",X20) -> 32 | AF20: =AE20-AD20-2 -> 29 | AG20: staff attitude | AH20: =AB20=AG20 -> TRUE
A21: 1397 | B21: ChIJ6VM40ubGsGoR5a8l3qpP5eU | C21: Sarmistha Dutta Roy | D21: ChIJ6VM40ubGsGoR5a8l3qpP5eUSarmistha Dutta Roy | E21: 5 | F21: 2 years ago | G21: I did two occasions which was my Son’s birthday and my 40th Birthday,I am very happy and satisfied with their excellent customer service. Food and ambience was remarkable .Staff’s behaviour was very good. And special mention about the manager Mr. Pratik who organised it with super perfection. Highly recommend for any parties. | H21: Spice N Ice | I21: 6012 | J21: 2023-10-11 | K21: {"overall_sentiment":"positive","aspects":[{"aspect":"customer service","category":"service","sentiment":"positive","evidence_span":"excellent customer service"},{"aspect":"food","category":"food","sentiment":"positive","evidence_span":"remarkable"},{"aspect":"ambience","category":"ambience","sentiment":"positive","evidence_span":"remarkable"},{"aspect":"staff behaviour","category":"staff","sentiment":"positive","evidence_span":"very good"},{"aspect":"manager","category":"management","sentiment":"positive","evidence_span":"super perfection"}]} | L21: {'sentence': 'I did two occasions which was my Son ’ s birthday and my 40th Birthday , I am very happy and satisfied with their excellent customer service . Food and ambience was remarkable . Staff ’ s behaviour was very good . And special mention about the manager Mr . Pratik who organised it with super perfection . Highly recommend for any parties .', 'IOB': ['O', 'O', 'O', 'O', 'O', 'O', 'O', 'O', 'O', 'O', 'O', 'O', 'O', 'O', 'O', 'O', 'O', 'O', 'O', 'O', 'O', 'O', 'O', 'O', 'O', 'O', 'B-ASP', 'O', 'B-ASP', 'O', 'B-ASP', 'O', 'O', 'O', 'B-ASP', 'O', 'O', 'O', 'O', 'O', 'O', 'O', 'O', 'O', 'O', 'O', 'O', 'B-ASP', 'O', 'O', 'O', 'O', 'O', 'O', 'O', 'O', 'O', 'O', 'O', 'O', 'O', 'O', 'O', 'O'], 'tokens': ['I', 'did', 'two', 'occasions', 'which', 'was', 'my', 'Son', '’', 's', 'birthday', 'and', 'my', '40th', 'Birthday', ',', 'I', 'am', 'very', 'happy', 'and', 'satisfied', 'with', 'their', 'excellent', 'customer', 'service', '.', 'Food', 'and', 'ambience', 'was', 'remarkable', '.', 'Staff', '’', 's', 'behaviour', 'was', 'very', 'good', '.', 'And', 'special', 'mention', 'about', 'the', 'manager', 'Mr', '.', 'Pratik', 'who', 'organised', 'it', 'with', 'super', 'perfection', '.', 'Highly', 'recommend', 'for', 'any', 'parties', '.'], 'aspect': ['service', 'Food', 'ambience', 'Staff', 'manager'], 'position': [[26], [28], [30], [34], [47]], 'sentiment': ['Positive', 'Positive', 'Positive', 'Positive', 'Positive'], 'probs': [[0.0004093546303920448, 0.003927676472812891, 0.9956629872322083], [0.0004435003502294421, 0.005155280232429504, 0.9944012761116028], [0.0005674285930581391, 0.006381411571055651, 0.9930511713027954], [0.0007698565605096519, 0.005589633248746395, 0.9936406016349792], [0.0010483399964869022, 0.0010373021941632032, 0.9979143738746643]], 'confidence': [0.9957, 0.9944, 0.9931, 0.9936, 0.9979]} | N21: 5 | O21: 5 | P21: =_xlfn.XLOOKUP(B21,'g1'!B:B,'g1'!R:R) -> 5 | Q21: =_xlfn.XLOOKUP(B21,'g2'!B:B,'g2'!U:U) -> 5 | R21: =_xlfn.XLOOKUP(B21,'g3'!B:B,'g3'!R:R) -> 5 | S21: =_xlfn.XLOOKUP(D21,'g4'!D:D,'g4'!N:N) -> 5 | T21: =$N21-P21 -> 0 | U21: =$N21-Q21 -> 0 | V21: =$N21-R21 -> 0 | W21: =$N21-S21 -> 0 | X21: [{'aspect': 'customer service', 'opinion': 'excellent', 'sentiment': 'positive'}, {'aspect': 'food', 'opinion': 'remarkable', 'sentiment': 'positive'}, {'aspect': 'ambience', 'opinion': 'remarkable', 'sentiment': 'positive'}, {'aspect': 'staff behavior', 'opinion': 'very good', 'sentiment': 'positive'}, {'aspect': 'manager', 'opinion': 'super perfection', 'sentiment': 'positive'}] | Y21: =FIND("[{",K21) -> 43 | Z21: =FIND("category",K21) -> 74 | AA21: =Z21-Y21-2 -> 29 | AB21: customer service | AD21: =FIND("[{",X21) -> 1 | AE21: =FIND("opinion",X21) -> 34 | AF21: =AE21-AD21-2 -> 31 | AG21: customer service | AH21: =AB21=AG21 -> TRUE
A22: 676 | B22: ChIJM4abjXIFkWsRjcn2PnqfpWA | C22: Fiona Polo | D22: ChIJM4abjXIFkWsRjcn2PnqfpWAFiona Polo | E22: 5 | F22: 6 years ago | G22: First time and the food was delicious! Meals are huge. Price is average. Interior is cool. Staff are very friendly and helpful. | H22: Steampunk Surfers Paradise | I22: 875 | J22: 2019-10-12 | K22: {"overall_sentiment":"positive","aspects":[{"aspect":"food","category":"food","sentiment":"positive","evidence_span":"food was delicious"},{"aspect":"meals","category":"food","sentiment":"positive","evidence_span":"Meals are huge"},{"aspect":"price","category":"price","sentiment":"neutral","evidence_span":"Price is average"},{"aspect":"interior","category":"ambience","sentiment":"positive","evidence_span":"Interior is cool"},{"aspect":"staff","category":"service","sentiment":"positive","evidence_span":"very friendly"}]} | L22: {'sentence': 'First time and the food was delicious ! Meals are huge . Price is average . Interior is cool . Staff are very friendly and helpful .', 'IOB': ['O', 'O', 'O', 'O', 'B-ASP', 'O', 'O', 'O', 'B-ASP', 'O', 'O', 'O', 'B-ASP', 'O', 'O', 'O', 'B-ASP', 'O', 'O', 'O', 'B-ASP', 'O', 'O', 'O', 'O', 'O', 'O'], 'tokens': ['First', 'time', 'and', 'the', 'food', 'was', 'delicious', '!', 'Meals', 'are', 'huge', '.', 'Price', 'is', 'average', '.', 'Interior', 'is', 'cool', '.', 'Staff', 'are', 'very', 'friendly', 'and', 'helpful', '.'], 'aspect': ['food', 'Meals', 'Price', 'Interior', 'Staff'], 'position': [[4], [8], [12], [16], [20]], 'sentiment': ['Positive', 'Positive', 'Neutral', 'Positive', 'Positive'], 'probs': [[0.0004132994799874723, 0.0003014410613104701, 0.9992853999137878], [0.0002638200530782342, 0.001427837647497654, 0.9983083009719849], [0.0004328535287640989, 0.8319836258888245, 0.16758349537849426], [0.0002771843282971531, 0.04387994110584259, 0.9558428525924683], [0.0002821066009346396, 0.0004883920191787183, 0.9992295503616333]], 'confidence': [0.9993, 0.9983, 0.832, 0.9558, 0.9992]} | N22: 5 | O22: 5 | P22: =_xlfn.XLOOKUP(B22,'g1'!B:B,'g1'!R:R) -> 5 | Q22: =_xlfn.XLOOKUP(B22,'g2'!B:B,'g2'!U:U) -> 5 | R22: =_xlfn.XLOOKUP(B22,'g3'!B:B,'g3'!R:R) -> 5 | S22: =_xlfn.XLOOKUP(D22,'g4'!D:D,'g4'!N:N) -> 5 | T22: =$N22-P22 -> 0 | U22: =$N22-Q22 -> 0 | V22: =$N22-R22 -> 0 | W22: =$N22-S22 -> 0 | X22: [{'aspect': 'food', 'opinion': 'delicious', 'sentiment': 'positive'}, {'aspect': 'meals', 'opinion': 'huge', 'sentiment': 'positive'}, {'aspect': 'price', 'opinion': 'average', 'sentiment': 'neutral'}, {'aspect': 'interior', 'opinion': 'cool', 'sentiment': 'positive'}, {'aspect': 'staff', 'opinion': 'very friendly and helpful', 'sentiment': 'positive'}] | Y22: =FIND("[{",K22) -> 43 | Z22: =FIND("category",K22) -> 62 | AA22: =Z22-Y22-2 -> 17 | AB22: food | AD22: =FIND("[{",X22) -> 1 | AE22: =FIND("opinion",X22) -> 22 | AF22: =AE22-AD22-2 -> 19 | AG22: food | AH22: =AB22=AG22 -> TRUE
A23: 714 | B23: ChIJM5itC0KuEmsRSeCUCWumXq8 | C23: Helene | D23: ChIJM5itC0KuEmsRSeCUCWumXq8Helene | E23: 2 | F23: 5 months ago | G23: Has nothing to do with techno. Absolute Tik-Tok club, if you want to go dancing, you should look for something else. Plus, carpetpoding is pretty much the shittiest thing to dance about! The staff was nice though | H23: Basement Sydney | I23: 14184 | J23: 2025-05-13 | K23: {"overall_sentiment":"negative","aspects":[{"aspect":"music","category":"music","sentiment":"negative","evidence_span":"nothing to do"},{"aspect":"Tik-Tok club","category":"ambiance","sentiment":"negative","evidence_span":"Tik-Tok club"},{"aspect":"dancing","category":"activity","sentiment":"negative","evidence_span":"go dancing"},{"aspect":"carpetpoding","category":"activity","sentiment":"negative","evidence_span":"shittiest thing"},{"aspect":"staff","category":"service","sentiment":"positive","evidence_span":"staff was nice"}]} | L23: {'sentence': 'Has nothing to do with techno . Absolute Tik - Tok club , if you want to go dancing , you should look for something else . Plus , carpetpoding is pretty much the shittiest thing to dance about ! The staff was nice though', 'IOB': ['O', 'O', 'O', 'O', 'O', 'B-ASP', 'O', 'O', 'O', 'O', 'O', 'B-ASP', 'O', 'O', 'O', 'O', 'O', 'O', 'O', 'O', 'O', 'O', 'O', 'O', 'O', 'O', 'O', 'O', 'O', 'O', 'O', 'O', 'O', 'O', 'O', 'O', 'O', 'O', 'O', 'O', 'O', 'B-ASP', 'O', 'O', 'O'], 'tokens': ['Has', 'nothing', 'to', 'do', 'with', 'techno', '.', 'Absolute', 'Tik', '-', 'Tok', 'club', ',', 'if', 'you', 'want', 'to', 'go', 'dancing', ',', 'you', 'should', 'look', 'for', 'something', 'else', '.', 'Plus', ',', 'carpetpoding', 'is', 'pretty', 'much', 'the', 'shittiest', 'thing', 'to', 'dance', 'about', '!', 'The', 'staff', 'was', 'nice', 'though'], 'aspect': ['techno', 'club', 'staff'], 'position': [[5], [11], [41]], 'sentiment': ['Neutral', 'Negative', 'Positive'], 'probs': [[0.0667160153388977, 0.9330411553382874, 0.0002428466104902327], [0.6654525995254517, 0.33430224657058716, 0.0002451488107908517], [0.007105718366801739, 0.0002644569904077798, 0.9926297664642334]], 'confidence': [0.933, 0.6655, 0.9926]} | M23: 1 | N23: =LEN(K23)-LEN(SUBSTITUTE(K23,"{",""))-1 -> 5 | O23: 3 | P23: =_xlfn.XLOOKUP(B23,'g1'!B:B,'g1'!R:R) -> 3 | Q23: =_xlfn.XLOOKUP(B23,'g2'!B:B,'g2'!U:U) -> 4 | R23: =_xlfn.XLOOKUP(B23,'g3'!B:B,'g3'!R:R) -> 4 | S23: =_xlfn.XLOOKUP(D23,'g4'!D:D,'g4'!N:N) -> 5 | T23: =$N23-P23 -> 2 | U23: =$N23-Q23 -> 1 | V23: =$N23-R23 -> 1 | W23: =$N23-S23 -> 0 | X23: [{'aspect': 'music', 'opinion': 'nothing to do with techno', 'sentiment': 'negative'}, {'aspect': 'club vibe', 'opinion': 'Absolute Tik-Tok club', 'sentiment': 'negative'}, {'aspect': 'dancing', 'opinion': 'if you want to go dancing, you should look for something else', 'sentiment': 'negative'}, {'aspect': 'dance floor', 'opinion': 'carpetpoding is pretty much the shittiest thing to dance about', 'sentiment': 'negative'}, {'aspect': 'staff', 'opinion': 'nice', 'sentiment': 'positive'}] | Y23: =FIND("[{",K23) -> 43 | Z23: =FIND("category",K23) -> 63 | AA23: =Z23-Y23-2 -> 18 | AB23: techno | AD23: =FIND("[{",X23) -> 1 | AE23: =FIND("opinion",X23) -> 23 | AF23: =AE23-AD23-2 -> 20 | AG23: music | AH23: =AB23=AG23 -> FALSE
A24: 345 | B24: ChIJBXftMiqlEmsRHo2ksAf5yHw | C24: Danielle Wilson | D24: ChIJBXftMiqlEmsRHo2ksAf5yHwDanielle Wilson | E24: 2 | F24: 5 years ago | G24: Very dusty and dirty. No rubbish bin inside the hall. You will always find a spider web. On the upside, good size for small gatherings and there is a toilet block next to the hall. | H24: Scout Hall Central Park | I24: 61048 | J24: 2020-10-11 | K24: { "overall_sentiment": "negative", "aspects": [ { "aspect": "cleanliness", "category": "hygiene", "sentiment": "negative", "evidence_span": "dusty" }, { "aspect": "rubbish bin", "category": "facilities", "sentiment": "negative", "evidence_span": "No rubbish bin" }, { "aspect": "spider web", "category": "hygiene", "sentiment": "negative", "evidence_span": "spider web" }, { "aspect": "size", "category": "space", "sentiment": "positive", "evidence_span": "good size" }, { "aspect": "toilet block", "category": "facilities", "sentiment": "positive", "evidence_span": "toilet block" } ] } | L24: {'sentence': 'Very dusty and dirty . No rubbish bin inside the hall . You will always find a spider web . On the upside , good size for small gatherings and there is a toilet block next to the hall .', 'IOB': ['O', 'O', 'O', 'O', 'O', 'O', 'O', 'O', 'O', 'O', 'B-ASP', 'O', 'O', 'O', 'O', 'O', 'O', 'O', 'O', 'O', 'O', 'O', 'O', 'O', 'O', 'O', 'O', 'O', 'O', 'O', 'O', 'O', 'O', 'B-ASP', 'O', 'O', 'O', 'O', 'O', 'O'], 'tokens': ['Very', 'dusty', 'and', 'dirty', '.', 'No', 'rubbish', 'bin', 'inside', 'the', 'hall', '.', 'You', 'will', 'always', 'find', 'a', 'spider', 'web', '.', 'On', 'the', 'upside', ',', 'good', 'size', 'for', 'small', 'gatherings', 'and', 'there', 'is', 'a', 'toilet', 'block', 'next', 'to', 'the', 'hall', '.'], 'aspect': ['hall', 'toilet'], 'position': [[10], [33]], 'sentiment': ['Negative', 'Neutral'], 'probs': [[0.9984422326087952, 0.0009591714479029179, 0.000598579877987504], [0.10969900339841843, 0.889731764793396, 0.0005692859995178878]], 'confidence': [0.9984, 0.8897]} | M24: 1 | N24: =LEN(K24)-LEN(SUBSTITUTE(K24,"{",""))-1 -> 5 | O24: 2 | P24: =_xlfn.XLOOKUP(B24,'g1'!B:B,'g1'!R:R) -> 4 | Q24: =_xlfn.XLOOKUP(B24,'g2'!B:B,'g2'!U:U) -> 5 | R24: =_xlfn.XLOOKUP(B24,'g3'!B:B,'g3'!R:R) -> 3 | S24: =_xlfn.XLOOKUP(D24,'g4'!D:D,'g4'!N:N) -> 5 | T24: =$N24-P24 -> 1 | U24: =$N24-Q24 -> 0 | V24: =$N24-R24 -> 2 | W24: =$N24-S24 -> 0 | X24: [{'aspect': 'cleanliness', 'opinion': 'Very dusty and dirty', 'sentiment': 'negative'}, {'aspect': 'rubbish bin', 'opinion': 'No rubbish bin', 'sentiment': 'negative'}, {'aspect': 'spider web', 'opinion': 'You will always find a spider web', 'sentiment': 'negative'}, {'aspect': 'size', 'opinion': 'good size for small gatherings', 'sentiment': 'positive'}, {'aspect': 'toilet block', 'opinion': 'there is a toilet block next to the hall', 'sentiment': 'neutral'}] | Y24: =FIND("[{",K24) -> #VALUE! | Z24: =FIND("category",K24) -> 97 | AA24: =Z24-Y24-2 -> #VALUE! | AB24: #VALUE! | AD24: =FIND("[{",X24) -> 1 | AE24: =FIND("opinion",X24) -> 29 | AF24: =AE24-AD24-2 -> 26 | AG24: cleanliness | AH24: =AB24=AG24 -> #VALUE!
A25: 1845 | B25: ChIJqfFLc6QfE2sRCJkoVSE3lzE | C25: Caroline Titchener-Bloom | D25: ChIJqfFLc6QfE2sRCJkoVSE3lzECaroline Titchener-Bloom | E25: 5 | F25: a year ago | G25: Beautiful beach. Lots of green grass. Bike Path all along. Plenty of seats to just sit and watch the ocean. | H25: Bulli Beach Reserve | I25: 31154 | J25: 2024-10-10 | K25: {"overall_sentiment":"positive","aspects":[{"aspect":"beach","category":"environment","sentiment":"positive","evidence_span":"Beautiful beach"},{"aspect":"grass","category":"environment","sentiment":"positive","evidence_span":"green grass"},{"aspect":"bike path","category":"amenity","sentiment":"positive","evidence_span":"Bike Path"},{"aspect":"seats","category":"amenity","sentiment":"positive","evidence_span":"Plenty of seats"},{"aspect":"ocean","category":"view","sentiment":"positive","evidence_span":"watch the ocean"}]} | L25: {'sentence': 'Beautiful beach . Lots of green grass . Bike Path all along . Plenty of seats to just sit and watch the ocean .', 'IOB': ['O', 'B-ASP', 'O', 'O', 'O', 'O', 'O', 'O', 'O', 'O', 'O', 'O', 'O', 'O', 'O', 'B-ASP', 'O', 'O', 'O', 'O', 'O', 'O', 'O', 'O'], 'tokens': ['Beautiful', 'beach', '.', 'Lots', 'of', 'green', 'grass', '.', 'Bike', 'Path', 'all', 'along', '.', 'Plenty', 'of', 'seats', 'to', 'just', 'sit', 'and', 'watch', 'the', 'ocean', '.'], 'aspect': ['beach', 'seats'], 'position': [[1], [15]], 'sentiment': ['Positive', 'Positive'], 'probs': [[0.000625246437266469, 0.0011599515564739704, 0.998214840888977], [0.0028472619596868753, 0.009674464352428913, 0.9874783754348755]], 'confidence': [0.9982, 0.9875]} | M25: 1 | N25: =LEN(K25)-LEN(SUBSTITUTE(K25,"{",""))-1 -> 5 | O25: 2 | P25: =_xlfn.XLOOKUP(B25,'g1'!B:B,'g1'!R:R) -> 4 | Q25: =_xlfn.XLOOKUP(B25,'g2'!B:B,'g2'!U:U) -> 4 | R25: =_xlfn.XLOOKUP(B25,'g3'!B:B,'g3'!R:R) -> 4 | S25: =_xlfn.XLOOKUP(D25,'g4'!D:D,'g4'!N:N) -> 5 | T25: =$N25-P25 -> 1 | U25: =$N25-Q25 -> 1 | V25: =$N25-R25 -> 1 | W25: =$N25-S25 -> 0 | X25: [{'aspect': 'beach', 'opinion': 'Beautiful beach', 'sentiment': 'positive'}, {'aspect': 'grass', 'opinion': 'Lots of green grass', 'sentiment': 'positive'}, {'aspect': 'bike path', 'opinion': 'Bike Path all along', 'sentiment': 'positive'}, {'aspect': 'seats', 'opinion': 'Plenty of seats to just sit', 'sentiment': 'positive'}, {'aspect': 'ocean', 'opinion': 'watch the ocean', 'sentiment': 'neutral'}] | Y25: =FIND("[{",K25) -> 43 | Z25: =FIND("category",K25) -> 63 | AA25: =Z25-Y25-2 -> 18 | AB25: beach | AD25: =FIND("[{",X25) -> 1 | AE25: =FIND("opinion",X25) -> 23 | AF25: =AE25-AD25-2 -> 20 | AG25: beach | AH25: =AB25=AG25 -> TRUE
A26: 191 | B26: ChIJXaAxq0euEmsRxiVSeqt-c6w | C26: Kelv | D26: ChIJXaAxq0euEmsRxiVSeqt-c6wKelv | E26: 4 | F26: 6 years ago | G26: Really nice food. Order your fish and a number of sides. They do have options for steaks and other meats too. Was easy to get a table for a group of 6 and the wait staff were friendly and helpful. Nice place to go for some good up market fish and chips. | H26: love.fish | I26: 1935 | J26: 2019-10-12 | K26: {"overall_sentiment":"positive","aspects":[{"aspect":"food","category":"food quality","sentiment":"positive","evidence_span":"nice food"},{"aspect":"fish and chips","category":"food quality","sentiment":"positive","evidence_span":"up market fish"},{"aspect":"seating","category":"service","sentiment":"positive","evidence_span":"get a table"},{"aspect":"wait staff","category":"service","sentiment":"positive","evidence_span":"friendly and helpful"},{"aspect":"place","category":"ambience","sentiment":"positive","evidence_span":"Nice place"}]} | L26: {'sentence': 'Really nice food . Order your fish and a number of sides . They do have options for steaks and other meats too . Was easy to get a table for a group of 6 and the wait staff were friendly and helpful . Nice place to go for some good up market fish and chips .', 'IOB': ['O', 'O', 'B-ASP', 'O', 'O', 'O', 'O', 'O', 'O', 'O', 'O', 'O', 'O', 'O', 'O', 'O', 'O', 'O', 'O', 'O', 'O', 'O', 'O', 'O', 'O', 'O', 'O', 'O', 'O', 'B-ASP', 'O', 'O', 'O', 'O', 'O', 'O', 'O', 'B-ASP', 'I-ASP', 'O', 'O', 'O', 'O', 'O', 'O', 'O', 'O', 'O', 'O', 'O', 'O', 'O', 'O', 'O', 'O', 'O', 'O'], 'tokens': ['Really', 'nice', 'food', '.', 'Order', 'your', 'fish', 'and', 'a', 'number', 'of', 'sides', '.', 'They', 'do', 'have', 'options', 'for', 'steaks', 'and', 'other', 'meats', 'too', '.', 'Was', 'easy', 'to', 'get', 'a', 'table', 'for', 'a', 'group', 'of', '6', 'and', 'the', 'wait', 'staff', 'were', 'friendly', 'and', 'helpful', '.', 'Nice', 'place', 'to', 'go', 'for', 'some', 'good', 'up', 'market', 'fish', 'and', 'chips', '.'], 'aspect': ['food', 'table', 'wait staff'], 'position': [[2], [29], [37, 38]], 'sentiment': ['Positive', 'Positive', 'Positive'], 'probs': [[0.0003673420869745314, 0.0005175316473469138, 0.9991151690483093], [0.00017141771968454123, 0.0005601945449598134, 0.9992683529853821], [0.0001631098275538534, 0.0003634742752183229, 0.9994733929634094]], 'confidence': [0.9991, 0.9993, 0.9995]} | M26: 1 | N26: 5 | O26: 3 | P26: =_xlfn.XLOOKUP(B26,'g1'!B:B,'g1'!R:R) -> 4 | Q26: =_xlfn.XLOOKUP(B26,'g2'!B:B,'g2'!U:U) -> 4 | R26: =_xlfn.XLOOKUP(B26,'g3'!B:B,'g3'!R:R) -> 5 | S26: =_xlfn.XLOOKUP(D26,'g4'!D:D,'g4'!N:N) -> 5 | T26: =$N26-P26 -> 1 | U26: =$N26-Q26 -> 1 | V26: =$N26-R26 -> 0 | W26: =$N26-S26 -> 0 | X26: [{'aspect': 'fish and chips', 'opinion': 'good up market', 'sentiment': 'positive'}, {'aspect': 'service', 'opinion': 'friendly and helpful', 'sentiment': 'positive'}, {'aspect': 'food', 'opinion': 'really nice', 'sentiment': 'positive'}, {'aspect': 'seating', 'opinion': 'easy to get a table for a group of 6', 'sentiment': 'positive'}, {'aspect': 'place', 'opinion': 'nice', 'sentiment': 'positive'}] | Y26: =FIND("[{",K26) -> 43 | Z26: =FIND("category",K26) -> 62 | AA26: =Z26-Y26-2 -> 17 | AB26: food | AD26: =FIND("[{",X26) -> 1 | AE26: =FIND("opinion",X26) -> 32 | AF26: =AE26-AD26-2 -> 29 | AG26: fish and chips | AH26: =AB26=AG26 -> FALSE
A27: 325 | B27: ChIJradWc6wVkWsRHcdG1mxgmEA | C27: Sezz 1 | D27: ChIJradWc6wVkWsRHcdG1mxgmEASezz 1 | E27: 1 | F27: 4 years ago | G27: Food was nice but $22 for a chicken burger that doesn’t have a full schnitzel in fact it would be lucky to even be half a schnitzel on it is steep, there was no aioli and.very very limited salad on the burger. Total rip off. We won’t be back | H27: Pimpama Tavern | I27: 1380 | J27: 2021-10-11 | K27: {"overall_sentiment":"negative","aspects":[{"aspect":"food","category":"food","sentiment":"positive","evidence_span":"Food was nice"},{"aspect":"price","category":"price","sentiment":"negative","evidence_span":"is steep"},{"aspect":"schnitzel","category":"portion","sentiment":"negative","evidence_span":"half a schnitzel"},{"aspect":"aioli","category":"condiment","sentiment":"negative","evidence_span":"no aioli"},{"aspect":"salad","category":"topping","sentiment":"negative","evidence_span":"limited salad"}]} | L27: {'sentence': 'Food was nice but $ 22 for a chicken burger that doesn ’ t have a full schnitzel in fact it would be lucky to even be half a schnitzel on it is steep , there was no aioli and . very very limited salad on the burger . Total rip off . We won ’ t be back', 'IOB': ['B-ASP', 'O', 'O', 'O', 'O', 'O', 'O', 'O', 'O', 'B-ASP', 'O', 'O', 'O', 'O', 'O', 'O', 'O', 'O', 'O', 'O', 'O', 'O', 'O', 'O', 'O', 'O', 'O', 'O', 'O', 'O', 'O', 'O', 'O', 'O', 'O', 'O', 'O', 'O', 'O', 'O', 'O', 'O', 'O', 'O', 'B-ASP', 'O', 'O', 'O', 'O', 'O', 'O', 'O', 'O', 'O', 'O', 'O', 'O', 'O', 'O'], 'tokens': ['Food', 'was', 'nice', 'but', '$', '22', 'for', 'a', 'chicken', 'burger', 'that', 'doesn', '’', 't', 'have', 'a', 'full', 'schnitzel', 'in', 'fact', 'it', 'would', 'be', 'lucky', 'to', 'even', 'be', 'half', 'a', 'schnitzel', 'on', 'it', 'is', 'steep', ',', 'there', 'was', 'no', 'aioli', 'and', '.', 'very', 'very', 'limited', 'salad', 'on', 'the', 'burger', '.', 'Total', 'rip', 'off', '.', 'We', 'won', '’', 't', 'be', 'back'], 'aspect': ['Food', 'burger', 'salad'], 'position': [[0], [9], [44]], 'sentiment': ['Positive', 'Negative', 'Negative'], 'probs': [[0.17456239461898804, 0.011041415855288506, 0.8143962025642395], [0.9762904644012451, 0.014520772732794285, 0.009188764728605747], [0.9888516068458557, 0.009792095981538296, 0.001356343156658113]], 'confidence': [0.8144, 0.9763, 0.9889]} | M27: 1 | N27: =LEN(K27)-LEN(SUBSTITUTE(K27,"{",""))-1 -> 5 | O27: 3 | P27: =_xlfn.XLOOKUP(B27,'g1'!B:B,'g1'!R:R) -> 5 | Q27: =_xlfn.XLOOKUP(B27,'g2'!B:B,'g2'!U:U) -> 6 | R27: =_xlfn.XLOOKUP(B27,'g3'!B:B,'g3'!R:R) -> 3 | S27: =_xlfn.XLOOKUP(D27,'g4'!D:D,'g4'!N:N) -> 5 | T27: =$N27-P27 -> 0 | U27: =$N27-Q27 -> -1 | V27: =$N27-R27 -> 2 | W27: =$N27-S27 -> 0 | X27: [{'aspect': 'food', 'opinion': 'nice', 'sentiment': 'positive'}, {'aspect': 'chicken burger', 'opinion': 'not full', 'sentiment': 'negative'}, {'aspect': 'price', 'opinion': 'steep', 'sentiment': 'negative'}, {'aspect': 'aioli', 'opinion': 'no', 'sentiment': 'negative'}, {'aspect': 'salad', 'opinion': 'limited', 'sentiment': 'negative'}] | Y27: =FIND("[{",K27) -> 43 | Z27: =FIND("category",K27) -> 62 | AA27: =Z27-Y27-2 -> 17 | AB27: food | AD27: =FIND("[{",X27) -> 1 | AE27: =FIND("opinion",X27) -> 22 | AF27: =AE27-AD27-2 -> 19 | AG27: food | AH27: =AB27=AG27 -> TRUE
A28: 1094 | B28: ChIJIXp1IqS6EmsRc7plR8jSBgc | C28: Steven Lee | D28: ChIJIXp1IqS6EmsRc7plR8jSBgcSteven Lee | E28: 2 | F28: 2 months ago | G28: The indoor heated pool has poor water quality and is not the standard length of a pool. The water jets are simple and there are no foot jets. The open, unisex shower room is inconvenient. | H28: Ashfield Aquatic Centre | I28: 2611 | J28: 2025-08-11 | K28: {"overall_sentiment":"negative","aspects":[{"aspect":"water quality","category":"pool","sentiment":"negative","evidence_span":"poor water quality"},{"aspect":"length","category":"pool","sentiment":"negative","evidence_span":"not the standard"},{"aspect":"water jets","category":"pool","sentiment":"negative","evidence_span":"are simple"},{"aspect":"foot jets","category":"pool","sentiment":"negative","evidence_span":"no foot jets"},{"aspect":"shower room","category":"shower","sentiment":"negative","evidence_span":"inconvenient"}]} | L28: {'sentence': 'The indoor heated pool has poor water quality and is not the standard length of a pool . The water jets are simple and there are no foot jets . The open , unisex shower room is inconvenient .', 'IOB': ['O', 'B-ASP', 'I-ASP', 'I-ASP', 'O', 'O', 'O', 'O', 'O', 'O', 'O', 'O', 'O', 'O', 'O', 'O', 'O', 'O', 'O', 'B-ASP', 'I-ASP', 'O', 'O', 'O', 'O', 'O', 'O', 'O', 'O', 'O', 'O', 'O', 'O', 'O', 'O', 'O', 'O', 'O', 'O'], 'tokens': ['The', 'indoor', 'heated', 'pool', 'has', 'poor', 'water', 'quality', 'and', 'is', 'not', 'the', 'standard', 'length', 'of', 'a', 'pool', '.', 'The', 'water', 'jets', 'are', 'simple', 'and', 'there', 'are', 'no', 'foot', 'jets', '.', 'The', 'open', ',', 'unisex', 'shower', 'room', 'is', 'inconvenient', '.'], 'aspect': ['indoor heated pool', 'water jets'], 'position': [[1, 2, 3], [19, 20]], 'sentiment': ['Negative', 'Negative'], 'probs': [[0.6230904459953308, 0.3765738606452942, 0.00033577290014363825], [0.8432884812355042, 0.15432754158973694, 0.002383978571742773]], 'confidence': [0.6231, 0.8433]} | M28: 1 | N28: =LEN(K28)-LEN(SUBSTITUTE(K28,"{",""))-1 -> 5 | O28: 2 | P28: =_xlfn.XLOOKUP(B28,'g1'!B:B,'g1'!R:R) -> 5 | Q28: =_xlfn.XLOOKUP(B28,'g2'!B:B,'g2'!U:U) -> 5 | R28: =_xlfn.XLOOKUP(B28,'g3'!B:B,'g3'!R:R) -> 3 | S28: =_xlfn.XLOOKUP(D28,'g4'!D:D,'g4'!N:N) -> 5 | T28: =$N28-P28 -> 0 | U28: =$N28-Q28 -> 0 | V28: =$N28-R28 -> 2 | W28: =$N28-S28 -> 0 | X28: [{'aspect': 'water quality', 'opinion': 'poor', 'sentiment': 'negative'}, {'aspect': 'pool length', 'opinion': 'not the standard length', 'sentiment': 'negative'}, {'aspect': 'water jets', 'opinion': 'simple', 'sentiment': 'negative'}, {'aspect': 'foot jets', 'opinion': 'none', 'sentiment': 'negative'}, {'aspect': 'shower room', 'opinion': 'inconvenient', 'sentiment': 'negative'}] | Y28: =FIND("[{",K28) -> 43 | Z28: =FIND("category",K28) -> 71 | AA28: =Z28-Y28-2 -> 26 | AB28: water quality | AD28: =FIND("[{",X28) -> 1 | AE28: =FIND("opinion",X28) -> 31 | AF28: =AE28-AD28-2 -> 28 | AG28: water quality | AH28: =AB28=AG28 -> TRUE
A29: 175 | B29: ChIJ9fPEZtw41GoR97feQpnAbQ8 | C29: Jennifer B | D29: ChIJ9fPEZtw41GoR97feQpnAbQ8Jennifer B | E29: 3 | F29: 3 months ago | G29: First time here. Staff are friendly. Playground ok, a little small. They charge for each adult as well as under 2s, which is abit much. Most places are free. Menu reasonbly priced (although have to pay extra for tomato sauce!) Will probably will find alternatives. | H29: Meerkat Manner Indoor Play & Cafe | I29: 16508 | J29: 2025-07-12 | K29: {"overall_sentiment":"negative","aspects":[{"aspect":"staff","category":"service","sentiment":"positive","evidence_span":"friendly"},{"aspect":"playground","category":"facility","sentiment":"negative","evidence_span":"a little small"},{"aspect":"charges","category":"price","sentiment":"negative","evidence_span":"They charge"},{"aspect":"menu","category":"price","sentiment":"positive","evidence_span":"reasonbly priced"},{"aspect":"tomato sauce","category":"food","sentiment":"negative","evidence_span":"pay extra"}]} | L29: {'sentence': 'First time here . Staff are friendly . Playground ok , a little small . They charge for each adult as well as under 2s , which is abit much . Most places are free . Menu reasonbly priced ( although have to pay extra for tomato sauce ! ) Will probably will find alternatives .', 'IOB': ['O', 'O', 'O', 'O', 'B-ASP', 'O', 'O', 'O', 'O', 'O', 'O', 'O', 'O', 'O', 'O', 'O', 'O', 'O', 'O', 'O', 'O', 'O', 'O', 'O', 'O', 'O', 'O', 'O', 'O', 'O', 'O', 'O', 'O', 'O', 'O', 'O', 'O', 'O', 'B-ASP', 'O', 'O', 'O', 'O', 'O', 'O', 'O', 'O', 'O', 'O', 'O', 'O', 'O', 'O', 'O', 'O', 'O'], 'tokens': ['First', 'time', 'here', '.', 'Staff', 'are', 'friendly', '.', 'Playground', 'ok', ',', 'a', 'little', 'small', '.', 'They', 'charge', 'for', 'each', 'adult', 'as', 'well', 'as', 'under', '2s', ',', 'which', 'is', 'abit', 'much', '.', 'Most', 'places', 'are', 'free', '.', 'Menu', 'reasonbly', 'priced', '(', 'although', 'have', 'to', 'pay', 'extra', 'for', 'tomato', 'sauce', '!', ')', 'Will', 'probably', 'will', 'find', 'alternatives', '.'], 'aspect': ['Staff', 'priced'], 'position': [[4], [38]], 'sentiment': ['Positive', 'Negative'], 'probs': [[0.014644547365605831, 0.0007351626409217715, 0.9846203327178955], [0.6081672310829163, 0.0021170806139707565, 0.3897157609462738]], 'confidence': [0.9846, 0.6082]} | M29: 1 | N29: =LEN(K29)-LEN(SUBSTITUTE(K29,"{",""))-1 -> 5 | O29: 2 | P29: =_xlfn.XLOOKUP(B29,'g1'!B:B,'g1'!R:R) -> 5 | Q29: =_xlfn.XLOOKUP(B29,'g2'!B:B,'g2'!U:U) -> 4 | R29: =_xlfn.XLOOKUP(B29,'g3'!B:B,'g3'!R:R) -> 4 | S29: =_xlfn.XLOOKUP(D29,'g4'!D:D,'g4'!N:N) -> 5 | T29: =$N29-P29 -> 0 | U29: =$N29-Q29 -> 1 | V29: =$N29-R29 -> 1 | W29: =$N29-S29 -> 0 | X29: [{'aspect': 'staff', 'opinion': 'are friendly', 'sentiment': 'positive'}, {'aspect': 'playground', 'opinion': 'ok, a little small', 'sentiment': 'neutral'}, {'aspect': 'charges', 'opinion': 'abit much', 'sentiment': 'negative'}, {'aspect': 'menu', 'opinion': 'reasonbly priced', 'sentiment': 'positive'}, {'aspect': 'tomato sauce', 'opinion': 'pay extra', 'sentiment': 'negative'}] | Y29: =FIND("[{",K29) -> 43 | Z29: =FIND("category",K29) -> 63 | AA29: =Z29-Y29-2 -> 18 | AB29: staff | AD29: =FIND("[{",X29) -> 1 | AE29: =FIND("opinion",X29) -> 23 | AF29: =AE29-AD29-2 -> 20 | AG29: staff | AH29: =AB29=AG29 -> TRUE
A30: 256 | B30: ChIJxbZg3o6jE2sRHWpQu8bCWkY | C30: Jamie Coates | D30: ChIJxbZg3o6jE2sRHWpQu8bCWkYJamie Coates | E30: 4 | F30: 3 years ago | G30: After the rains, the route to the falls has taken a bit of a battering. There will be some muddy sections, and a small creek to cross which can be a little slippery. Plenty of overgrowth covering some of the path through. Not so well sign … | H30: Sixty Foot Falls | I30: 42134 | J30: 2022-10-11 | K30: {"overall_sentiment":"negative","aspects":[{"aspect":"route","category":"access","sentiment":"negative","evidence_span":"battering"},{"aspect":"mud","category":"trail condition","sentiment":"negative","evidence_span":"muddy"},{"aspect":"creek","category":"safety","sentiment":"negative","evidence_span":"slippery"},{"aspect":"overgrowth","category":"trail maintenance","sentiment":"negative","evidence_span":"overgrowth"},{"aspect":"signage","category":"navigation","sentiment":"negative","evidence_span":"Not so well"}]} | L30: {'sentence': 'After the rains , the route to the falls has taken a bit of a battering . There will be some muddy sections , and a small creek to cross which can be a little slippery . Plenty of overgrowth covering some of the path through . Not so well sign …', 'IOB': ['O', 'O', 'O', 'O', 'O', 'O', 'O', 'O', 'O', 'O', 'O', 'O', 'O', 'O', 'O', 'O', 'O', 'O', 'O', 'O', 'O', 'O', 'O', 'O', 'O', 'O', 'O', 'O', 'O', 'O', 'O', 'O', 'O', 'O', 'O', 'O', 'O', 'O', 'O', 'O', 'O', 'O', 'O', 'O', 'B-ASP', 'O', 'O', 'O', 'O', 'O', 'O', 'O'], 'tokens': ['After', 'the', 'rains', ',', 'the', 'route', 'to', 'the', 'falls', 'has', 'taken', 'a', 'bit', 'of', 'a', 'battering', '.', 'There', 'will', 'be', 'some', 'muddy', 'sections', ',', 'and', 'a', 'small', 'creek', 'to', 'cross', 'which', 'can', 'be', 'a', 'little', 'slippery', '.', 'Plenty', 'of', 'overgrowth', 'covering', 'some', 'of', 'the', 'path', 'through', '.', 'Not', 'so', 'well', 'sign', '…'], 'aspect': ['path'], 'position': [[44]], 'sentiment': ['Negative'], 'probs': [[0.9917140007019043, 0.007989807054400444, 0.0002962252765428275]], 'confidence': [0.9917]} | M30: 1 | N30: =LEN(K30)-LEN(SUBSTITUTE(K30,"{",""))-1 -> 5 | O30: 1 | P30: =_xlfn.XLOOKUP(B30,'g1'!B:B,'g1'!R:R) -> 5 | Q30: =_xlfn.XLOOKUP(B30,'g2'!B:B,'g2'!U:U) -> 5 | R30: =_xlfn.XLOOKUP(B30,'g3'!B:B,'g3'!R:R) -> 4 | S30: =_xlfn.XLOOKUP(D30,'g4'!D:D,'g4'!N:N) -> 5 | T30: =$N30-P30 -> 0 | U30: =$N30-Q30 -> 0 | V30: =$N30-R30 -> 1 | W30: =$N30-S30 -> 0 | X30: [{'aspect': 'route', 'opinion': 'taken a bit of a battering', 'sentiment': 'negative'}, {'aspect': 'muddy', 'opinion': 'muddy sections', 'sentiment': 'negative'}, {'aspect': 'creek', 'opinion': 'a little slippery', 'sentiment': 'negative'}, {'aspect': 'overgrowth', 'opinion': 'plenty of overgrowth covering', 'sentiment': 'negative'}, {'aspect': 'sign', 'opinion': 'not so well', 'sentiment': 'negative'}] | Y30: =FIND("[{",K30) -> 43 | Z30: =FIND("category",K30) -> 63 | AA30: =Z30-Y30-2 -> 18 | AB30: route | AD30: =FIND("[{",X30) -> 1 | AE30: =FIND("opinion",X30) -> 23 | AF30: =AE30-AD30-2 -> 20 | AG30: route | AH30: =AB30=AG30 -> TRUE
A31: 278 | B31: ChIJ171WpA5akWsR4YZbJ5axBbE | C31: Sean Nuguid | D31: ChIJ171WpA5akWsR4YZbJ5axBbESean Nuguid | E31: 4 | F31: 3 years ago | G31: Decent ticket prices but the schedule is a bit odd (few screenings, new movies sometimes not showing, or not showing often). Cup holders are a bit small for large size drinks and seats can be creaky. If you need to readjust expect to make a loud creak. No assigned seating which can be good and bad. | H31: Cineplex South Bank | I31: 201 | J31: 2022-10-11 | K31: {"overall_sentiment":"negative","aspects":[{"aspect":"ticket prices","category":"price","sentiment":"positive","evidence_span":"Decent ticket prices"},{"aspect":"schedule","category":"scheduling","sentiment":"negative","evidence_span":"a bit odd"},{"aspect":"cup holders","category":"amenities","sentiment":"negative","evidence_span":"a bit small"},{"aspect":"seats","category":"seating","sentiment":"negative","evidence_span":"creaky"},{"aspect":"assigned seating","category":"seating","sentiment":"neutral","evidence_span":"No assigned seating"}]} | L31: {'sentence': 'Decent ticket prices but the schedule is a bit odd ( few screenings , new movies sometimes not showing , or not showing often ) . Cup holders are a bit small for large size drinks and seats can be creaky . If you need to readjust expect to make a loud creak . No assigned seating which can be good and bad .', 'IOB': ['O', 'O', 'B-ASP', 'O', 'O', 'O', 'O', 'O', 'O', 'O', 'O', 'O', 'O', 'O', 'O', 'O', 'O', 'O', 'O', 'O', 'O', 'O', 'O', 'O', 'O', 'O', 'O', 'O', 'O', 'O', 'O', 'O', 'O', 'O', 'O', 'B-ASP', 'O', 'B-ASP', 'O', 'O', 'O', 'O', 'O', 'O', 'O', 'O', 'O', 'O', 'O', 'O', 'O', 'O', 'O', 'O', 'O', 'O', 'O', 'O', 'O', 'O', 'O', 'O', 'O', 'O'], 'tokens': ['Decent', 'ticket', 'prices', 'but', 'the', 'schedule', 'is', 'a', 'bit', 'odd', '(', 'few', 'screenings', ',', 'new', 'movies', 'sometimes', 'not', 'showing', ',', 'or', 'not', 'showing', 'often', ')', '.', 'Cup', 'holders', 'are', 'a', 'bit', 'small', 'for', 'large', 'size', 'drinks', 'and', 'seats', 'can', 'be', 'creaky', '.', 'If', 'you', 'need', 'to', 'readjust', 'expect', 'to', 'make', 'a', 'loud', 'creak', '.', 'No', 'assigned', 'seating', 'which', 'can', 'be', 'good', 'and', 'bad', '.'], 'aspect': ['prices', 'drinks', 'seats'], 'position': [[2], [35], [37]], 'sentiment': ['Positive', 'Negative', 'Negative'], 'probs': [[0.3257499635219574, 0.004531820770353079, 0.6697182059288025], [0.9593765139579773, 0.0021114377304911613, 0.03851202130317688], [0.9874191880226135, 0.007756600622087717, 0.004824161063879728]], 'confidence': [0.6697, 0.9594, 0.9874]} | M31: 1 | N31: =LEN(K31)-LEN(SUBSTITUTE(K31,"{",""))-1 -> 5 | O31: 3 | P31: =_xlfn.XLOOKUP(B31,'g1'!B:B,'g1'!R:R) -> 5 | Q31: =_xlfn.XLOOKUP(B31,'g2'!B:B,'g2'!U:U) -> 5 | R31: =_xlfn.XLOOKUP(B31,'g3'!B:B,'g3'!R:R) -> 4 | S31: =_xlfn.XLOOKUP(D31,'g4'!D:D,'g4'!N:N) -> 5 | T31: =$N31-P31 -> 0 | U31: =$N31-Q31 -> 0 | V31: =$N31-R31 -> 1 | W31: =$N31-S31 -> 0 | X31: [{'aspect': 'ticket prices', 'opinion': 'decent', 'sentiment': 'positive'}, {'aspect': 'movie schedule', 'opinion': 'a bit odd', 'sentiment': 'negative'}, {'aspect': 'cup holders', 'opinion': 'a bit small', 'sentiment': 'negative'}, {'aspect': 'seats', 'opinion': 'creaky', 'sentiment': 'negative'}, {'aspect': 'seating policy', 'opinion': 'no assigned seating', 'sentiment': 'neutral'}] | Y31: =FIND("[{",K31) -> 43 | Z31: =FIND("category",K31) -> 71 | AA31: =Z31-Y31-2 -> 26 | AB31: ticket prices | AD31: =FIND("[{",X31) -> 1 | AE31: =FIND("opinion",X31) -> 31 | AF31: =AE31-AD31-2 -> 28 | AG31: ticket prices | AH31: =AB31=AG31 -> TRUE
A32: 288 | B32: ChIJ-RlaManz1moRRTIVby5JrRk | C32: Sharon Fuller | D32: ChIJ-RlaManz1moRRTIVby5JrRkSharon Fuller | E32: 4 | F32: 2 years ago | G32: The whole function area and winery it self was beautiful our food as choosen buy the group we were with was nice .But the beer and wine was definitely not up to any standard, ie beer was flat and had a white film on and in it ,the red … | H32: Witchmount Estate Functions & Restaurant | I32: 12743 | J32: 2023-10-11 | K32: {"overall_sentiment":"negative","aspects":[{"aspect":"function area","category":"facilities","sentiment":"positive","evidence_span":"was beautiful"},{"aspect":"winery","category":"facilities","sentiment":"positive","evidence_span":"was beautiful"},{"aspect":"food","category":"food","sentiment":"positive","evidence_span":"was nice"},{"aspect":"beer","category":"drink","sentiment":"negative","evidence_span":"was flat"},{"aspect":"wine","category":"drink","sentiment":"negative","evidence_span":"not up to"}]} | L32: {'sentence': 'The whole function area and winery it self was beautiful our food as choosen buy the group we were with was nice . But the beer and wine was definitely not up to any standard , ie beer was flat and had a white film on and in it , the red …', 'IOB': ['O', 'O', 'O', 'O', 'O', 'O', 'O', 'O', 'O', 'O', 'O', 'B-ASP', 'O', 'O', 'O', 'O', 'O', 'O', 'O', 'O', 'O', 'O', 'O', 'O', 'O', 'B-ASP', 'O', 'O', 'O', 'O', 'O', 'O', 'O', 'O', 'O', 'O', 'O', 'O', 'O', 'O', 'O', 'O', 'O', 'O', 'O', 'O', 'O', 'O', 'O', 'O', 'O', 'O', 'O'], 'tokens': ['The', 'whole', 'function', 'area', 'and', 'winery', 'it', 'self', 'was', 'beautiful', 'our', 'food', 'as', 'choosen', 'buy', 'the', 'group', 'we', 'were', 'with', 'was', 'nice', '.', 'But', 'the', 'beer', 'and', 'wine', 'was', 'definitely', 'not', 'up', 'to', 'any', 'standard', ',', 'ie', 'beer', 'was', 'flat', 'and', 'had', 'a', 'white', 'film', 'on', 'and', 'in', 'it', ',', 'the', 'red', '…'], 'aspect': ['food', 'beer'], 'position': [[11], [25]], 'sentiment': ['Positive', 'Negative'], 'probs': [[0.012613237835466862, 0.0009018564014695585, 0.9864848852157593], [0.9901918172836304, 0.005425231531262398, 0.004382923245429993]], 'confidence': [0.9865, 0.9902]} | M32: 1 | N32: =LEN(K32)-LEN(SUBSTITUTE(K32,"{",""))-1 -> 5 | O32: 2 | P32: =_xlfn.XLOOKUP(B32,'g1'!B:B,'g1'!R:R) -> 5 | Q32: =_xlfn.XLOOKUP(B32,'g2'!B:B,'g2'!U:U) -> 5 | R32: =_xlfn.XLOOKUP(B32,'g3'!B:B,'g3'!R:R) -> 4 | S32: =_xlfn.XLOOKUP(D32,'g4'!D:D,'g4'!N:N) -> 5 | T32: =$N32-P32 -> 0 | U32: =$N32-Q32 -> 0 | V32: =$N32-R32 -> 1 | W32: =$N32-S32 -> 0 | X32: [{'aspect': 'function area', 'opinion': 'beautiful', 'sentiment': 'positive'}, {'aspect': 'winery', 'opinion': 'beautiful', 'sentiment': 'positive'}, {'aspect': 'food', 'opinion': 'nice', 'sentiment': 'positive'}, {'aspect': 'beer', 'opinion': 'not up to standard', 'sentiment': 'negative'}, {'aspect': 'wine', 'opinion': 'not up to standard', 'sentiment': 'negative'}] | Y32: =FIND("[{",K32) -> 43 | Z32: =FIND("category",K32) -> 71 | AA32: =Z32-Y32-2 -> 26 | AB32: function area | AD32: =FIND("[{",X32) -> 1 | AE32: =FIND("opinion",X32) -> 31 | AF32: =AE32-AD32-2 -> 28 | AG32: function area | AH32: =AB32=AG32 -> TRUE
A33: 362 | B33: ChIJ80qj2BE9kWsRnYZqzmEB2To | C33: brenda green | D33: ChIJ80qj2BE9kWsRnYZqzmEB2Tobrenda green | E33: 5 | F33: 4 months ago | G33: This place is amazing. The service and professionalism was excellent. The grounds are spotless. And camping grounds are amazing. | H33: Plunkett Villa Tamborine | I33: 31885 | J33: 2025-06-12 | K33: {"overall_sentiment":"positive","aspects":[{"aspect":"place","category":"general","sentiment":"positive","evidence_span":"amazing"},{"aspect":"service","category":"service","sentiment":"positive","evidence_span":"excellent"},{"aspect":"professionalism","category":"service","sentiment":"positive","evidence_span":"excellent"},{"aspect":"grounds","category":"cleanliness","sentiment":"positive","evidence_span":"spotless"},{"aspect":"camping grounds","category":"facility","sentiment":"positive","evidence_span":"amazing"}]} | L33: {'sentence': 'This place is amazing . The service and professionalism was excellent . The grounds are spotless . And camping grounds are amazing .', 'IOB': ['O', 'O', 'O', 'O', 'O', 'O', 'B-ASP', 'O', 'O', 'O', 'O', 'O', 'O', 'B-ASP', 'O', 'O', 'O', 'O', 'B-ASP', 'I-ASP', 'O', 'O', 'O'], 'tokens': ['This', 'place', 'is', 'amazing', '.', 'The', 'service', 'and', 'professionalism', 'was', 'excellent', '.', 'The', 'grounds', 'are', 'spotless', '.', 'And', 'camping', 'grounds', 'are', 'amazing', '.'], 'aspect': ['service', 'grounds', 'camping grounds'], 'position': [[6], [13], [18, 19]], 'sentiment': ['Positive', 'Positive', 'Positive'], 'probs': [[0.0003347445745021105, 0.00027231834246777, 0.9993928670883179], [0.00020761897030752152, 0.0004434938309714198, 0.9993488192558289], [0.00020277239673305303, 0.00025666269357316196, 0.9995405673980713]], 'confidence': [0.9994, 0.9993, 0.9995]} | M33: 1 | N33: =LEN(K33)-LEN(SUBSTITUTE(K33,"{",""))-1 -> 5 | O33: 3 | P33: =_xlfn.XLOOKUP(B33,'g1'!B:B,'g1'!R:R) -> 5 | Q33: =_xlfn.XLOOKUP(B33,'g2'!B:B,'g2'!U:U) -> 5 | R33: =_xlfn.XLOOKUP(B33,'g3'!B:B,'g3'!R:R) -> 4 | S33: =_xlfn.XLOOKUP(D33,'g4'!D:D,'g4'!N:N) -> 5 | T33: =$N33-P33 -> 0 | U33: =$N33-Q33 -> 0 | V33: =$N33-R33 -> 1 | W33: =$N33-S33 -> 0 | X33: [{'aspect': 'place', 'opinion': 'amazing', 'sentiment': 'positive'}, {'aspect': 'service', 'opinion': 'excellent', 'sentiment': 'positive'}, {'aspect': 'professionalism', 'opinion': 'excellent', 'sentiment': 'positive'}, {'aspect': 'grounds', 'opinion': 'spotless', 'sentiment': 'positive'}, {'aspect': 'camping grounds', 'opinion': 'amazing', 'sentiment': 'positive'}] | Y33: =FIND("[{",K33) -> 43 | Z33: =FIND("category",K33) -> 63 | AA33: =Z33-Y33-2 -> 18 | AB33: place | AD33: =FIND("[{",X33) -> 1 | AE33: =FIND("opinion",X33) -> 23 | AF33: =AE33-AD33-2 -> 20 | AG33: place | AH33: =AB33=AG33 -> TRUE
A34: 40 | B34: ChIJR4l2Z3SvMioRJOcvOZRBF1w | C34: Nikki Mence | D34: ChIJR4l2Z3SvMioRJOcvOZRBF1wNikki Mence | E34: 5 | F34: a year ago | G34: Great afternoon at the new Bounce in Osbourne Park. Everything was a fab experience from start to finish, easy to book online, plenty of dedicated parking, no queueing upon checkin with fast, efficient friendly front desk team. Clean, … | H34: BOUNCEinc Osborne Park | I34: 8691 | J34: 2024-10-10 | K34: {"overall_sentiment":"positive","aspects":[{"aspect":"booking process","category":"booking","sentiment":"positive","evidence_span":"easy to book"},{"aspect":"parking","category":"parking","sentiment":"positive","evidence_span":"dedicated parking"},{"aspect":"checkin","category":"service","sentiment":"positive","evidence_span":"no queueing"},{"aspect":"front desk","category":"staff","sentiment":"positive","evidence_span":"friendly front desk"},{"aspect":"cleanliness","category":"cleanliness","sentiment":"positive","evidence_span":"Clean"}]} | L34: {'sentence': 'Great afternoon at the new Bounce in Osbourne Park . Everything was a fab experience from start to finish , easy to book online , plenty of dedicated parking , no queueing upon checkin with fast , efficient friendly front desk team . Clean , …', 'IOB': ['O', 'O', 'O', 'O', 'O', 'O', 'O', 'O', 'O', 'O', 'O', 'O', 'O', 'O', 'O', 'O', 'O', 'O', 'O', 'O', 'O', 'O', 'B-ASP', 'O', 'O', 'O', 'O', 'O', 'O', 'O', 'O', 'O', 'O', 'O', 'O', 'O', 'O', 'O', 'O', 'B-ASP', 'I-ASP', 'I-ASP', 'O', 'O', 'O', 'O'], 'tokens': ['Great', 'afternoon', 'at', 'the', 'new', 'Bounce', 'in', 'Osbourne', 'Park', '.', 'Everything', 'was', 'a', 'fab', 'experience', 'from', 'start', 'to', 'finish', ',', 'easy', 'to', 'book', 'online', ',', 'plenty', 'of', 'dedicated', 'parking', ',', 'no', 'queueing', 'upon', 'checkin', 'with', 'fast', ',', 'efficient', 'friendly', 'front', 'desk', 'team', '.', 'Clean', ',', '…'], 'aspect': ['book', 'front desk team'], 'position': [[22], [39, 40, 41]], 'sentiment': ['Positive', 'Positive'], 'probs': [[0.00013864152424503118, 0.0007655263761989772, 0.9990957975387573], [0.00017842811939772218, 0.00027740871882997453, 0.9995442032814026]], 'confidence': [0.9991, 0.9995]} | M34: 1 | N34: =LEN(K34)-LEN(SUBSTITUTE(K34,"{",""))-1 -> 5 | O34: 2 | P34: =_xlfn.XLOOKUP(B34,'g1'!B:B,'g1'!R:R) -> 5 | Q34: =_xlfn.XLOOKUP(B34,'g2'!B:B,'g2'!U:U) -> 5 | R34: =_xlfn.XLOOKUP(B34,'g3'!B:B,'g3'!R:R) -> 4 | S34: =_xlfn.XLOOKUP(D34,'g4'!D:D,'g4'!N:N) -> 5 | T34: =$N34-P34 -> 0 | U34: =$N34-Q34 -> 0 | V34: =$N34-R34 -> 1 | W34: =$N34-S34 -> 0 | X34: [{'aspect': 'booking process', 'opinion': 'easy to book online', 'sentiment': 'positive'}, {'aspect': 'parking availability', 'opinion': 'plenty of dedicated parking', 'sentiment': 'positive'}, {'aspect': 'checkin process', 'opinion': 'no queueing upon checkin', 'sentiment': 'positive'}, {'aspect': 'staff friendliness', 'opinion': 'friendly front desk team', 'sentiment': 'positive'}, {'aspect': 'venue cleanliness', 'opinion': 'Clean', 'sentiment': 'positive'}] | Y34: =FIND("[{",K34) -> 43 | Z34: =FIND("category",K34) -> 73 | AA34: =Z34-Y34-2 -> 28 | AB34: booking | AD34: =FIND("[{",X34) -> 1 | AE34: =FIND("opinion",X34) -> 33 | AF34: =AE34-AD34-2 -> 30 | AG34: booking process | AH34: =AB34=AG34 -> FALSE
A35: 1726 | B35: ChIJ05KcaO-A7GsRy-Wo6cqLYgQ | C35: PCEscudero | D35: ChIJ05KcaO-A7GsRy-Wo6cqLYgQPCEscudero | E35: 2 | F35: 7 years ago on Tripadvisor | G35: This is perhaps the only advantage of this campsite. The structure is very simple, bathrooms, laundry and especially the toilets leave something to be desired. But it is very close to where the excursions to Fraser Island depart, which was our objective! | H35: Hervey Bay Caravan Park | I35: 6893 | J35: 2018-10-12 | K35: {"overall_sentiment":"negative","aspects":[{"aspect":"structure","category":"amenities","sentiment":"negative","evidence_span":"very simple"},{"aspect":"bathrooms","category":"amenities","sentiment":"negative","evidence_span":"bathrooms"},{"aspect":"laundry","category":"amenities","sentiment":"negative","evidence_span":"laundry"},{"aspect":"toilets","category":"amenities","sentiment":"negative","evidence_span":"the toilets"},{"aspect":"location","category":"location","sentiment":"positive","evidence_span":"very close"}]} | L35: {'sentence': 'This is perhaps the only advantage of this campsite . The structure is very simple , bathrooms , laundry and especially the toilets leave something to be desired . But it is very close to where the excursions to Fraser Island depart , which was our objective !', 'IOB': ['O', 'O', 'O', 'O', 'O', 'O', 'O', 'O', 'O', 'O', 'O', 'O', 'O', 'O', 'O', 'O', 'O', 'O', 'B-ASP', 'O', 'O', 'O', 'B-ASP', 'O', 'O', 'O', 'O', 'O', 'O', 'O', 'O', 'O', 'O', 'O', 'O', 'O', 'O', 'O', 'O', 'O', 'O', 'O', 'O', 'O', 'O', 'O', 'O', 'O'], 'tokens': ['This', 'is', 'perhaps', 'the', 'only', 'advantage', 'of', 'this', 'campsite', '.', 'The', 'structure', 'is', 'very', 'simple', ',', 'bathrooms', ',', 'laundry', 'and', 'especially', 'the', 'toilets', 'leave', 'something', 'to', 'be', 'desired', '.', 'But', 'it', 'is', 'very', 'close', 'to', 'where', 'the', 'excursions', 'to', 'Fraser', 'Island', 'depart', ',', 'which', 'was', 'our', 'objective', '!'], 'aspect': ['laundry', 'toilets'], 'position': [[18], [22]], 'sentiment': ['Negative', 'Negative'], 'probs': [[0.7812215089797974, 0.2179923802614212, 0.0007860762416385114], [0.995845377445221, 0.003902731230482459, 0.0002519391127862036]], 'confidence': [0.7812, 0.9958]} | M35: 1 | N35: 5 | O35: 2 | P35: =_xlfn.XLOOKUP(B35,'g1'!B:B,'g1'!R:R) -> 5 | Q35: =_xlfn.XLOOKUP(B35,'g2'!B:B,'g2'!U:U) -> 5 | R35: =_xlfn.XLOOKUP(B35,'g3'!B:B,'g3'!R:R) -> 5 | S35: =_xlfn.XLOOKUP(D35,'g4'!D:D,'g4'!N:N) -> 5 | T35: =$N35-P35 -> 0 | U35: =$N35-Q35 -> 0 | V35: =$N35-R35 -> 0 | W35: =$N35-S35 -> 0 | X35: [{'aspect': 'structure', 'opinion': 'very simple', 'sentiment': 'negative'}, {'aspect': 'bathrooms', 'opinion': 'leave something to be desired', 'sentiment': 'negative'}, {'aspect': 'laundry', 'opinion': 'leave something to be desired', 'sentiment': 'negative'}, {'aspect': 'toilets', 'opinion': 'leave something to be desired', 'sentiment': 'negative'}, {'aspect': 'proximity to Fraser Island excursions', 'opinion': 'very close', 'sentiment': 'positive'}] | Y35: =FIND("[{",K35) -> 43 | Z35: =FIND("category",K35) -> 67 | AA35: =Z35-Y35-2 -> 22 | AB35: structure | AD35: =FIND("[{",X35) -> 1 | AE35: =FIND("opinion",X35) -> 27 | AF35: =AE35-AD35-2 -> 24 | AG35: structure | AH35: =AB35=AG35 -> TRUE
A36: 1889 | B36: ChIJ-4A36u6xEmsRR7nQMSPB8ms | C36: jose santos | D36: ChIJ-4A36u6xEmsRR7nQMSPB8msjose santos | E36: 2 | F36: 5 years ago | G36: There is no scale, no water, no tube, no slide, no trash can, etc. | H36: Raleigh Park Playground | I36: 83281 | J36: 2020-10-11 | K36: {"overall_sentiment":"negative","aspects":[{"aspect":"scale","category":"facility","sentiment":"negative","evidence_span":"no scale"},{"aspect":"water","category":"facility","sentiment":"negative","evidence_span":"no water"},{"aspect":"tube","category":"equipment","sentiment":"negative","evidence_span":"no tube"},{"aspect":"slide","category":"facility","sentiment":"negative","evidence_span":"no slide"},{"aspect":"trash can","category":"facility","sentiment":"negative","evidence_span":"no trash can"}]} | L36: {'sentence': 'There is no scale , no water , no tube , no slide , no trash can , etc .', 'IOB': ['O', 'O', 'O', 'B-ASP', 'O', 'O', 'B-ASP', 'O', 'O', 'O', 'O', 'O', 'B-ASP', 'O', 'O', 'O', 'O', 'O', 'O', 'O'], 'tokens': ['There', 'is', 'no', 'scale', ',', 'no', 'water', ',', 'no', 'tube', ',', 'no', 'slide', ',', 'no', 'trash', 'can', ',', 'etc', '.'], 'aspect': ['scale', 'water', 'slide'], 'position': [[3], [6], [12]], 'sentiment': ['Neutral', 'Neutral', 'Neutral'], 'probs': [[0.09971987456083298, 0.8976886868476868, 0.0025914846919476986], [0.013032023794949055, 0.9855910539627075, 0.0013769575161859393], [0.11930452287197113, 0.8754032850265503, 0.005292248912155628]], 'confidence': [0.8977, 0.9856, 0.8754]} | M36: 1 | N36: 5 | O36: 3 | P36: =_xlfn.XLOOKUP(B36,'g1'!B:B,'g1'!R:R) -> 5 | Q36: =_xlfn.XLOOKUP(B36,'g2'!B:B,'g2'!U:U) -> 5 | R36: =_xlfn.XLOOKUP(B36,'g3'!B:B,'g3'!R:R) -> 5 | S36: =_xlfn.XLOOKUP(D36,'g4'!D:D,'g4'!N:N) -> 5 | T36: =$N36-P36 -> 0 | U36: =$N36-Q36 -> 0 | V36: =$N36-R36 -> 0 | W36: =$N36-S36 -> 0 | X36: [{'aspect': 'scale', 'opinion': 'no scale', 'sentiment': 'negative'}, {'aspect': 'water', 'opinion': 'no water', 'sentiment': 'negative'}, {'aspect': 'tube', 'opinion': 'no tube', 'sentiment': 'negative'}, {'aspect': 'slide', 'opinion': 'no slide', 'sentiment': 'negative'}, {'aspect': 'trash can', 'opinion': 'no trash can', 'sentiment': 'negative'}] | Y36: =FIND("[{",K36) -> 43 | Z36: =FIND("category",K36) -> 63 | AA36: =Z36-Y36-2 -> 18 | AB36: scale | AD36: =FIND("[{",X36) -> 1 | AE36: =FIND("opinion",X36) -> 23 | AF36: =AE36-AD36-2 -> 20 | AG36: scale | AH36: =AB36=AG36 -> TRUE
A37: 478 | B37: ChIJu5XL1v0EkWsRWxalOCXAcb8 | C37: Maz | D37: ChIJu5XL1v0EkWsRWxalOCXAcb8Maz | E37: 2 | F37: 3 years ago | G37: The floors in this night club smell and it is always overpacked. There’s never any aircon. The womens toilets are always blocked or out of order by 11pm. At least when I was there a few weeks ago, the music was better. | H37: Casablanca Gold Coast | I37: 13943 | J37: 2022-10-11 | K37: {"overall_sentiment":"negative","aspects":[{"aspect":"floors","category":"cleanliness","sentiment":"negative","evidence_span":"smell"},{"aspect":"crowd","category":"crowding","sentiment":"negative","evidence_span":"overpacked"},{"aspect":"aircon","category":"facilities","sentiment":"negative","evidence_span":"never any aircon"},{"aspect":"toilets","category":"facilities","sentiment":"negative","evidence_span":"blocked"},{"aspect":"music","category":"entertainment","sentiment":"positive","evidence_span":"music was better"}]} | L37: {'sentence': 'The floors in this night club smell and it is always overpacked . There ’ s never any aircon . The womens toilets are always blocked or out of order by 11pm . \n At least when I was there a few weeks ago , the music was better .', 'IOB': ['O', 'O', 'O', 'O', 'O', 'O', 'O', 'O', 'O', 'O', 'O', 'O', 'O', 'O', 'O', 'O', 'O', 'O', 'O', 'O', 'O', 'O', 'B-ASP', 'O', 'O', 'O', 'O', 'O', 'O', 'O', 'O', 'O', 'O', 'O', 'O', 'O', 'O', 'O', 'O', 'O', 'O', 'O', 'O', 'O', 'O', 'B-ASP', 'O', 'O', 'O', '[SEP]'], 'tokens': ['The', 'floors', 'in', 'this', 'night', 'club', 'smell', 'and', 'it', 'is', 'always', 'overpacked', '.', 'There', '’', 's', 'never', 'any', 'aircon', '.', 'The', 'womens', 'toilets', 'are', 'always', 'blocked', 'or', 'out', 'of', 'order', 'by', '11pm', '.', '\n', 'At', 'least', 'when', 'I', 'was', 'there', 'a', 'few', 'weeks', 'ago', ',', 'the', 'music', 'was', 'better', '.'], 'aspect': ['toilets', 'the'], 'position': [[22], [45]], 'sentiment': ['Negative', 'Positive'], 'probs': [[0.9962812066078186, 0.0034919949248433113, 0.00022688954777549952], [0.000673718866892159, 0.00027041471912525594, 0.999055802822113]], 'confidence': [0.9963, 0.9991]} | M37: 1 | N37: 5 | O37: 2 | P37: =_xlfn.XLOOKUP(B37,'g1'!B:B,'g1'!R:R) -> 5 | Q37: =_xlfn.XLOOKUP(B37,'g2'!B:B,'g2'!U:U) -> 5 | R37: =_xlfn.XLOOKUP(B37,'g3'!B:B,'g3'!R:R) -> 5 | S37: =_xlfn.XLOOKUP(D37,'g4'!D:D,'g4'!N:N) -> 5 | T37: =$N37-P37 -> 0 | U37: =$N37-Q37 -> 0 | V37: =$N37-R37 -> 0 | W37: =$N37-S37 -> 0 | X37: [{'aspect': 'floors', 'opinion': 'smell', 'sentiment': 'negative'}, {'aspect': 'aircon', 'opinion': 'no aircon', 'sentiment': 'negative'}, {'aspect': 'toilets', 'opinion': 'blocked or out of order', 'sentiment': 'negative'}, {'aspect': 'music', 'opinion': 'better', 'sentiment': 'positive'}, {'aspect': 'crowd', 'opinion': 'overpacked', 'sentiment': 'negative'}] | Y37: =FIND("[{",K37) -> 43 | Z37: =FIND("category",K37) -> 64 | AA37: =Z37-Y37-2 -> 19 | AB37: floors | AD37: =FIND("[{",X37) -> 1 | AE37: =FIND("opinion",X37) -> 24 | AF37: =AE37-AD37-2 -> 21 | AG37: floors | AH37: =AB37=AG37 -> TRUE
A38: 604 | B38: ChIJy5rTDTavEmsRMzWjIWyf0yw | C38: Alex F | D38: ChIJy5rTDTavEmsRMzWjIWyf0ywAlex F | E38: 2 | F38: a year ago | G38: Service was great but food a complete let down. Got the set menu and the dishes were average at best. The saving grace was the foccacia with black garlic butter and pasta dish. Delicious. Save your money and go to Grana downstairs instead. … | H38: Lana | I38: 2936 | J38: 2024-10-10 | K38: {"overall_sentiment":"negative","aspects":[{"aspect":"service","category":"service","sentiment":"positive","evidence_span":"Service was great"},{"aspect":"food","category":"food","sentiment":"negative","evidence_span":"complete let down"},{"aspect":"dishes","category":"food","sentiment":"negative","evidence_span":"average at best"},{"aspect":"foccacia","category":"food","sentiment":"positive","evidence_span":"Delicious."},{"aspect":"pasta","category":"food","sentiment":"positive","evidence_span":"Delicious."}]} | L38: {'sentence': 'Service was great but food a complete let down . Got the set menu and the dishes were average at best . The saving grace was the foccacia with black garlic butter and pasta dish . Delicious . Save your money and go to Grana downstairs instead . …', 'IOB': ['B-ASP', 'O', 'O', 'O', 'B-ASP', 'O', 'O', 'O', 'O', 'O', 'O', 'O', 'O', 'O', 'O', 'O', 'O', 'O', 'O', 'O', 'O', 'O', 'O', 'O', 'O', 'O', 'O', 'B-ASP', 'O', 'O', 'O', 'O', 'O', 'O', 'O', 'O', 'O', 'O', 'O', 'O', 'O', 'O', 'O', 'O', 'O', 'O', 'O', 'O', 'O'], 'tokens': ['Service', 'was', 'great', 'but', 'food', 'a', 'complete', 'let', 'down', '.', 'Got', 'the', 'set', 'menu', 'and', 'the', 'dishes', 'were', 'average', 'at', 'best', '.', 'The', 'saving', 'grace', 'was', 'the', 'foccacia', 'with', 'black', 'garlic', 'butter', 'and', 'pasta', 'dish', '.', 'Delicious', '.', 'Save', 'your', 'money', 'and', 'go', 'to', 'Grana', 'downstairs', 'instead', '.', '…'], 'aspect': ['Service', 'food', 'foccacia'], 'position': [[0], [4], [27]], 'sentiment': ['Negative', 'Negative', 'Positive'], 'probs': [[0.9713393449783325, 0.021740635856986046, 0.006920000072568655], [0.9652400612831116, 0.03398767486214638, 0.0007722192094661295], [0.000946800340898335, 0.0003159782208967954, 0.9987372756004333]], 'confidence': [0.9713, 0.9652, 0.9987]} | M38: 1 | N38: 5 | O38: 3 | P38: =_xlfn.XLOOKUP(B38,'g1'!B:B,'g1'!R:R) -> 5 | Q38: =_xlfn.XLOOKUP(B38,'g2'!B:B,'g2'!U:U) -> 4 | R38: =_xlfn.XLOOKUP(B38,'g3'!B:B,'g3'!R:R) -> 5 | S38: =_xlfn.XLOOKUP(D38,'g4'!D:D,'g4'!N:N) -> 5 | T38: =$N38-P38 -> 0 | U38: =$N38-Q38 -> 1 | V38: =$N38-R38 -> 0 | W38: =$N38-S38 -> 0 | X38: [{'aspect': 'service', 'opinion': 'great', 'sentiment': 'positive'}, {'aspect': 'food', 'opinion': 'a complete let down', 'sentiment': 'negative'}, {'aspect': 'dishes', 'opinion': 'average at best', 'sentiment': 'negative'}, {'aspect': 'foccacia', 'opinion': 'delicious', 'sentiment': 'positive'}, {'aspect': 'pasta', 'opinion': 'delicious', 'sentiment': 'positive'}] | Y38: =FIND("[{",K38) -> 43 | Z38: =FIND("category",K38) -> 65 | AA38: =Z38-Y38-2 -> 20 | AB38: service | AD38: =FIND("[{",X38) -> 1 | AE38: =FIND("opinion",X38) -> 25 | AF38: =AE38-AD38-2 -> 22 | AG38: service | AH38: =AB38=AG38 -> TRUE
A39: 619 | B39: ChIJjwxCHDO_12oRreezlXFG79U | C39: Maria Dawes | D39: ChIJjwxCHDO_12oRreezlXFG79UMaria Dawes | E39: 3 | F39: 7 years ago | G39: I'd give it 5 stars for the beauty of the spot, but: there's limited parking, mostly walk-in camping, and there are regular groups of dirtbikers on weekends passing through the site on the road which dissects the campground. If you're camping mid-week during school term it's probably perfect! | H39: Andersons Garden | I39: 15771 | J39: 2018-10-12 | K39: {"overall_sentiment":"neutral","aspects":[{"aspect":"beauty","category":"environment","sentiment":"positive","evidence_span":"beauty"},{"aspect":"parking","category":"facilities","sentiment":"negative","evidence_span":"limited parking"},{"aspect":"walk-in camping","category":"facilities","sentiment":"negative","evidence_span":"walk-in camping"},{"aspect":"dirtbikers","category":"noise","sentiment":"negative","evidence_span":"dirtbikers"},{"aspect":"mid-week camping","category":"availability","sentiment":"positive","evidence_span":"camping mid-week"}]} | L39: {'sentence': "I ' d give it 5 stars for the beauty of the spot , but : there ' s limited parking , mostly walk - in camping , and there are regular groups of dirtbikers on weekends passing through the site on the road which dissects the campground . If you ' re camping mid - week during school term it ' s probably perfect !", 'IOB': ['O', 'O', 'O', 'O', 'O', 'O', 'O', 'O', 'O', 'O', 'O', 'O', 'B-ASP', 'O', 'O', 'O', 'O', 'O', 'O', 'O', 'O', 'O', 'O', 'O', 'O', 'O', 'O', 'O', 'O', 'O', 'O', 'O', 'O', 'O', 'O', 'O', 'O', 'O', 'O', 'O', 'O', 'O', 'O', 'O', 'O', 'O', 'O', 'O', 'O', 'O', 'O', 'O', 'O', 'O', 'O', 'O', 'O', 'O', 'O', 'O', 'O', 'O', 'O', 'O', 'O', 'O'], 'tokens': ['I', "'", 'd', 'give', 'it', '5', 'stars', 'for', 'the', 'beauty', 'of', 'the', 'spot', ',', 'but', ':', 'there', "'", 's', 'limited', 'parking', ',', 'mostly', 'walk', '-', 'in', 'camping', ',', 'and', 'there', 'are', 'regular', 'groups', 'of', 'dirtbikers', 'on', 'weekends', 'passing', 'through', 'the', 'site', 'on', 'the', 'road', 'which', 'dissects', 'the', 'campground', '.', 'If', 'you', "'", 're', 'camping', 'mid', '-', 'week', 'during', 'school', 'term', 'it', "'", 's', 'probably', 'perfect', '!'], 'aspect': ['spot'], 'position': [[12]], 'sentiment': ['Positive'], 'probs': [[0.012064271606504917, 0.0004809324746020138, 0.9874547719955444]], 'confidence': [0.9875]} | M39: 1 | N39: 5 | O39: 1 | P39: =_xlfn.XLOOKUP(B39,'g1'!B:B,'g1'!R:R) -> 5 | Q39: =_xlfn.XLOOKUP(B39,'g2'!B:B,'g2'!U:U) -> 5 | R39: =_xlfn.XLOOKUP(B39,'g3'!B:B,'g3'!R:R) -> 5 | S39: =_xlfn.XLOOKUP(D39,'g4'!D:D,'g4'!N:N) -> 5 | T39: =$N39-P39 -> 0 | U39: =$N39-Q39 -> 0 | V39: =$N39-R39 -> 0 | W39: =$N39-S39 -> 0 | X39: [{'aspect': 'beauty', 'opinion': '5 stars', 'sentiment': 'positive'}, {'aspect': 'parking', 'opinion': 'limited', 'sentiment': 'negative'}, {'aspect': 'camping', 'opinion': 'mostly walk-in', 'sentiment': 'negative'}, {'aspect': 'dirtbikers', 'opinion': 'regular groups of dirtbikers on weekends passing through the site', 'sentiment': 'negative'}, {'aspect': 'mid-week camping', 'opinion': 'probably perfect', 'sentiment': 'positive'}] | Y39: =FIND("[{",K39) -> 42 | Z39: =FIND("category",K39) -> 63 | AA39: =Z39-Y39-2 -> 19 | AB39: beauty | AD39: =FIND("[{",X39) -> 1 | AE39: =FIND("opinion",X39) -> 24 | AF39: =AE39-AD39-2 -> 21 | AG39: beauty | AH39: =AB39=AG39 -> TRUE
A40: 666 | B40: ChIJ2asGfJVGc2sRbIQIiN0KdRs | C40: Jess Burg | D40: ChIJ2asGfJVGc2sRbIQIiN0KdRsJess Burg | E40: 3 | F40: 6 years ago | G40: Lots of Mozzies. Equipment is good. But for children at least 4 or 5 and up. Few seats around. Shaded mostly from trees | H40: East Maitland Playground | I40: 52187 | J40: 2019-10-12 | K40: {"overall_sentiment":"neutral","aspects":[{"aspect":"mosquitoes","category":"pests","sentiment":"negative","evidence_span":"Lots of Mozzies"},{"aspect":"Equipment","category":"facilities","sentiment":"positive","evidence_span":"Equipment is good"},{"aspect":"Age","category":"suitability","sentiment":"negative","evidence_span":"4 or 5"},{"aspect":"Seats","category":"seating","sentiment":"negative","evidence_span":"Few seats"},{"aspect":"Shade","category":"environment","sentiment":"positive","evidence_span":"Shaded mostly"}]} | L40: {'sentence': 'Lots of Mozzies . Equipment is good . But for children at least 4 or 5 and up . Few seats around . Shaded mostly from trees', 'IOB': ['O', 'O', 'O', 'O', 'B-ASP', 'O', 'O', 'O', 'O', 'O', 'O', 'O', 'O', 'O', 'O', 'O', 'O', 'O', 'O', 'O', 'B-ASP', 'O', 'O', 'O', 'O', 'O', 'O'], 'tokens': ['Lots', 'of', 'Mozzies', '.', 'Equipment', 'is', 'good', '.', 'But', 'for', 'children', 'at', 'least', '4', 'or', '5', 'and', 'up', '.', 'Few', 'seats', 'around', '.', 'Shaded', 'mostly', 'from', 'trees'], 'aspect': ['Equipment', 'seats'], 'position': [[4], [20]], 'sentiment': ['Positive', 'Negative'], 'probs': [[0.40135446190834045, 0.0011145914904773235, 0.5975308418273926], [0.9936878085136414, 0.00608618650585413, 0.0002260588516946882]], 'confidence': [0.5975, 0.9937]} | M40: 1 | N40: 5 | O40: 2 | P40: =_xlfn.XLOOKUP(B40,'g1'!B:B,'g1'!R:R) -> 5 | Q40: =_xlfn.XLOOKUP(B40,'g2'!B:B,'g2'!U:U) -> 5 | R40: =_xlfn.XLOOKUP(B40,'g3'!B:B,'g3'!R:R) -> 5 | S40: =_xlfn.XLOOKUP(D40,'g4'!D:D,'g4'!N:N) -> 5 | T40: =$N40-P40 -> 0 | U40: =$N40-Q40 -> 0 | V40: =$N40-R40 -> 0 | W40: =$N40-S40 -> 0 | X40: [{'aspect': 'mosquitoes', 'opinion': 'Lots of Mozzies', 'sentiment': 'negative'}, {'aspect': 'play equipment', 'opinion': 'Equipment is good', 'sentiment': 'positive'}, {'aspect': 'age suitability', 'opinion': 'at least 4 or 5 and up', 'sentiment': 'negative'}, {'aspect': 'seating', 'opinion': 'Few seats around', 'sentiment': 'negative'}, {'aspect': 'shade', 'opinion': 'Shaded mostly from trees', 'sentiment': 'positive'}] | Y40: =FIND("[{",K40) -> 42 | Z40: =FIND("category",K40) -> 67 | AA40: =Z40-Y40-2 -> 23 | AB40: Mozzies | AD40: =FIND("[{",X40) -> 1 | AE40: =FIND("opinion",X40) -> 28 | AF40: =AE40-AD40-2 -> 25 | AG40: mosquitoes | AH40: =AB40=AG40 -> FALSE
A41: 729 | B41: ChIJQbaf77GFMioRq-9LMiQDX4I | C41: Sarah Daniels | D41: ChIJQbaf77GFMioRq-9LMiQDX4ISarah Daniels | E41: 3 | F41: 5 years ago | G41: Great tree too lookout and bridge.. very natural park. Few too many big rocks. | H41: The Rivergums Adventure Park | I41: 27186 | J41: 2020-10-11 | K41: {"overall_sentiment":"positive","aspects":[{"aspect":"tree","category":"nature","sentiment":"positive","evidence_span":"Great tree"},{"aspect":"lookout","category":"viewpoint","sentiment":"positive","evidence_span":"lookout"},{"aspect":"bridge","category":"structure","sentiment":"positive","evidence_span":"bridge"},{"aspect":"park","category":"environment","sentiment":"positive","evidence_span":"natural park"},{"aspect":"rocks","category":"terrain","sentiment":"negative","evidence_span":"big rocks"}]} | L41: {'sentence': 'Great tree too lookout and bridge . . very natural park . Few too many big rocks .', 'IOB': ['O', 'O', 'O', 'O', 'O', 'O', 'O', 'O', 'O', 'O', 'O', 'O', 'O', 'O', 'O', 'O', 'B-ASP', 'O'], 'tokens': ['Great', 'tree', 'too', 'lookout', 'and', 'bridge', '.', '.', 'very', 'natural', 'park', '.', 'Few', 'too', 'many', 'big', 'rocks', '.'], 'aspect': ['rocks'], 'position': [[16]], 'sentiment': ['Negative'], 'probs': [[0.9986839890480042, 0.0006064256886020303, 0.0007095219334587455]], 'confidence': [0.9987]} | M41: 1 | N41: 5 | O41: 1 | P41: =_xlfn.XLOOKUP(B41,'g1'!B:B,'g1'!R:R) -> 5 | Q41: =_xlfn.XLOOKUP(B41,'g2'!B:B,'g2'!U:U) -> 5 | R41: =_xlfn.XLOOKUP(B41,'g3'!B:B,'g3'!R:R) -> 5 | S41: =_xlfn.XLOOKUP(D41,'g4'!D:D,'g4'!N:N) -> 5 | T41: =$N41-P41 -> 0 | U41: =$N41-Q41 -> 0 | V41: =$N41-R41 -> 0 | W41: =$N41-S41 -> 0 | X41: [{'aspect': 'tree', 'opinion': 'Great', 'sentiment': 'positive'}, {'aspect': 'lookout', 'opinion': 'Great', 'sentiment': 'positive'}, {'aspect': 'bridge', 'opinion': 'Great', 'sentiment': 'positive'}, {'aspect': 'park', 'opinion': 'very natural', 'sentiment': 'positive'}, {'aspect': 'big rocks', 'opinion': 'Few too many', 'sentiment': 'negative'}] | Y41: =FIND("[{",K41) -> 43 | Z41: =FIND("category",K41) -> 62 | AA41: =Z41-Y41-2 -> 17 | AB41: tree | AD41: =FIND("[{",X41) -> 1 | AE41: =FIND("opinion",X41) -> 22 | AF41: =AE41-AD41-2 -> 19 | AG41: tree | AH41: =AB41=AG41 -> TRUE
A42: 733 | B42: ChIJffG3WlvacmsRjjycWw_i86Q | C42: Terry Fear | D42: ChIJffG3WlvacmsRjjycWw_i86QTerry Fear | E42: 4 | F42: 8 years ago | G42: Friendly staff, great beer selections, awesome restaurant, great members rewards program and regular entertainment events make this place great! | H42: The Ary Toukley | I42: 2379 | J42: 2017-10-12 | K42: {"overall_sentiment":"positive","aspects":[{"aspect":"staff","category":"service","sentiment":"positive","evidence_span":"Friendly staff"},{"aspect":"beer selections","category":"beverage","sentiment":"positive","evidence_span":"great beer selections"},{"aspect":"restaurant","category":"food","sentiment":"positive","evidence_span":"awesome restaurant"},{"aspect":"members rewards program","category":"membership","sentiment":"positive","evidence_span":"members rewards program"},{"aspect":"entertainment events","category":"entertainment","sentiment":"positive","evidence_span":"entertainment events"}]} | L42: {'sentence': 'Friendly staff , great beer selections , awesome restaurant , great members rewards program and regular entertainment events make this place great !', 'IOB': ['O', 'B-ASP', 'O', 'O', 'B-ASP', 'I-ASP', 'O', 'O', 'O', 'O', 'O', 'O', 'O', 'O', 'O', 'B-ASP', 'I-ASP', 'I-ASP', 'O', 'O', 'O', 'O', 'O'], 'tokens': ['Friendly', 'staff', ',', 'great', 'beer', 'selections', ',', 'awesome', 'restaurant', ',', 'great', 'members', 'rewards', 'program', 'and', 'regular', 'entertainment', 'events', 'make', 'this', 'place', 'great', '!'], 'aspect': ['staff', 'beer selections', 'regular entertainment events'], 'position': [[1], [4, 5], [15, 16, 17]], 'sentiment': ['Positive', 'Positive', 'Positive'], 'probs': [[0.0003868507337756455, 0.0002521418209653348, 0.9993610978126526], [0.00027491329819895327, 0.00023056467762216926, 0.9994945526123047], [0.00014627336349803954, 0.00038383991341106594, 0.9994698166847229]], 'confidence': [0.9994, 0.9995, 0.9995]} | M42: 1 | N42: 5 | O42: 3 | P42: =_xlfn.XLOOKUP(B42,'g1'!B:B,'g1'!R:R) -> 5 | Q42: =_xlfn.XLOOKUP(B42,'g2'!B:B,'g2'!U:U) -> 5 | R42: =_xlfn.XLOOKUP(B42,'g3'!B:B,'g3'!R:R) -> 5 | S42: =_xlfn.XLOOKUP(D42,'g4'!D:D,'g4'!N:N) -> 5 | T42: =$N42-P42 -> 0 | U42: =$N42-Q42 -> 0 | V42: =$N42-R42 -> 0 | W42: =$N42-S42 -> 0 | X42: [{'aspect': 'staff', 'opinion': 'friendly', 'sentiment': 'positive'}, {'aspect': 'beer selections', 'opinion': 'great', 'sentiment': 'positive'}, {'aspect': 'restaurant', 'opinion': 'awesome', 'sentiment': 'positive'}, {'aspect': 'members rewards program', 'opinion': 'great', 'sentiment': 'positive'}, {'aspect': 'entertainment events', 'opinion': 'regular', 'sentiment': 'neutral'}] | Y42: =FIND("[{",K42) -> 43 | Z42: =FIND("category",K42) -> 63 | AA42: =Z42-Y42-2 -> 18 | AB42: staff | AD42: =FIND("[{",X42) -> 1 | AE42: =FIND("opinion",X42) -> 23 | AF42: =AE42-AD42-2 -> 20 | AG42: staff | AH42: =AB42=AG42 -> TRUE
A43: 1287 | B43: ChIJ8aT5zxm9JmsRn45zE4LgI4w | C43: Amanda Wood | D43: ChIJ8aT5zxm9JmsRn45zE4LgI4wAmanda Wood | E43: 4 | F43: Edited a year ago | G43: Enjoyable meal, great atmosphere, very clean throughout. Friendly staff, child friendly which is always a bonus | H43: Club Savoy | I43: 15161 | J43: 2024-10-10 | K43: { "overall_sentiment": "positive", "aspects": [ { "aspect": "meal", "category": "food", "sentiment": "positive", "evidence_span": "Enjoyable meal" }, { "aspect": "atmosphere", "category": "ambience", "sentiment": "positive", "evidence_span": "great atmosphere" }, { "aspect": "cleanliness", "category": "facilities", "sentiment": "positive", "evidence_span": "very clean" }, { "aspect": "staff", "category": "service", "sentiment": "positive", "evidence_span": "Friendly staff" }, { "aspect": "child friendly", "category": "family", "sentiment": "positive", "evidence_span": "child friendly" } ] } | L43: {'sentence': 'Enjoyable meal , great atmosphere , very clean throughout . Friendly staff , child friendly which is always a bonus', 'IOB': ['O', 'B-ASP', 'O', 'O', 'B-ASP', 'O', 'O', 'O', 'O', 'O', 'O', 'B-ASP', 'O', 'O', 'O', 'O', 'O', 'O', 'O', 'O'], 'tokens': ['Enjoyable', 'meal', ',', 'great', 'atmosphere', ',', 'very', 'clean', 'throughout', '.', 'Friendly', 'staff', ',', 'child', 'friendly', 'which', 'is', 'always', 'a', 'bonus'], 'aspect': ['meal', 'atmosphere', 'staff'], 'position': [[1], [4], [11]], 'sentiment': ['Positive', 'Positive', 'Positive'], 'probs': [[0.00023294832499232143, 0.00029837823240086436, 0.9994687438011169], [0.00017827324336394668, 0.00032561676925979555, 0.9994961023330688], [0.00025692820781841874, 0.00030838706879876554, 0.999434769153595]], 'confidence': [0.9995, 0.9995, 0.9994]} | M43: 1 | N43: 5 | O43: 3 | P43: =_xlfn.XLOOKUP(B43,'g1'!B:B,'g1'!R:R) -> 5 | Q43: =_xlfn.XLOOKUP(B43,'g2'!B:B,'g2'!U:U) -> 5 | R43: =_xlfn.XLOOKUP(B43,'g3'!B:B,'g3'!R:R) -> 5 | S43: =_xlfn.XLOOKUP(D43,'g4'!D:D,'g4'!N:N) -> 5 | T43: =$N43-P43 -> 0 | U43: =$N43-Q43 -> 0 | V43: =$N43-R43 -> 0 | W43: =$N43-S43 -> 0 | X43: [{'aspect': 'meal', 'opinion': 'Enjoyable', 'sentiment': 'positive'}, {'aspect': 'atmosphere', 'opinion': 'great', 'sentiment': 'positive'}, {'aspect': 'cleanliness', 'opinion': 'very clean', 'sentiment': 'positive'}, {'aspect': 'staff', 'opinion': 'Friendly', 'sentiment': 'positive'}, {'aspect': 'child-friendliness', 'opinion': 'child friendly', 'sentiment': 'positive'}] | Y43: =FIND("[{",K43) -> #VALUE! | Z43: =FIND("category",K43) -> 90 | AA43: =Z43-Y43-2 -> #VALUE! | AB43: #VALUE! | AD43: =FIND("[{",X43) -> 1 | AE43: =FIND("opinion",X43) -> 22 | AF43: =AE43-AD43-2 -> 19 | AG43: meal | AH43: =AB43=AG43 -> #VALUE!
A44: 1347 | B44: ChIJSYkwfoMHdmsRcgxTI-xnlFc | C44: Phil Darnton | D44: ChIJSYkwfoMHdmsRcgxTI-xnlFcPhil Darnton | E44: 5 | F44: a year ago | G44: Amazing park, something for everyone. Great bowl, excellent flow, great street obstacles, pump track is great. Very … | H44: Lake Cathie Skatepark | I44: 81633 | J44: 2024-10-10 | K44: {"overall_sentiment":"positive","aspects":[{"aspect":"park","category":"facility","sentiment":"positive","evidence_span":"Amazing park"},{"aspect":"bowl","category":"feature","sentiment":"positive","evidence_span":"Great bowl"},{"aspect":"flow","category":"feature","sentiment":"positive","evidence_span":"excellent flow"},{"aspect":"street obstacles","category":"feature","sentiment":"positive","evidence_span":"great street obstacles"},{"aspect":"pump track","category":"feature","sentiment":"positive","evidence_span":"track is great"}]} | L44: {'sentence': 'Amazing park , something for everyone . \n \n Great bowl , excellent flow , great street obstacles , pump track is great . Very …', 'IOB': ['O', 'B-ASP', 'O', 'O', 'O', 'O', 'O', 'O', 'B-ASP', 'O', 'O', 'O', 'O', 'O', 'O', 'O', 'O', 'O', 'O', 'O', 'O', 'O', 'O', 'O', '[SEP]', 'O'], 'tokens': ['Amazing', 'park', ',', 'something', 'for', 'everyone', '.', '\n', '\n', 'Great', 'bowl', ',', 'excellent', 'flow', ',', 'great', 'street', 'obstacles', ',', 'pump', 'track', 'is', 'great', '.', 'Very', '…'], 'aspect': ['park', '\n'], 'position': [[1], [8]], 'sentiment': ['Positive', 'Positive'], 'probs': [[0.0003774578799493611, 0.00028189781005494297, 0.9993407130241394], [0.000261371344095096, 0.0002680735196918249, 0.9994705319404602]], 'confidence': [0.9993, 0.9995]} | M44: 1 | N44: 5 | O44: 2 | P44: =_xlfn.XLOOKUP(B44,'g1'!B:B,'g1'!R:R) -> 5 | Q44: =_xlfn.XLOOKUP(B44,'g2'!B:B,'g2'!U:U) -> 5 | R44: =_xlfn.XLOOKUP(B44,'g3'!B:B,'g3'!R:R) -> 5 | S44: =_xlfn.XLOOKUP(D44,'g4'!D:D,'g4'!N:N) -> 5 | T44: =$N44-P44 -> 0 | U44: =$N44-Q44 -> 0 | V44: =$N44-R44 -> 0 | W44: =$N44-S44 -> 0 | X44: [{'aspect': 'bowl', 'opinion': 'great bowl', 'sentiment': 'positive'}, {'aspect': 'street obstacles', 'opinion': 'great street obstacles', 'sentiment': 'positive'}, {'aspect': 'pump track', 'opinion': 'pump track is great', 'sentiment': 'positive'}, {'aspect': 'flow', 'opinion': 'excellent flow', 'sentiment': 'positive'}, {'aspect': 'park', 'opinion': 'Amazing park', 'sentiment': 'positive'}] | Y44: =FIND("[{",K44) -> 43 | Z44: =FIND("category",K44) -> 62 | AA44: =Z44-Y44-2 -> 17 | AB44: park | AD44: =FIND("[{",X44) -> 1 | AE44: =FIND("opinion",X44) -> 22 | AF44: =AE44-AD44-2 -> 19 | AG44: bowl | AH44: =AB44=AG44 -> FALSE
A45: 1773 | B45: ChIJIYfmRRK6FWsREfBq2NJBtR4 | C45: Kristine de castro | D45: ChIJIYfmRRK6FWsREfBq2NJBtR4Kristine de castro | E45: 5 | F45: a year ago | G45: Quiet and relaxing campsite. Lots of lovely birds and animals around. Loved the fact that it has barbecues, toilet and shower | H45: Pebbly Beach Campground | I45: 7391 | J45: 2024-10-10 | K45: {"overall_sentiment":"positive","aspects":[{"aspect":"campsite","category":"ambience","sentiment":"positive","evidence_span":"Quiet and relaxing"},{"aspect":"birds and animals","category":"nature","sentiment":"positive","evidence_span":"birds and animals"},{"aspect":"barbecues","category":"facilities","sentiment":"positive","evidence_span":"barbecues"},{"aspect":"toilet","category":"facilities","sentiment":"positive","evidence_span":"toilet"},{"aspect":"shower","category":"facilities","sentiment":"positive","evidence_span":"shower"}]} | L45: {'sentence': 'Quiet and relaxing campsite . Lots of lovely birds and animals around . Loved the fact that it has barbecues , toilet and shower', 'IOB': ['O', 'O', 'O', 'B-ASP', 'O', 'O', 'O', 'O', 'B-ASP', 'O', 'O', 'O', 'O', 'O', 'O', 'O', 'O', 'O', 'O', 'B-ASP', 'O', 'O', 'O', 'O'], 'tokens': ['Quiet', 'and', 'relaxing', 'campsite', '.', 'Lots', 'of', 'lovely', 'birds', 'and', 'animals', 'around', '.', 'Loved', 'the', 'fact', 'that', 'it', 'has', 'barbecues', ',', 'toilet', 'and', 'shower'], 'aspect': ['campsite', 'birds', 'barbecues'], 'position': [[3], [8], [19]], 'sentiment': ['Positive', 'Positive', 'Neutral'], 'probs': [[0.0004662097489926964, 0.00020114010840188712, 0.9993327260017395], [0.0003173404256813228, 0.00020736583974212408, 0.9994754195213318], [0.00019182830874342471, 0.9806962609291077, 0.019111914560198784]], 'confidence': [0.9993, 0.9995, 0.9807]} | M45: 1 | N45: =LEN(K45)-LEN(SUBSTITUTE(K45,"{",""))-1 -> 5 | O45: 3 | P45: =_xlfn.XLOOKUP(B45,'g1'!B:B,'g1'!R:R) -> 6 | Q45: =_xlfn.XLOOKUP(B45,'g2'!B:B,'g2'!U:U) -> 6 | R45: =_xlfn.XLOOKUP(B45,'g3'!B:B,'g3'!R:R) -> 3 | S45: =_xlfn.XLOOKUP(D45,'g4'!D:D,'g4'!N:N) -> 5 | T45: =$N45-P45 -> -1 | U45: =$N45-Q45 -> -1 | V45: =$N45-R45 -> 2 | W45: =$N45-S45 -> 0 | X45: [{'aspect': 'campsite', 'opinion': 'quiet and relaxing', 'sentiment': 'positive'}, {'aspect': 'birds and animals', 'opinion': 'lots of lovely birds and animals', 'sentiment': 'positive'}, {'aspect': 'barbecues', 'opinion': 'loved the fact that it has', 'sentiment': 'positive'}, {'aspect': 'toilet', 'opinion': 'loved the fact that it has toilet', 'sentiment': 'positive'}, {'aspect': 'shower', 'opinion': 'loved the fact that it has shower', 'sentiment': 'positive'}] | Y45: =FIND("[{",K45) -> 43 | Z45: =FIND("category",K45) -> 66 | AA45: =Z45-Y45-2 -> 21 | AB45: atmosphere | AD45: =FIND("[{",X45) -> 1 | AE45: =FIND("opinion",X45) -> 26 | AF45: =AE45-AD45-2 -> 23 | AG45: campsite | AH45: =AB45=AG45 -> FALSE
A46: 1969 | B46: ChIJd_eFaDGwEmsRdL0W_8SmBHA | C46: Jinu Jacob | D46: ChIJd_eFaDGwEmsRdL0W_8SmBHAJinu Jacob | E46: 2 | F46: 2 years ago | G46: Good theatre… nice and clean…but small Screen and no sound effect at all… the other issue is to find a parking.. | H46: Dendy Cinemas Newtown | I46: 656 | J46: 2023-10-11 | K46: {"overall_sentiment":"negative","aspects":[{"aspect":"theatre","category":"facility","sentiment":"positive","evidence_span":"Good theatre"},{"aspect":"cleanliness","category":"cleanliness","sentiment":"positive","evidence_span":"nice and clean"},{"aspect":"size","category":"space","sentiment":"negative","evidence_span":"but small"},{"aspect":"sound effect","category":"audio","sentiment":"negative","evidence_span":"no sound effect"},{"aspect":"parking","category":"access","sentiment":"negative","evidence_span":"find a parking"}]} | L46: {'sentence': 'Good theatre … nice and clean … but small \n Screen and no sound effect at all … the other issue is to find a parking . .', 'IOB': ['O', 'B-ASP', 'O', 'O', 'O', 'O', 'O', 'O', 'O', 'B-ASP', 'O', 'O', 'O', 'O', 'O', 'O', 'O', 'O', 'O', 'O', 'O', 'O', 'O', 'O', 'O', 'O', 'O', '[SEP]'], 'tokens': ['Good', 'theatre', '…', 'nice', 'and', 'clean', '…', 'but', 'small', '\n', 'Screen', 'and', 'no', 'sound', 'effect', 'at', 'all', '…', 'the', 'other', 'issue', 'is', 'to', 'find', 'a', 'parking', '.', '.'], 'aspect': ['theatre', '\n'], 'position': [[1], [9]], 'sentiment': ['Positive', 'Negative'], 'probs': [[0.00020623861928470433, 0.0004284793685656041, 0.9993652701377869], [0.9986490607261658, 0.0011015924392268062, 0.0002494317595846951]], 'confidence': [0.9994, 0.9986]} | M46: 1 | N46: =LEN(K46)-LEN(SUBSTITUTE(K46,"{",""))-1 -> 5 | O46: 2 | P46: =_xlfn.XLOOKUP(B46,'g1'!B:B,'g1'!R:R) -> 6 | Q46: =_xlfn.XLOOKUP(B46,'g2'!B:B,'g2'!U:U) -> 4 | R46: =_xlfn.XLOOKUP(B46,'g3'!B:B,'g3'!R:R) -> 4 | S46: =_xlfn.XLOOKUP(D46,'g4'!D:D,'g4'!N:N) -> 5 | T46: =$N46-P46 -> -1 | U46: =$N46-Q46 -> 1 | V46: =$N46-R46 -> 1 | W46: =$N46-S46 -> 0 | X46: [{'aspect': 'theatre', 'opinion': 'good', 'sentiment': 'positive'}, {'aspect': 'cleanliness', 'opinion': 'nice and clean', 'sentiment': 'positive'}, {'aspect': 'screen', 'opinion': 'small', 'sentiment': 'negative'}, {'aspect': 'sound effects', 'opinion': 'no sound effect at all', 'sentiment': 'negative'}, {'aspect': 'parking', 'opinion': 'issue', 'sentiment': 'negative'}] | Y46: =FIND("[{",K46) -> 43 | Z46: =FIND("category",K46) -> 65 | AA46: =Z46-Y46-2 -> 20 | AB46: theatre | AD46: =FIND("[{",X46) -> 1 | AE46: =FIND("opinion",X46) -> 25 | AF46: =AE46-AD46-2 -> 22 | AG46: theatre | AH46: =AB46=AG46 -> TRUE
A47: 447 | B47: ChIJJ7KmbliAk2sRd2Wnuq4WoEU | C47: Mmac | D47: ChIJJ7KmbliAk2sRd2Wnuq4WoEUMmac | E47: 4 | F47: 6 years ago | G47: Lookout is ok. There are much better ones around. Did the 20k return walk from Kondalilla. Well signed good track. Quite a lot of uphill/downhill. Not much to see on the way but nice walk! | H47: Baroon Lookout | I47: 30626 | J47: 2019-10-12 | K47: {"overall_sentiment":"neutral","aspects":[{"aspect":"Lookout","category":"viewpoint","sentiment":"negative","evidence_span":"much better"},{"aspect":"signage","category":"amenity","sentiment":"positive","evidence_span":"Well signed"},{"aspect":"track","category":"trail","sentiment":"positive","evidence_span":"good track"},{"aspect":"scenery","category":"view","sentiment":"negative","evidence_span":"Not much"},{"aspect":"walk","category":"experience","sentiment":"positive","evidence_span":"nice walk"}]} | L47: {'sentence': 'Lookout is ok . There are much better ones around . Did the 20k return walk from Kondalilla . Well signed good track . Quite a lot of uphill / downhill . Not much to see on the way but nice walk !', 'IOB': ['O', 'O', 'O', 'O', 'O', 'O', 'O', 'O', 'O', 'O', 'O', 'O', 'O', 'O', 'O', 'O', 'O', 'O', 'O', 'O', 'O', 'O', 'B-ASP', 'O', 'O', 'O', 'O', 'O', 'O', 'O', 'O', 'O', 'O', 'O', 'O', 'O', 'O', 'O', 'O', 'O', 'O', 'O', 'O'], 'tokens': ['Lookout', 'is', 'ok', '.', 'There', 'are', 'much', 'better', 'ones', 'around', '.', 'Did', 'the', '20k', 'return', 'walk', 'from', 'Kondalilla', '.', 'Well', 'signed', 'good', 'track', '.', 'Quite', 'a', 'lot', 'of', 'uphill', '/', 'downhill', '.', 'Not', 'much', 'to', 'see', 'on', 'the', 'way', 'but', 'nice', 'walk', '!'], 'aspect': ['track'], 'position': [[22]], 'sentiment': ['Positive'], 'probs': [[0.047750141471624374, 0.0006533254054374993, 0.9515965580940247]], 'confidence': [0.9516]} | M47: 1 | N47: 5 | O47: 1 | P47: =_xlfn.XLOOKUP(B47,'g1'!B:B,'g1'!R:R) -> 6 | Q47: =_xlfn.XLOOKUP(B47,'g2'!B:B,'g2'!U:U) -> 6 | R47: =_xlfn.XLOOKUP(B47,'g3'!B:B,'g3'!R:R) -> 5 | S47: =_xlfn.XLOOKUP(D47,'g4'!D:D,'g4'!N:N) -> 5 | T47: =$N47-P47 -> -1 | U47: =$N47-Q47 -> -1 | V47: =$N47-R47 -> 0 | W47: =$N47-S47 -> 0 | X47: [{'aspect': 'lookout', 'opinion': 'much better ones around', 'sentiment': 'positive'}, {'aspect': 'walk', 'opinion': 'nice', 'sentiment': 'positive'}, {'aspect': 'track', 'opinion': 'good', 'sentiment': 'positive'}, {'aspect': 'signage', 'opinion': 'well signed', 'sentiment': 'positive'}, {'aspect': 'scenery', 'opinion': 'not much to see', 'sentiment': 'negative'}] | Y47: =FIND("[{",K47) -> 42 | Z47: =FIND("category",K47) -> 64 | AA47: =Z47-Y47-2 -> 20 | AB47: Lookout | AD47: =FIND("[{",X47) -> 1 | AE47: =FIND("opinion",X47) -> 25 | AF47: =AE47-AD47-2 -> 22 | AG47: lookout | AH47: =AB47=AG47 -> TRUE
A48: 672 | B48: ChIJN_nILqe8EmsR-64POaOIeC8 | C48: Tom Holland | D48: ChIJN_nILqe8EmsR-64POaOIeC8Tom Holland | E48: 4 | F48: 6 years ago | G48: Dooley's is a really big and very neat and new. Lots of games for the gamblers and sports bar with a huge family dinning area for all your food at reasonable prices. Make sure to wear shoes as it's an ESL and you have to and take off that hat young man! | H48: DOOLEYS Lidcombe Catholic Club | I48: 654 | J48: 2019-10-12 | K48: {"overall_sentiment":"positive","aspects":[{"aspect":"size","category":"ambience","sentiment":"positive","evidence_span":"really big"},{"aspect":"cleanliness","category":"cleanliness","sentiment":"positive","evidence_span":"very neat"},{"aspect":"games","category":"entertainment","sentiment":"positive","evidence_span":"Lots of games"},{"aspect":"dining area","category":"ambience","sentiment":"positive","evidence_span":"family dinning area"},{"aspect":"prices","category":"price","sentiment":"positive","evidence_span":"reasonable prices"}]} | L48: {'sentence': "Dooley ' s is a really big and very neat and new . Lots of games for the gamblers and sports bar with a huge family dinning area for all your food at reasonable prices . Make sure to wear shoes as it ' s an ESL and you have to and take off that hat young man !", 'IOB': ['O', 'O', 'O', 'O', 'O', 'O', 'O', 'O', 'O', 'O', 'O', 'O', 'O', 'O', 'O', 'O', 'O', 'O', 'O', 'O', 'O', 'B-ASP', 'O', 'O', 'O', 'B-ASP', 'I-ASP', 'I-ASP', 'O', 'O', 'O', 'O', 'O', 'O', 'B-ASP', 'O', 'O', 'O', 'O', 'O', 'O', 'O', 'O', 'O', 'O', 'O', 'O', 'O', 'O', 'O', 'O', 'O', 'O', 'O', 'O', 'O', 'O', 'O', 'O'], 'tokens': ['Dooley', "'", 's', 'is', 'a', 'really', 'big', 'and', 'very', 'neat', 'and', 'new', '.', 'Lots', 'of', 'games', 'for', 'the', 'gamblers', 'and', 'sports', 'bar', 'with', 'a', 'huge', 'family', 'dinning', 'area', 'for', 'all', 'your', 'food', 'at', 'reasonable', 'prices', '.', 'Make', 'sure', 'to', 'wear', 'shoes', 'as', 'it', "'", 's', 'an', 'ESL', 'and', 'you', 'have', 'to', 'and', 'take', 'off', 'that', 'hat', 'young', 'man', '!'], 'aspect': ['bar', 'family dinning area', 'prices'], 'position': [[21], [25, 26, 27], [34]], 'sentiment': ['Neutral', 'Positive', 'Neutral'], 'probs': [[0.00037044184864498675, 0.9960975646972656, 0.0035319337621331215], [0.00019375060219317675, 0.0046553704887628555, 0.9951509237289429], [0.001127540715970099, 0.5687622427940369, 0.4301101863384247]], 'confidence': [0.9961, 0.9952, 0.5688]} | M48: 1 | N48: =LEN(K48)-LEN(SUBSTITUTE(K48,"{",""))-1 -> 5 | O48: 3 | P48: =_xlfn.XLOOKUP(B48,'g1'!B:B,'g1'!R:R) -> 7 | Q48: =_xlfn.XLOOKUP(B48,'g2'!B:B,'g2'!U:U) -> 7 | R48: =_xlfn.XLOOKUP(B48,'g3'!B:B,'g3'!R:R) -> 4 | S48: =_xlfn.XLOOKUP(D48,'g4'!D:D,'g4'!N:N) -> 5 | T48: =$N48-P48 -> -2 | U48: =$N48-Q48 -> -2 | V48: =$N48-R48 -> 1 | W48: =$N48-S48 -> 0 | X48: [{'aspect': 'size', 'opinion': 'really big', 'sentiment': 'neutral'}, {'aspect': 'neatness', 'opinion': 'very neat', 'sentiment': 'neutral'}, {'aspect': 'newness', 'opinion': 'new', 'sentiment': 'neutral'}, {'aspect': 'dining area', 'opinion': 'family dining', 'sentiment': 'neutral'}, {'aspect': 'dress code', 'opinion': 'wear shoes, remove hat', 'sentiment': 'neutral'}] | Y48: =FIND("[{",K48) -> 43 | Z48: =FIND("category",K48) -> 62 | AA48: =Z48-Y48-2 -> 17 | AB48: space | AD48: =FIND("[{",X48) -> 1 | AE48: =FIND("opinion",X48) -> 22 | AF48: =AE48-AD48-2 -> 19 | AG48: size | AH48: =AB48=AG48 -> FALSE
A49: 816 | B49: ChIJb2cxPkcOnqoRKV5Mop9_h1M | C49: Denise Flipo | D49: ChIJb2cxPkcOnqoRKV5Mop9_h1MDenise Flipo | E49: 4 | F49: 3 years ago | G49: Very friendly service, nice atmosphere and generous servings of tasty, well-cooked food. | H49: Nelson Hotel | I49: 10682 | J49: 2022-10-11 | K49: {"overall_sentiment":"positive","aspects":[{"aspect":"service","category":"service","sentiment":"positive","evidence_span":"friendly service"},{"aspect":"atmosphere","category":"ambience","sentiment":"positive","evidence_span":"nice atmosphere"},{"aspect":"servings","category":"portion size","sentiment":"positive","evidence_span":"generous servings"},{"aspect":"food","category":"food","sentiment":"positive","evidence_span":"tasty"}]} | L49: {'sentence': 'Very friendly service , nice atmosphere and generous servings of tasty , well - cooked food .', 'IOB': ['O', 'O', 'B-ASP', 'O', 'O', 'B-ASP', 'O', 'O', 'B-ASP', 'O', 'O', 'O', 'O', 'O', 'O', 'B-ASP', 'O'], 'tokens': ['Very', 'friendly', 'service', ',', 'nice', 'atmosphere', 'and', 'generous', 'servings', 'of', 'tasty', ',', 'well', '-', 'cooked', 'food', '.'], 'aspect': ['service', 'atmosphere', 'servings', 'food'], 'position': [[2], [5], [8], [15]], 'sentiment': ['Positive', 'Positive', 'Positive', 'Positive'], 'probs': [[0.007080380339175463, 0.0077927312813699245, 0.9851269125938416], [0.0028140011709183455, 0.004987058229744434, 0.9921990036964417], [0.002799535170197487, 0.007047205697745085, 0.9901532530784607], [0.0029925077687948942, 0.011977968737483025, 0.9850295186042786]], 'confidence': [0.9851, 0.9922, 0.9902, 0.985]} | N49: =LEN(K49)-LEN(SUBSTITUTE(K49,"{",""))-1 -> 4 | O49: 4 | P49: =_xlfn.XLOOKUP(B49,'g1'!B:B,'g1'!R:R) -> 4 | Q49: =_xlfn.XLOOKUP(B49,'g2'!B:B,'g2'!U:U) -> 4 | R49: =_xlfn.XLOOKUP(B49,'g3'!B:B,'g3'!R:R) -> 3 | S49: =_xlfn.XLOOKUP(D49,'g4'!D:D,'g4'!N:N) -> 5 | T49: =$N49-P49 -> 0 | U49: =$N49-Q49 -> 0 | V49: =$N49-R49 -> 1 | W49: =$N49-S49 -> -1 | X49: [{'aspect': 'service', 'opinion': 'very friendly', 'sentiment': 'positive'}, {'aspect': 'atmosphere', 'opinion': 'nice', 'sentiment': 'positive'}, {'aspect': 'food', 'opinion': 'tasty', 'sentiment': 'positive'}, {'aspect': 'food', 'opinion': 'well-cooked', 'sentiment': 'positive'}, {'aspect': 'servings', 'opinion': 'generous', 'sentiment': 'positive'}] | Y49: =FIND("[{",K49) -> 43 | Z49: =FIND("category",K49) -> 65 | AA49: =Z49-Y49-2 -> 20 | AB49: service | AD49: =FIND("[{",X49) -> 1 | AE49: =FIND("opinion",X49) -> 25 | AF49: =AE49-AD49-2 -> 22 | AG49: service | AH49: =AB49=AG49 -> TRUE
A50: 1156 | B50: ChIJr28dSkhd1moR1rNfI5DI0Ww | C50: Jim Jackson | D50: ChIJr28dSkhd1moR1rNfI5DI0WwJim Jackson | E50: 4 | F50: 3 years ago | G50: O.K. Beautiful old building. Arriving late, we were treated very well by Security and Ushers. Seated behind the Baptismal Font, buried under a thousand candles, or so it seemed, Oh! and the Quintet were excellent, the lead fiddler's … | H50: St James’ Old Cathedral | I50: 20148 | J50: 2022-10-11 | K50: {"overall_sentiment":"positive","aspects":[{"aspect":"old building","category":"architecture","sentiment":"positive","evidence_span":"Beautiful old"},{"aspect":"security","category":"staff","sentiment":"positive","evidence_span":"treated very well"},{"aspect":"ushers","category":"staff","sentiment":"positive","evidence_span":"treated very well"},{"aspect":"quintet","category":"performance","sentiment":"positive","evidence_span":"were excellent"}]} | L50: {'sentence': "O . K . Beautiful old building . Arriving late , we were treated very well by Security and Ushers . Seated behind the Baptismal Font , buried under a thousand candles , or so it seemed , Oh ! and the Quintet were excellent , the lead fiddler ' s …", 'IOB': ['O', 'O', 'O', 'O', 'O', 'O', 'B-ASP', 'O', 'O', 'O', 'O', 'O', 'O', 'O', 'O', 'O', 'O', 'B-ASP', 'O', 'B-ASP', 'O', 'O', 'O', 'O', 'O', 'B-ASP', 'O', 'O', 'O', 'O', 'O', 'O', 'O', 'O', 'O', 'O', 'O', 'O', 'O', 'O', 'O', 'O', 'O', 'O', 'O', 'O', 'O', 'O', 'O', 'O', 'O', 'O'], 'tokens': ['O', '.', 'K', '.', 'Beautiful', 'old', 'building', '.', 'Arriving', 'late', ',', 'we', 'were', 'treated', 'very', 'well', 'by', 'Security', 'and', 'Ushers', '.', 'Seated', 'behind', 'the', 'Baptismal', 'Font', ',', 'buried', 'under', 'a', 'thousand', 'candles', ',', 'or', 'so', 'it', 'seemed', ',', 'Oh', '!', 'and', 'the', 'Quintet', 'were', 'excellent', ',', 'the', 'lead', 'fiddler', "'", 's', '…'], 'aspect': ['building', 'Security', 'Ushers', 'Font'], 'position': [[6], [17], [19], [25]], 'sentiment': ['Positive', 'Positive', 'Positive', 'Neutral'], 'probs': [[0.0002208143414463848, 0.0005973058869130909, 0.9991818070411682], [0.0004304844478610903, 0.0003430586657486856, 0.999226450920105], [0.0003993113641627133, 0.000655585725326091, 0.9989451766014099], [0.0004767817445099354, 0.9971069693565369, 0.0024162298068404198]], 'confidence': [0.9992, 0.9992, 0.9989, 0.9971]} | N50: =LEN(K50)-LEN(SUBSTITUTE(K50,"{",""))-1 -> 4 | O50: 4 | P50: =_xlfn.XLOOKUP(B50,'g1'!B:B,'g1'!R:R) -> 4 | Q50: =_xlfn.XLOOKUP(B50,'g2'!B:B,'g2'!U:U) -> 4 | R50: =_xlfn.XLOOKUP(B50,'g3'!B:B,'g3'!R:R) -> 4 | S50: =_xlfn.XLOOKUP(D50,'g4'!D:D,'g4'!N:N) -> 5 | T50: =$N50-P50 -> 0 | U50: =$N50-Q50 -> 0 | V50: =$N50-R50 -> 0 | W50: =$N50-S50 -> -1 | X50: [{'aspect': 'old building', 'opinion': 'Beautiful', 'sentiment': 'positive'}, {'aspect': 'security', 'opinion': 'treated very well', 'sentiment': 'positive'}, {'aspect': 'ushers', 'opinion': 'treated very well', 'sentiment': 'positive'}, {'aspect': 'baptismal font', 'opinion': 'buried under candles', 'sentiment': 'neutral'}, {'aspect': 'quintet', 'opinion': 'excellent', 'sentiment': 'positive'}] | Y50: =FIND("[{",K50) -> 43 | Z50: =FIND("category",K50) -> 70 | AA50: =Z50-Y50-2 -> 25 | AB50: building | AD50: =FIND("[{",X50) -> 1 | AE50: =FIND("opinion",X50) -> 30 | AF50: =AE50-AD50-2 -> 27 | AG50: old building | AH50: =AB50=AG50 -> FALSE
A51: 1761 | B51: ChIJWUmEMXAxt2oRXHhAk-0HHIc | C51: Stephen Williams | D51: ChIJWUmEMXAxt2oRXHhAk-0HHIcStephen Williams | E51: 4 | F51: 4 years ago | G51: Great place to visit. Large vaiety of jams, sauces and relishes. Cheap prices amd nice staff. Got some good variety packs for Christmas presents. | H51: Beerenberg Farm | I51: 387 | J51: 2021-10-11 | K51: {"overall_sentiment":"positive","aspects":[{"aspect":"place","category":"location","sentiment":"positive","evidence_span":"Great place"},{"aspect":"variety","category":"product","sentiment":"positive","evidence_span":"Large vaiety"},{"aspect":"prices","category":"price","sentiment":"positive","evidence_span":"Cheap prices"},{"aspect":"staff","category":"service","sentiment":"positive","evidence_span":"nice staff"}]} | L51: {'sentence': 'Great place to visit . Large vaiety of jams , sauces and relishes . Cheap prices amd nice staff . Got some good variety packs for Christmas presents .', 'IOB': ['O', 'B-ASP', 'O', 'O', 'O', 'O', 'O', 'O', 'O', 'O', 'B-ASP', 'O', 'O', 'O', 'O', 'B-ASP', 'O', 'O', 'B-ASP', 'O', 'O', 'O', 'O', 'O', 'O', 'O', 'O', 'O', 'O'], 'tokens': ['Great', 'place', 'to', 'visit', '.', 'Large', 'vaiety', 'of', 'jams', ',', 'sauces', 'and', 'relishes', '.', 'Cheap', 'prices', 'amd', 'nice', 'staff', '.', 'Got', 'some', 'good', 'variety', 'packs', 'for', 'Christmas', 'presents', '.'], 'aspect': ['place', 'sauces', 'prices', 'staff'], 'position': [[1], [10], [15], [18]], 'sentiment': ['Positive', 'Neutral', 'Positive', 'Positive'], 'probs': [[0.00040341864223591983, 0.00030594391864724457, 0.9992905855178833], [0.00038257436244748533, 0.650119423866272, 0.3494979441165924], [0.00014649025979451835, 0.0013242883142083883, 0.9985291957855225], [0.0002523554430808872, 0.00025886468938551843, 0.9994887113571167]], 'confidence': [0.9993, 0.6501, 0.9985, 0.9995]} | N51: =LEN(K51)-LEN(SUBSTITUTE(K51,"{",""))-1 -> 4 | O51: 4 | P51: =_xlfn.XLOOKUP(B51,'g1'!B:B,'g1'!R:R) -> 5 | Q51: =_xlfn.XLOOKUP(B51,'g2'!B:B,'g2'!U:U) -> 5 | R51: =_xlfn.XLOOKUP(B51,'g3'!B:B,'g3'!R:R) -> 4 | S51: =_xlfn.XLOOKUP(D51,'g4'!D:D,'g4'!N:N) -> 5 | T51: =$N51-P51 -> -1 | U51: =$N51-Q51 -> -1 | V51: =$N51-R51 -> 0 | W51: =$N51-S51 -> -1 | X51: [{'aspect': 'place', 'opinion': 'Great', 'sentiment': 'positive'}, {'aspect': 'jams, sauces, and relishes', 'opinion': 'Large variety', 'sentiment': 'positive'}, {'aspect': 'staff', 'opinion': 'nice', 'sentiment': 'positive'}, {'aspect': 'prices', 'opinion': 'Cheap', 'sentiment': 'positive'}, {'aspect': 'variety packs', 'opinion': 'good', 'sentiment': 'positive'}] | Y51: =FIND("[{",K51) -> 43 | Z51: =FIND("category",K51) -> 63 | AA51: =Z51-Y51-2 -> 18 | AB51: place | AD51: =FIND("[{",X51) -> 1 | AE51: =FIND("opinion",X51) -> 23 | AF51: =AE51-AD51-2 -> 20 | AG51: place | AH51: =AB51=AG51 -> TRUE
A52: 1959 | B52: ChIJFwC1lrJC1moRjtLuCpWlcF0 | C52: Brad Dalgleish | D52: ChIJFwC1lrJC1moRjtLuCpWlcF0Brad Dalgleish | E52: 2 | F52: Edited 4 months ago | G52: Terrible experience, the steak at $76 was a waste, the quality of meet was supermarket quality. Sunday surcharge is ok at 10% however between the menu and the booking system the venue charges more than the 10% on most items (round up to the … | H52: Left Bank Melbourne Restaurant & Cocktail Bar | I52: 128 | J52: 2025-06-12 | K52: {"overall_sentiment":"negative","aspects":[{'aspect': 'experience',"category":'experience', 'opinion': 'terrible', 'sentiment': 'negative'},{"aspect":"steak","category":"food","sentiment":"negative","evidence_span":"a waste"},{"aspect":"quality","category":"food","sentiment":"negative","evidence_span":"supermarket quality"},{"aspect":"surcharge","category":"price","sentiment":"neutral","evidence_span":"is ok"},{"aspect":"charges","category":"price","sentiment":"negative","evidence_span":"charges more"}]} | L52: {'sentence': 'Terrible experience , the steak at $ 76 was a waste , the quality of meet was supermarket quality . Sunday surcharge is ok at 10 % however between the menu and the booking system the venue charges more than the 10 % on most items ( round up to the …', 'IOB': ['O', 'O', 'O', 'O', 'B-ASP', 'O', 'O', 'O', 'O', 'O', 'O', 'O', 'O', 'O', 'O', 'O', 'O', 'O', 'O', 'O', 'O', 'O', 'O', 'O', 'O', 'O', 'O', 'O', 'O', 'O', 'O', 'O', 'O', 'O', 'O', 'O', 'B-ASP', 'O', 'O', 'O', 'O', 'O', 'O', 'O', 'O', 'O', 'O', 'O', 'O', 'O', 'O', 'O'], 'tokens': ['Terrible', 'experience', ',', 'the', 'steak', 'at', '$', '76', 'was', 'a', 'waste', ',', 'the', 'quality', 'of', 'meet', 'was', 'supermarket', 'quality', '.', 'Sunday', 'surcharge', 'is', 'ok', 'at', '10', '%', 'however', 'between', 'the', 'menu', 'and', 'the', 'booking', 'system', 'the', 'venue', 'charges', 'more', 'than', 'the', '10', '%', 'on', 'most', 'items', '(', 'round', 'up', 'to', 'the', '…'], 'aspect': ['steak', 'venue'], 'position': [[4], [36]], 'sentiment': ['Negative', 'Negative'], 'probs': [[0.9984789490699768, 0.0011553306831046939, 0.0003658322966657579], [0.8803490996360779, 0.11927656829357147, 0.0003743897832464427]], 'confidence': [0.9985, 0.8803]} | M52: 1 | N52: =LEN(K52)-LEN(SUBSTITUTE(K52,"{",""))-1 -> 5 | O52: 2 | P52: =_xlfn.XLOOKUP(B52,'g1'!B:B,'g1'!R:R) -> 4 | Q52: =_xlfn.XLOOKUP(B52,'g2'!B:B,'g2'!U:U) -> 5 | R52: =_xlfn.XLOOKUP(B52,'g3'!B:B,'g3'!R:R) -> 2 | S52: =_xlfn.XLOOKUP(D52,'g4'!D:D,'g4'!N:N) -> 5 | T52: =$N52-P52 -> 1 | U52: =$N52-Q52 -> 0 | V52: =$N52-R52 -> 3 | W52: =$N52-S52 -> 0 | X52: [{'aspect': 'experience', 'opinion': 'terrible', 'sentiment': 'negative'}, {'aspect': 'steak', 'opinion': 'a waste', 'sentiment': 'negative'}, {'aspect': 'meat', 'opinion': 'supermarket quality', 'sentiment': 'negative'}, {'aspect': 'surcharge', 'opinion': 'ok', 'sentiment': 'neutral'}, {'aspect': 'charges', 'opinion': 'more than the 10%', 'sentiment': 'negative'}] | Y52: =FIND("[{",K52) -> 43 | Z52: =FIND("category",K52) -> 69 | AA52: =Z52-Y52-2 -> 24 | AB52: steak | AD52: =FIND("[{",X52) -> 1 | AE52: =FIND("opinion",X52) -> 28 | AF52: =AE52-AD52-2 -> 25 | AG52: experience | AH52: =AB52=AG52 -> FALSE
A53: 1132 | B53: ChIJDyqzrEQ-MioR-60wmRIhmIo | C53: Yosh | D53: ChIJDyqzrEQ-MioR-60wmRIhmIoYosh | E53: 1 | F53: Edited 9 years ago | G53: f***ing freezing, no heating. hot showers so its ok I guess. But its real stuffy and everyones forced into the dorms and literally sleep on top of each other. | H53: Nanga Bush Camp | I53: 20551 | J53: 2016-10-12 | K53: {"overall_sentiment":"negative","aspects":[{"aspect":"cold","category":"environment","sentiment":"negative","evidence_span":"f***ing freezing"},{"aspect":"heating","category":"facilities","sentiment":"negative","evidence_span":"no heating"},{"aspect":"showers","category":"facilities","sentiment":"positive","evidence_span":"hot showers"},{"aspect":"crowding","category":"environment","sentiment":"negative","evidence_span":"sleep on top"}]} | L53: {'sentence': 'f * * * ing freezing , no heating . hot showers so its ok I guess . But its real stuffy and everyones forced into the dorms and literally sleep on top of each other .', 'IOB': ['O', 'O', 'O', 'O', 'O', 'O', 'O', 'O', 'O', 'O', 'O', 'O', 'O', 'O', 'O', 'O', 'O', 'O', 'O', 'O', 'O', 'O', 'O', 'O', 'O', 'O', 'O', 'B-ASP', 'O', 'O', 'O', 'O', 'O', 'O', 'O', 'O', 'O'], 'tokens': ['f', '*', '*', '*', 'ing', 'freezing', ',', 'no', 'heating', '.', 'hot', 'showers', 'so', 'its', 'ok', 'I', 'guess', '.', 'But', 'its', 'real', 'stuffy', 'and', 'everyones', 'forced', 'into', 'the', 'dorms', 'and', 'literally', 'sleep', 'on', 'top', 'of', 'each', 'other', '.'], 'aspect': ['dorms'], 'position': [[27]], 'sentiment': ['Negative'], 'probs': [[0.970660924911499, 0.029083525761961937, 0.0002554337843321264]], 'confidence': [0.9707]} | M53: 1 | N53: =LEN(K53)-LEN(SUBSTITUTE(K53,"{",""))-1 -> 4 | O53: 1 | P53: =_xlfn.XLOOKUP(B53,'g1'!B:B,'g1'!R:R) -> 4 | Q53: =_xlfn.XLOOKUP(B53,'g2'!B:B,'g2'!U:U) -> 4 | R53: =_xlfn.XLOOKUP(B53,'g3'!B:B,'g3'!R:R) -> 3 | S53: =_xlfn.XLOOKUP(D53,'g4'!D:D,'g4'!N:N) -> 5 | T53: =$N53-P53 -> 0 | U53: =$N53-Q53 -> 0 | V53: =$N53-R53 -> 1 | W53: =$N53-S53 -> -1 | X53: [{'aspect': 'cold', 'opinion': 'f***ing freezing', 'sentiment': 'negative'}, {'aspect': 'no heating', 'opinion': 'no heating', 'sentiment': 'negative'}, {'aspect': 'hot showers', 'opinion': 'hot showers so its ok', 'sentiment': 'positive'}, {'aspect': 'stuffy', 'opinion': 'its real stuffy', 'sentiment': 'negative'}, {'aspect': 'dorms', 'opinion': "everyone's forced into the dorms", 'sentiment': 'negative'}] | Y53: =FIND("[{",K53) -> 43 | Z53: =FIND("category",K53) -> 62 | AA53: =Z53-Y53-2 -> 17 | AB53: temperature | AD53: =FIND("[{",X53) -> 1 | AE53: =FIND("opinion",X53) -> 22 | AF53: =AE53-AD53-2 -> 19 | AG53: cold | AH53: =AB53=AG53 -> FALSE
A54: 29 | B54: ChIJeV1gv-axEmsRFXSXZZsx5Ns | C54: Rolf Bachmann | D54: ChIJeV1gv-axEmsRFXSXZZsx5NsRolf Bachmann | E54: 4 | F54: 7 months ago | G54: Street parking, very compact gym but well laid out. Limited equipment because of the space, so may you need to wait or share equipment. … | H54: Anytime Fitness Zetland | I54: 16887 | J54: 2025-03-14 | K54: {"overall_sentiment":"negative","aspects":[{"aspect":"parking","category":"access","sentiment":"neutral","evidence_span":"Street parking"},{"aspect":"gym","category":"facility","sentiment":"negative","evidence_span":"compact gym"},{"aspect":"layout","category":"facility","sentiment":"positive","evidence_span":"well laid out"},{"aspect":"equipment","category":"equipment","sentiment":"negative","evidence_span":"Limited equipment"}]} | L54: {'sentence': 'Street parking , very compact gym but well laid out . Limited equipment because of the space , so may you need to wait or share equipment . …', 'IOB': ['O', 'O', 'O', 'O', 'O', 'B-ASP', 'O', 'O', 'O', 'O', 'O', 'O', 'O', 'O', 'O', 'O', 'B-ASP', 'O', 'O', 'O', 'O', 'O', 'O', 'O', 'O', 'O', 'O', 'O', 'O'], 'tokens': ['Street', 'parking', ',', 'very', 'compact', 'gym', 'but', 'well', 'laid', 'out', '.', 'Limited', 'equipment', 'because', 'of', 'the', 'space', ',', 'so', 'may', 'you', 'need', 'to', 'wait', 'or', 'share', 'equipment', '.', '…'], 'aspect': ['gym', 'space'], 'position': [[5], [16]], 'sentiment': ['Negative', 'Negative'], 'probs': [[0.6566897630691528, 0.297799289226532, 0.045511018484830856], [0.6882863640785217, 0.31131163239479065, 0.0004019391199108213]], 'confidence': [0.6567, 0.6883]} | M54: 1 | N54: =LEN(K54)-LEN(SUBSTITUTE(K54,"{",""))-1 -> 4 | O54: 2 | P54: =_xlfn.XLOOKUP(B54,'g1'!B:B,'g1'!R:R) -> 4 | Q54: =_xlfn.XLOOKUP(B54,'g2'!B:B,'g2'!U:U) -> 2 | R54: =_xlfn.XLOOKUP(B54,'g3'!B:B,'g3'!R:R) -> 3 | S54: =_xlfn.XLOOKUP(D54,'g4'!D:D,'g4'!N:N) -> 5 | T54: =$N54-P54 -> 0 | U54: =$N54-Q54 -> 2 | V54: =$N54-R54 -> 1 | W54: =$N54-S54 -> -1 | X54: [{'aspect': 'parking', 'opinion': 'street parking', 'sentiment': 'neutral'}, {'aspect': 'layout', 'opinion': 'well laid out', 'sentiment': 'positive'}, {'aspect': 'equipment', 'opinion': 'limited', 'sentiment': 'negative'}, {'aspect': 'waiting times', 'opinion': 'may need to wait or share', 'sentiment': 'negative'}, {'aspect': 'gym space', 'opinion': 'very compact', 'sentiment': 'negative'}] | Y54: =FIND("[{",K54) -> 43 | Z54: =FIND("category",K54) -> 65 | AA54: =Z54-Y54-2 -> 20 | AB54: parking | AD54: =FIND("[{",X54) -> 1 | AE54: =FIND("opinion",X54) -> 25 | AF54: =AE54-AD54-2 -> 22 | AG54: parking | AH54: =AB54=AG54 -> TRUE
A55: 228 | B55: ChIJr57bACeuEmsRUKBa35B3cfY | C55: R R | D55: ChIJr57bACeuEmsRUKBa35B3cfYR R | E55: 3 | F55: 3 years ago | G55: The energy of the management staff was a bit off but the waiter who looked after us was amazing. They made a mistake with our pizza which meant that we had to wait a bit longer than usual for the pizza we ordered. Overall, a decent restaurant. | H55: Andiamo Trattoria Chippendale | I55: 3190 | J55: 2022-10-11 | K55: {"overall_sentiment":"neutral","aspects":[{"aspect":"management staff","category":"staff","sentiment":"negative","evidence_span":"a bit off"},{"aspect":"waiter","category":"service","sentiment":"positive","evidence_span":"amazing"},{"aspect":"pizza","category":"food","sentiment":"negative","evidence_span":"made a mistake"},{"aspect":"wait time","category":"service","sentiment":"negative","evidence_span":"a bit longer"}]} | L55: {'sentence': 'The energy of the management staff was a bit off but the waiter who looked after us was amazing . They made a mistake with our pizza which meant that we had to wait a bit longer than usual for the pizza we ordered . Overall , a decent restaurant .', 'IOB': ['O', 'O', 'O', 'O', 'B-ASP', 'I-ASP', 'O', 'O', 'O', 'O', 'O', 'O', 'B-ASP', 'O', 'O', 'O', 'O', 'O', 'O', 'O', 'O', 'O', 'O', 'O', 'O', 'O', 'O', 'O', 'O', 'O', 'O', 'O', 'O', 'O', 'O', 'O', 'O', 'O', 'O', 'O', 'O', 'O', 'O', 'O', 'O', 'O', 'O', 'O', 'O', 'O', 'O'], 'tokens': ['The', 'energy', 'of', 'the', 'management', 'staff', 'was', 'a', 'bit', 'off', 'but', 'the', 'waiter', 'who', 'looked', 'after', 'us', 'was', 'amazing', '.', 'They', 'made', 'a', 'mistake', 'with', 'our', 'pizza', 'which', 'meant', 'that', 'we', 'had', 'to', 'wait', 'a', 'bit', 'longer', 'than', 'usual', 'for', 'the', 'pizza', 'we', 'ordered', '.', 'Overall', ',', 'a', 'decent', 'restaurant', '.'], 'aspect': ['management staff', 'waiter'], 'position': [[4, 5], [12]], 'sentiment': ['Negative', 'Positive'], 'probs': [[0.995381772518158, 0.004343212116509676, 0.00027495561516843736], [0.00595629820600152, 0.0002527348406147212, 0.9937910437583923]], 'confidence': [0.9954, 0.9938]} | M55: 1 | N55: 4 | O55: 2 | P55: =_xlfn.XLOOKUP(B55,'g1'!B:B,'g1'!R:R) -> 4 | Q55: =_xlfn.XLOOKUP(B55,'g2'!B:B,'g2'!U:U) -> 3 | R55: =_xlfn.XLOOKUP(B55,'g3'!B:B,'g3'!R:R) -> 4 | S55: =_xlfn.XLOOKUP(D55,'g4'!D:D,'g4'!N:N) -> 5 | T55: =$N55-P55 -> 0 | U55: =$N55-Q55 -> 1 | V55: =$N55-R55 -> 0 | W55: =$N55-S55 -> -1 | X55: [{'aspect': 'management staff', 'opinion': 'a bit off', 'sentiment': 'negative'}, {'aspect': 'waiter', 'opinion': 'amazing', 'sentiment': 'positive'}, {'aspect': 'service', 'opinion': 'made a mistake', 'sentiment': 'negative'}, {'aspect': 'waiting time', 'opinion': 'had to wait a bit longer than usual', 'sentiment': 'negative'}, {'aspect': 'restaurant', 'opinion': 'decent', 'sentiment': 'positive'}] | Y55: =FIND("[{",K55) -> 42 | Z55: =FIND("category",K55) -> 73 | AA55: =Z55-Y55-2 -> 29 | AB55: management | AD55: =FIND("[{",X55) -> 1 | AE55: =FIND("opinion",X55) -> 34 | AF55: =AE55-AD55-2 -> 31 | AG55: management staff | AH55: =AB55=AG55 -> FALSE
A56: 232 | B56: ChIJCVFX7QhEkWsRXO7Y_6h7J1A | C56: Douglas Gillis | D56: ChIJCVFX7QhEkWsRXO7Y_6h7J1ADouglas Gillis | E56: 4 | F56: 2 years ago | G56: Some interesting pieces if you are into art. I was dragged along by a friend but I still appreciated a couple of the pieces. Friendly attendents and clean facilities. They have new items every 6 weeks | H56: Logan Art Gallery | I56: 15274 | J56: 2023-10-11 | K56: {"overall_sentiment":"positive","aspects":[{"aspect":"art","category":"art","sentiment":"positive","evidence_span":"interesting pieces"},{"aspect":"attendents","category":"service","sentiment":"positive","evidence_span":"Friendly attendents"},{"aspect":"facilities","category":"cleanliness","sentiment":"positive","evidence_span":"clean facilities"},{"aspect":"items","category":"variety","sentiment":"neutral","evidence_span":"new items"}]} | L56: {'sentence': 'Some interesting pieces if you are into art . I was dragged along by a friend but I still appreciated a couple of the pieces . Friendly attendents and clean facilities . They have new items every 6 weeks', 'IOB': ['O', 'O', 'O', 'O', 'O', 'O', 'O', 'O', 'O', 'O', 'O', 'O', 'O', 'O', 'O', 'O', 'O', 'O', 'O', 'O', 'O', 'O', 'O', 'O', 'O', 'O', 'O', 'B-ASP', 'O', 'O', 'B-ASP', 'O', 'O', 'O', 'O', 'O', 'O', 'O', 'O'], 'tokens': ['Some', 'interesting', 'pieces', 'if', 'you', 'are', 'into', 'art', '.', 'I', 'was', 'dragged', 'along', 'by', 'a', 'friend', 'but', 'I', 'still', 'appreciated', 'a', 'couple', 'of', 'the', 'pieces', '.', 'Friendly', 'attendents', 'and', 'clean', 'facilities', '.', 'They', 'have', 'new', 'items', 'every', '6', 'weeks'], 'aspect': ['attendents', 'facilities'], 'position': [[27], [30]], 'sentiment': ['Positive', 'Positive'], 'probs': [[0.00030512918601743877, 0.00028128508711233735, 0.9994136095046997], [0.0001644639705773443, 0.000751578074414283, 0.9990839958190918]], 'confidence': [0.9994, 0.9991]} | M56: 1 | N56: 4 | O56: 2 | P56: =_xlfn.XLOOKUP(B56,'g1'!B:B,'g1'!R:R) -> 4 | Q56: =_xlfn.XLOOKUP(B56,'g2'!B:B,'g2'!U:U) -> 4 | R56: =_xlfn.XLOOKUP(B56,'g3'!B:B,'g3'!R:R) -> 4 | S56: =_xlfn.XLOOKUP(D56,'g4'!D:D,'g4'!N:N) -> 5 | T56: =$N56-P56 -> 0 | U56: =$N56-Q56 -> 0 | V56: =$N56-R56 -> 0 | W56: =$N56-S56 -> -1 | X56: [{'aspect': 'art', 'opinion': 'interesting', 'sentiment': 'neutral'}, {'aspect': 'pieces', 'opinion': 'appreciated', 'sentiment': 'positive'}, {'aspect': 'attendents', 'opinion': 'friendly', 'sentiment': 'positive'}, {'aspect': 'facilities', 'opinion': 'clean', 'sentiment': 'positive'}, {'aspect': 'items', 'opinion': 'new', 'sentiment': 'neutral'}] | Y56: =FIND("[{",K56) -> 43 | Z56: =FIND("category",K56) -> 61 | AA56: =Z56-Y56-2 -> 16 | AB56: pieces | AD56: =FIND("[{",X56) -> 1 | AE56: =FIND("opinion",X56) -> 21 | AF56: =AE56-AD56-2 -> 18 | AG56: art | AH56: =AB56=AG56 -> FALSE
A57: 347 | B57: ChIJrYFjkwNAp2sRxWzYfoHQ9ko | C57: Blake Bucknall | D57: ChIJrYFjkwNAp2sRxWzYfoHQ9koBlake Bucknall | E57: 4 | F57: 4 weeks ago | G57: There's no employees just some signage to read. Other than the dishes themselves you'll only be there for a few mins to take photos then leave. Cool nonetheless if you love your astronomy. | H57: Australia Telescope Compact Array | I57: 18462 | J57: 2025-09-12 | K57: {"overall_sentiment":"positive","aspects":[{"aspect":"signage","category":"staff","sentiment":"negative","evidence_span":"no employees"},{"aspect":"signage","category":"signage","sentiment":"neutral","evidence_span":"some signage"},{"aspect":"visit time","category":"duration","sentiment":"neutral","evidence_span":"few mins"},{"aspect":"astronomy","category":"theme","sentiment":"positive","evidence_span":"love your astronomy"}]} | L57: {'sentence': "There ' s no employees just some signage to read . Other than the dishes themselves you ' ll only be there for a few mins to take photos then leave . Cool nonetheless if you love your astronomy .", 'IOB': ['O', 'O', 'O', 'O', 'B-ASP', 'O', 'O', 'O', 'O', 'O', 'O', 'O', 'O', 'O', 'B-ASP', 'O', 'O', 'O', 'O', 'O', 'O', 'O', 'O', 'O', 'O', 'O', 'O', 'O', 'O', 'O', 'O', 'O', 'O', 'O', 'O', 'O', 'O', 'O', 'O', 'O'], 'tokens': ['There', "'", 's', 'no', 'employees', 'just', 'some', 'signage', 'to', 'read', '.', 'Other', 'than', 'the', 'dishes', 'themselves', 'you', "'", 'll', 'only', 'be', 'there', 'for', 'a', 'few', 'mins', 'to', 'take', 'photos', 'then', 'leave', '.', 'Cool', 'nonetheless', 'if', 'you', 'love', 'your', 'astronomy', '.'], 'aspect': ['employees', 'dishes'], 'position': [[4], [14]], 'sentiment': ['Negative', 'Neutral'], 'probs': [[0.9993170499801636, 0.00039816266507841647, 0.00028483528876677155], [0.00022607477148994803, 0.9987133741378784, 0.0010605253046378493]], 'confidence': [0.9993, 0.9987]} | M57: 1 | N57: =LEN(K57)-LEN(SUBSTITUTE(K57,"{",""))-1 -> 4 | O57: 2 | P57: =_xlfn.XLOOKUP(B57,'g1'!B:B,'g1'!R:R) -> 5 | Q57: =_xlfn.XLOOKUP(B57,'g2'!B:B,'g2'!U:U) -> 5 | R57: =_xlfn.XLOOKUP(B57,'g3'!B:B,'g3'!R:R) -> 2 | S57: =_xlfn.XLOOKUP(D57,'g4'!D:D,'g4'!N:N) -> 5 | T57: =$N57-P57 -> -1 | U57: =$N57-Q57 -> -1 | V57: =$N57-R57 -> 2 | W57: =$N57-S57 -> -1 | X57: [{'aspect': 'signage', 'opinion': 'just some signage', 'sentiment': 'neutral'}, {'aspect': 'dishes', 'opinion': 'the dishes themselves', 'sentiment': 'neutral'}, {'aspect': 'employees', 'opinion': 'no employees', 'sentiment': 'neutral'}, {'aspect': 'visit duration', 'opinion': 'few mins to take photos then leave', 'sentiment': 'neutral'}, {'aspect': 'experience', 'opinion': 'cool nonetheless', 'sentiment': 'neutral'}] | Y57: =FIND("[{",K57) -> 43 | Z57: =FIND("category",K57) -> 65 | AA57: =Z57-Y57-2 -> 20 | AB57: employees | AD57: =FIND("[{",X57) -> 1 | AE57: =FIND("opinion",X57) -> 25 | AF57: =AE57-AD57-2 -> 22 | AG57: signage | AH57: =AB57=AG57 -> FALSE
A58: 453 | B58: ChIJMetwdOhxk2sRpqSfwRjwzJk | C58: Mary Figone | D58: ChIJMetwdOhxk2sRpqSfwRjwzJkMary Figone | E58: 5 | F58: 8 years ago | G58: Gina and Paula are the best at what they do! My son has been swimming at Gina's twice a week since he was 6 weeks old. He loves the water, is learning invaluable life saving techniques and having fun all the while. I wouldn't take him anywhere else! | H58: Gina's Blue Water Babies Swim School | I58: 45821 | J58: 2017-10-12 | K58: {"overall_sentiment":"positive","aspects":[{"aspect":"Gina and Paula","category":"staff","sentiment":"positive","evidence_span":"best at"},{"aspect":"water","category":"facilities","sentiment":"positive","evidence_span":"loves the water"},{"aspect":"techniques","category":"training","sentiment":"positive","evidence_span":"life saving techniques"},{"aspect":"fun","category":"experience","sentiment":"positive","evidence_span":"having fun"}]} | L58: {'sentence': "Gina and Paula are the best at what they do ! My son has been swimming at Gina ' s twice a week since he was 6 weeks old . He loves the water , is learning invaluable life saving techniques and having fun all the while . I wouldn ' t take him anywhere else !", 'IOB': ['B-ASP', 'O', 'B-ASP', 'O', 'O', 'O', 'O', 'O', 'O', 'O', 'O', 'O', 'O', 'O', 'O', 'O', 'O', 'O', 'O', 'O', 'O', 'O', 'O', 'O', 'O', 'O', 'O', 'O', 'O', 'O', 'O', 'O', 'O', 'O', 'O', 'O', 'O', 'O', 'O', 'O', 'O', 'O', 'O', 'O', 'O', 'O', 'O', 'O', 'O', 'O', 'O', 'O', 'O', 'O', 'O', 'O', 'O'], 'tokens': ['Gina', 'and', 'Paula', 'are', 'the', 'best', 'at', 'what', 'they', 'do', '!', 'My', 'son', 'has', 'been', 'swimming', 'at', 'Gina', "'", 's', 'twice', 'a', 'week', 'since', 'he', 'was', '6', 'weeks', 'old', '.', 'He', 'loves', 'the', 'water', ',', 'is', 'learning', 'invaluable', 'life', 'saving', 'techniques', 'and', 'having', 'fun', 'all', 'the', 'while', '.', 'I', 'wouldn', "'", 't', 'take', 'him', 'anywhere', 'else', '!'], 'aspect': ['Gina', 'Paula'], 'position': [[0], [2]], 'sentiment': ['Positive', 'Positive'], 'probs': [[0.0003322958655189723, 0.000269866461167112, 0.999397873878479], [0.0003288376610726118, 0.0002568553027231246, 0.999414324760437]], 'confidence': [0.9994, 0.9994]} | M58: 1 | N58: =LEN(K58)-LEN(SUBSTITUTE(K58,"{",""))-1 -> 4 | O58: 2 | P58: =_xlfn.XLOOKUP(B58,'g1'!B:B,'g1'!R:R) -> 5 | Q58: =_xlfn.XLOOKUP(B58,'g2'!B:B,'g2'!U:U) -> 4 | R58: =_xlfn.XLOOKUP(B58,'g3'!B:B,'g3'!R:R) -> 2 | S58: =_xlfn.XLOOKUP(D58,'g4'!D:D,'g4'!N:N) -> 5 | T58: =$N58-P58 -> -1 | U58: =$N58-Q58 -> 0 | V58: =$N58-R58 -> 2 | W58: =$N58-S58 -> -1 | X58: [{'aspect': 'Gina and Paula', 'opinion': 'best at what they do', 'sentiment': 'positive'}, {'aspect': "Gina's Blue Water Babies Swim School", 'opinion': "wouldn't take him anywhere else", 'sentiment': 'positive'}, {'aspect': 'life saving techniques', 'opinion': 'invaluable', 'sentiment': 'positive'}, {'aspect': 'water', 'opinion': 'loves', 'sentiment': 'positive'}, {'aspect': 'swim classes', 'opinion': 'having fun', 'sentiment': 'positive'}] | Y58: =FIND("[{",K58) -> 43 | Z58: =FIND("category",K58) -> 72 | AA58: =Z58-Y58-2 -> 27 | AB58: instructors | AD58: =FIND("[{",X58) -> 1 | AE58: =FIND("opinion",X58) -> 32 | AF58: =AE58-AD58-2 -> 29 | AG58: Gina and Paula | AH58: =AB58=AG58 -> FALSE
A59: 546 | B59: ChIJBXbXT1N11moRTbMxNvd7yLY | C59: Lorraine Field | D59: ChIJBXbXT1N11moRTbMxNvd7yLYLorraine Field | E59: 1 | F59: 7 months ago | G59: Too much dog shit every where, rude people with their uncontrolled dogs off lead, council does nothing. Dogs in the kids play area every time I walk through. | H59: Abram Reserve | I59: 105448 | J59: 2025-03-14 | K59: {"overall_sentiment":"negative","aspects":[{"aspect":"dog shit","category":"cleanliness","sentiment":"negative","evidence_span":"dog shit"},{"aspect":"people","category":"behavior","sentiment":"negative","evidence_span":"rude people"},{"aspect":"dog control","category":"management","sentiment":"negative","evidence_span":"off lead"},{"aspect":"council","category":"management","sentiment":"negative","evidence_span":"does nothing"}]} | L59: {'sentence': 'Too much dog shit every where , rude people with their uncontrolled dogs off lead , council does nothing . Dogs in the kids play area every time I walk through .', 'IOB': ['O', 'O', 'B-ASP', 'O', 'O', 'O', 'O', 'O', 'O', 'O', 'O', 'O', 'O', 'O', 'O', 'O', 'O', 'O', 'O', 'O', 'O', 'O', 'O', 'O', 'O', 'B-ASP', 'O', 'O', 'O', 'O', 'O', 'O'], 'tokens': ['Too', 'much', 'dog', 'shit', 'every', 'where', ',', 'rude', 'people', 'with', 'their', 'uncontrolled', 'dogs', 'off', 'lead', ',', 'council', 'does', 'nothing', '.', 'Dogs', 'in', 'the', 'kids', 'play', 'area', 'every', 'time', 'I', 'walk', 'through', '.'], 'aspect': ['dog', 'area'], 'position': [[2], [25]], 'sentiment': ['Negative', 'Neutral'], 'probs': [[0.9989035129547119, 0.0008379883365705609, 0.00025856512365862727], [0.007478899788111448, 0.9922125935554504, 0.00030842976411804557]], 'confidence': [0.9989, 0.9922]} | M59: 1 | N59: 4 | O59: 2 | P59: =_xlfn.XLOOKUP(B59,'g1'!B:B,'g1'!R:R) -> 5 | Q59: =_xlfn.XLOOKUP(B59,'g2'!B:B,'g2'!U:U) -> 4 | R59: =_xlfn.XLOOKUP(B59,'g3'!B:B,'g3'!R:R) -> 4 | S59: =_xlfn.XLOOKUP(D59,'g4'!D:D,'g4'!N:N) -> 5 | T59: =$N59-P59 -> -1 | U59: =$N59-Q59 -> 0 | V59: =$N59-R59 -> 0 | W59: =$N59-S59 -> -1 | X59: [{'aspect': 'dog shit', 'opinion': 'every where', 'sentiment': 'negative'}, {'aspect': 'people', 'opinion': 'rude people with their uncontrolled dogs off lead', 'sentiment': 'negative'}, {'aspect': 'dogs', 'opinion': 'uncontrolled dogs in the kids play area', 'sentiment': 'negative'}, {'aspect': 'council', 'opinion': 'does nothing', 'sentiment': 'negative'}, {'aspect': 'kids play area', 'opinion': 'Dogs in the kids play area every time I walk through', 'sentiment': 'negative'}] | Y59: =FIND("[{",K59) -> 43 | Z59: =FIND("category",K59) -> 66 | AA59: =Z59-Y59-2 -> 21 | AB59: dog shit | AD59: =FIND("[{",X59) -> 1 | AE59: =FIND("opinion",X59) -> 26 | AF59: =AE59-AD59-2 -> 23 | AG59: dog shit | AH59: =AB59=AG59 -> TRUE
A60: 551 | B60: ChIJ8bLaZidD1moR7idXQCIcGWI | C60: Michael Robinson | D60: ChIJ8bLaZidD1moR7idXQCIcGWIMichael Robinson | E60: 1 | F60: 4 years ago | G60: Gym is just not looked after. Sauna and steam room has been turned off since I joined. When asked about it being repaired I was dismissed. It’s been a year and despite being sold a membership with sauna and steam room included I’ve never … | H60: Goodlife Health Clubs Fitzroy | I60: 11839 | J60: 2021-10-11 | K60: {"overall_sentiment":"negative","aspects":[{"aspect":"gym","category":"maintenance","sentiment":"negative","evidence_span":"not looked after"},{"aspect":"sauna","category":"facility","sentiment":"negative","evidence_span":"turned off"},{"aspect":"steam room","category":"facility","sentiment":"negative","evidence_span":"turned off"},{"aspect":"staff","category":"service","sentiment":"negative","evidence_span":"dismissed"}]} | L60: {'sentence': 'Gym is just not looked after . Sauna and steam room has been turned off since I joined . When asked about it being repaired I was dismissed . It ’ s been a year and despite being sold a membership with sauna and steam room included I ’ ve never …', 'IOB': ['O', 'O', 'O', 'O', 'O', 'O', 'O', 'B-ASP', 'O', 'O', 'B-ASP', 'O', 'O', 'O', 'O', 'O', 'O', 'O', 'O', 'O', 'O', 'O', 'O', 'O', 'O', 'O', 'O', 'O', 'O', 'O', 'O', 'O', 'O', 'O', 'O', 'O', 'O', 'O', 'O', 'O', 'O', 'O', 'O', 'O', 'O', 'O', 'O', 'O', 'O', 'O', 'O', 'O'], 'tokens': ['Gym', 'is', 'just', 'not', 'looked', 'after', '.', 'Sauna', 'and', 'steam', 'room', 'has', 'been', 'turned', 'off', 'since', 'I', 'joined', '.', 'When', 'asked', 'about', 'it', 'being', 'repaired', 'I', 'was', 'dismissed', '.', 'It', '’', 's', 'been', 'a', 'year', 'and', 'despite', 'being', 'sold', 'a', 'membership', 'with', 'sauna', 'and', 'steam', 'room', 'included', 'I', '’', 've', 'never', '…'], 'aspect': ['Sauna', 'room'], 'position': [[7], [10]], 'sentiment': ['Negative', 'Negative'], 'probs': [[0.9958963394165039, 0.003763884073123336, 0.0003398095432203263], [0.9957048296928406, 0.003995539154857397, 0.00029955169884487987]], 'confidence': [0.9959, 0.9957]} | M60: 1 | N60: =LEN(K60)-LEN(SUBSTITUTE(K60,"{",""))-1 -> 4 | O60: 2 | P60: =_xlfn.XLOOKUP(B60,'g1'!B:B,'g1'!R:R) -> 5 | Q60: =_xlfn.XLOOKUP(B60,'g2'!B:B,'g2'!U:U) -> 4 | R60: =_xlfn.XLOOKUP(B60,'g3'!B:B,'g3'!R:R) -> 3 | S60: =_xlfn.XLOOKUP(D60,'g4'!D:D,'g4'!N:N) -> 5 | T60: =$N60-P60 -> -1 | U60: =$N60-Q60 -> 0 | V60: =$N60-R60 -> 1 | W60: =$N60-S60 -> -1 | X60: [{'aspect': 'gym', 'opinion': 'not looked after', 'sentiment': 'negative'}, {'aspect': 'sauna', 'opinion': 'has been turned off', 'sentiment': 'negative'}, {'aspect': 'steam room', 'opinion': 'has been turned off', 'sentiment': 'negative'}, {'aspect': 'staff', 'opinion': 'dismissed', 'sentiment': 'negative'}, {'aspect': 'membership', 'opinion': 'sold with sauna and steam room included', 'sentiment': 'negative'}] | Y60: =FIND("[{",K60) -> 43 | Z60: =FIND("category",K60) -> 61 | AA60: =Z60-Y60-2 -> 16 | AB60: gym | AD60: =FIND("[{",X60) -> 1 | AE60: =FIND("opinion",X60) -> 21 | AF60: =AE60-AD60-2 -> 18 | AG60: gym | AH60: =AB60=AG60 -> TRUE
A61: 622 | B61: ChIJKQ1V2W-yEmsRRtjm6OAFSkk | C61: Mik Sta | D61: ChIJKQ1V2W-yEmsRRtjm6OAFSkkMik Sta | E61: 2 | F61: Edited 6 years ago | G61: It is the only place that serves coffee on the beach. Service really needs improving, food is expensive and average. Coffee really needs a step up. Not open late, as in after 4pm, so having an evening stroll and coffee around … | H61: Seasalt Clovelly | I61: 2619 | J61: 2019-10-12 | K61: {"overall_sentiment":"negative","aspects":[{"aspect":"service","category":"service","sentiment":"negative","evidence_span":"needs improving"},{"aspect":"food","category":"food","sentiment":"negative","evidence_span":"expensive"},{"aspect":"coffee","category":"beverage","sentiment":"negative","evidence_span":"step up"},{"aspect":"opening hours","category":"availability","sentiment":"negative","evidence_span":"Not open late"}]} | L61: {'sentence': 'It is the only place that serves coffee on the beach . Service really needs improving , food is expensive and average . Coffee really needs a step up . \n Not open late , as in after 4pm , so having an evening stroll and coffee around …', 'IOB': ['O', 'O', 'O', 'O', 'O', 'O', 'O', 'O', 'O', 'O', 'O', 'O', 'B-ASP', 'O', 'O', 'O', 'O', 'B-ASP', 'O', 'O', 'O', 'O', 'O', 'O', 'O', 'O', 'O', 'O', 'O', 'O', 'O', 'O', 'O', 'O', 'O', 'O', 'O', 'O', 'O', 'O', 'O', 'O', 'O', 'O', 'O', 'O', 'O', 'O', '[SEP]'], 'tokens': ['It', 'is', 'the', 'only', 'place', 'that', 'serves', 'coffee', 'on', 'the', 'beach', '.', 'Service', 'really', 'needs', 'improving', ',', 'food', 'is', 'expensive', 'and', 'average', '.', 'Coffee', 'really', 'needs', 'a', 'step', 'up', '.', '\n', 'Not', 'open', 'late', ',', 'as', 'in', 'after', '4pm', ',', 'so', 'having', 'an', 'evening', 'stroll', 'and', 'coffee', 'around', '…'], 'aspect': ['Service', 'food'], 'position': [[12], [17]], 'sentiment': ['Negative', 'Negative'], 'probs': [[0.6565878987312317, 0.15452168881893158, 0.18889044225215912], [0.9691688418388367, 0.029917888343334198, 0.0009132477571256459]], 'confidence': [0.6566, 0.9692]} | M61: 1 | N61: =LEN(K61)-LEN(SUBSTITUTE(K61,"{",""))-1 -> 4 | O61: 2 | P61: =_xlfn.XLOOKUP(B61,'g1'!B:B,'g1'!R:R) -> 5 | Q61: =_xlfn.XLOOKUP(B61,'g2'!B:B,'g2'!U:U) -> 4 | R61: =_xlfn.XLOOKUP(B61,'g3'!B:B,'g3'!R:R) -> 3 | S61: =_xlfn.XLOOKUP(D61,'g4'!D:D,'g4'!N:N) -> 5 | T61: =$N61-P61 -> -1 | U61: =$N61-Q61 -> 0 | V61: =$N61-R61 -> 1 | W61: =$N61-S61 -> -1 | X61: [{'aspect': 'opening hours', 'opinion': 'not open late', 'sentiment': 'negative'}, {'aspect': 'location', 'opinion': 'the only place that serves coffee on the beach', 'sentiment': 'positive'}, {'aspect': 'service', 'opinion': 'needs improving', 'sentiment': 'negative'}, {'aspect': 'food', 'opinion': 'expensive and average', 'sentiment': 'negative'}, {'aspect': 'coffee', 'opinion': 'needs a step up', 'sentiment': 'negative'}] | Y61: =FIND("[{",K61) -> 43 | Z61: =FIND("category",K61) -> 65 | AA61: =Z61-Y61-2 -> 20 | AB61: service | AD61: =FIND("[{",X61) -> 1 | AE61: =FIND("opinion",X61) -> 31 | AF61: =AE61-AD61-2 -> 28 | AG61: opening hours | AH61: =AB61=AG61 -> FALSE
A62: 647 | B62: ChIJyT_-0WupumoRE3YfXPgSnyk | C62: Aerwyn | D62: ChIJyT_-0WupumoRE3YfXPgSnykAerwyn | E62: 3 | F62: 2 years ago | G62: Primarily bush walk better when it's green with defined sand/dirt tracks. Some signs found throughout that mention history or information about revegetation. Small pond to side closest to footy oval with a creek bed. Left hand side appears reserved for bike jumps as there's many man-made mounds for doing jumps. | H62: Victoria Park | I62: 89979 | J62: 2023-10-11 | K62: {"overall_sentiment":"neutral","aspects":[{"aspect":"bush walk","category":"path","sentiment":"positive","evidence_span":"sand/dirt tracks"},{"aspect":"signs","category":"signage","sentiment":"neutral","evidence_span":"Some signs"},{"aspect":"pond","category":"water feature","sentiment":"neutral","evidence_span":"Small pond"},{"aspect":"bike jumps","category":"recreation","sentiment":"neutral","evidence_span":"bike jumps"}]} | L62: {'sentence': "Primarily bush walk better when it ' s green with defined sand / dirt tracks . Some signs found throughout that mention history or information about revegetation . Small pond to side closest to footy oval with a creek bed . Left hand side appears reserved for bike jumps as there ' s many man - made mounds for doing jumps .", 'IOB': ['O', 'O', 'O', 'O', 'O', 'O', 'O', 'O', 'O', 'O', 'O', 'O', 'O', 'O', 'O', 'O', 'O', 'B-ASP', 'O', 'O', 'O', 'O', 'O', 'O', 'O', 'O', 'O', 'O', 'O', 'O', 'O', 'O', 'O', 'O', 'O', 'O', 'O', 'O', 'O', 'O', 'O', 'O', 'O', 'O', 'O', 'O', 'O', 'O', 'O', 'O', 'O', 'O', 'O', 'O', 'O', 'O', 'O', 'O', 'O', 'O', 'O', 'O'], 'tokens': ['Primarily', 'bush', 'walk', 'better', 'when', 'it', "'", 's', 'green', 'with', 'defined', 'sand', '/', 'dirt', 'tracks', '.', 'Some', 'signs', 'found', 'throughout', 'that', 'mention', 'history', 'or', 'information', 'about', 'revegetation', '.', 'Small', 'pond', 'to', 'side', 'closest', 'to', 'footy', 'oval', 'with', 'a', 'creek', 'bed', '.', 'Left', 'hand', 'side', 'appears', 'reserved', 'for', 'bike', 'jumps', 'as', 'there', "'", 's', 'many', 'man', '-', 'made', 'mounds', 'for', 'doing', 'jumps', '.'], 'aspect': ['signs'], 'position': [[17]], 'sentiment': ['Neutral'], 'probs': [[0.2438793033361435, 0.7531116604804993, 0.0030090082436800003]], 'confidence': [0.7531]} | M62: 1 | N62: 4 | O62: 1 | P62: =_xlfn.XLOOKUP(B62,'g1'!B:B,'g1'!R:R) -> 5 | Q62: =_xlfn.XLOOKUP(B62,'g2'!B:B,'g2'!U:U) -> 4 | R62: =_xlfn.XLOOKUP(B62,'g3'!B:B,'g3'!R:R) -> 4 | S62: =_xlfn.XLOOKUP(D62,'g4'!D:D,'g4'!N:N) -> 5 | T62: =$N62-P62 -> -1 | U62: =$N62-Q62 -> 0 | V62: =$N62-R62 -> 0 | W62: =$N62-S62 -> -1 | X62: [{'aspect': 'bush walk', 'opinion': "better when it's green with defined sand/dirt tracks", 'sentiment': 'positive'}, {'aspect': 'signs', 'opinion': 'some signs found throughout that mention history or information about revegetation', 'sentiment': 'neutral'}, {'aspect': 'pond', 'opinion': 'small pond to side closest to footy oval with a creek bed', 'sentiment': 'neutral'}, {'aspect': 'creek bed', 'opinion': 'creek bed', 'sentiment': 'neutral'}, {'aspect': 'bike jumps area', 'opinion': "appears reserved for bike jumps as there's many man-made mounds for doing jumps", 'sentiment': 'neutral'}] | Y62: =FIND("[{",K62) -> 42 | Z62: =FIND("category",K62) -> 66 | AA62: =Z62-Y62-2 -> 22 | AB62: tracks | AD62: =FIND("[{",X62) -> 1 | AE62: =FIND("opinion",X62) -> 27 | AF62: =AE62-AD62-2 -> 24 | AG62: bush walk | AH62: =AB62=AG62 -> FALSE
A63: 653 | B63: ChIJUwyLKB3jk2sRt_YgvYjm20Y | C63: Ramya Bhuthalingam | D63: ChIJUwyLKB3jk2sRt_YgvYjm20YRamya Bhuthalingam | E63: 5 | F63: a year ago | G63: Beautiful place that has things to do for everyone. Play park for kids, off-leash area for dogs, pathway next to the beach for walks/runs etc, pier to fish from etc. | H63: Sandgate Foreshores Park | I63: 99287 | J63: 2024-10-10 | K63: {"overall_sentiment":"positive","aspects":[{'aspect': 'place', 'category':'location', 'opinion': 'beautiful', 'sentiment': 'positive'}, {"aspect":"play park","category":"playground","sentiment":"positive","evidence_span":"Play park"},{"aspect":"off-leash area","category":"pet_area","sentiment":"positive","evidence_span":"off-leash area"},{"aspect":"pathway","category":"walking_trail","sentiment":"positive","evidence_span":"pathway"},{"aspect":"pier","category":"fishing","sentiment":"positive","evidence_span":"pier"}]} | L63: {'sentence': 'Beautiful place that has things to do for everyone . Play park for kids , off - leash area for dogs , pathway next to the beach for walks / runs etc , pier to fish from etc .', 'IOB': ['O', 'B-ASP', 'O', 'O', 'O', 'O', 'O', 'O', 'O', 'O', 'O', 'O', 'O', 'O', 'O', 'O', 'O', 'O', 'O', 'O', 'O', 'O', 'O', 'O', 'O', 'O', 'O', 'O', 'O', 'O', 'O', 'O', 'O', 'O', 'O', 'O', 'O', 'O', 'O'], 'tokens': ['Beautiful', 'place', 'that', 'has', 'things', 'to', 'do', 'for', 'everyone', '.', 'Play', 'park', 'for', 'kids', ',', 'off', '-', 'leash', 'area', 'for', 'dogs', ',', 'pathway', 'next', 'to', 'the', 'beach', 'for', 'walks', '/', 'runs', 'etc', ',', 'pier', 'to', 'fish', 'from', 'etc', '.'], 'aspect': ['place'], 'position': [[1]], 'sentiment': ['Positive'], 'probs': [[0.0005416713538579643, 0.000256187078775838, 0.9992021918296814]], 'confidence': [0.9992]} | M63: 1 | N63: 4 | O63: 1 | P63: =_xlfn.XLOOKUP(B63,'g1'!B:B,'g1'!R:R) -> 5 | Q63: =_xlfn.XLOOKUP(B63,'g2'!B:B,'g2'!U:U) -> 4 | R63: =_xlfn.XLOOKUP(B63,'g3'!B:B,'g3'!R:R) -> 4 | S63: =_xlfn.XLOOKUP(D63,'g4'!D:D,'g4'!N:N) -> 5 | T63: =$N63-P63 -> -1 | U63: =$N63-Q63 -> 0 | V63: =$N63-R63 -> 0 | W63: =$N63-S63 -> -1 | X63: [{'aspect': 'place', 'opinion': 'beautiful', 'sentiment': 'positive'}, {'aspect': 'play park', 'opinion': 'things to do for everyone', 'sentiment': 'positive'}, {'aspect': 'off-leash area', 'opinion': 'things to do for everyone', 'sentiment': 'positive'}, {'aspect': 'pathway', 'opinion': 'things to do for everyone', 'sentiment': 'positive'}, {'aspect': 'pier', 'opinion': 'things to do for everyone', 'sentiment': 'positive'}] | Y63: =FIND("[{",K63) -> 43 | Z63: =FIND("category",K63) -> 65 | AA63: =Z63-Y63-2 -> 20 | AB63: play park | AD63: =FIND("[{",X63) -> 1 | AE63: =FIND("opinion",X63) -> 23 | AF63: =AE63-AD63-2 -> 20 | AG63: place | AH63: =AB63=AG63 -> FALSE
A64: 157 | B64: ChIJa5i5vTCbEmsRNAAoR_StmSs | C64: J&N Em | D64: ChIJa5i5vTCbEmsRNAAoR_StmSsJ&N Em | E64: 2 | F64: Edited 11 months ago | G64: Always plays Bollywood music. Not enough classes, Zumba is the only decent class!! The place has gone downward since it opened tbh. It pretty much caters and focuses on a certain group. | H64: Mates Gym - Best 24hrs Weight Loss Gym | Creche | Cheap Gym Membership | Zumba & Bhangra Classes | I64: 4491 | J64: 2024-11-14 | K64: {"overall_sentiment":"negative","aspects":[{"aspect":"music","category":"Ambience","sentiment":"negative","evidence_span":"Bollywood music"},{"aspect":"classes","category":"Facilities","sentiment":"negative","evidence_span":"Not enough classes"},{"aspect":"Zumba","category":"Facilities","sentiment":"positive","evidence_span":"only decent class"},{"aspect":"quality","category":"General","sentiment":"negative","evidence_span":"gone downward"}]} | L64: {'sentence': 'Always plays Bollywood music . Not enough classes , Zumba is the only decent class ! ! The place has gone downward since it opened tbh . It pretty much caters and focuses on a certain group .', 'IOB': ['O', 'O', 'O', 'O', 'O', 'O', 'O', 'O', 'O', 'B-ASP', 'O', 'O', 'O', 'O', 'O', 'O', 'O', 'O', 'B-ASP', 'O', 'O', 'O', 'O', 'O', 'O', 'O', 'O', 'O', 'O', 'O', 'O', 'O', 'O', 'O', 'O', 'O', 'O', 'O'], 'tokens': ['Always', 'plays', 'Bollywood', 'music', '.', 'Not', 'enough', 'classes', ',', 'Zumba', 'is', 'the', 'only', 'decent', 'class', '!', '!', 'The', 'place', 'has', 'gone', 'downward', 'since', 'it', 'opened', 'tbh', '.', 'It', 'pretty', 'much', 'caters', 'and', 'focuses', 'on', 'a', 'certain', 'group', '.'], 'aspect': ['Zumba', 'place'], 'position': [[9], [18]], 'sentiment': ['Positive', 'Negative'], 'probs': [[0.004601074382662773, 0.40724971890449524, 0.5881492495536804], [0.8937033414840698, 0.0029138370882719755, 0.10338285565376282]], 'confidence': [0.5881, 0.8937]} | M64: 1 | N64: =LEN(K64)-LEN(SUBSTITUTE(K64,"{",""))-1 -> 4 | O64: 2 | P64: =_xlfn.XLOOKUP(B64,'g1'!B:B,'g1'!R:R) -> 5 | Q64: =_xlfn.XLOOKUP(B64,'g2'!B:B,'g2'!U:U) -> 5 | R64: =_xlfn.XLOOKUP(B64,'g3'!B:B,'g3'!R:R) -> 5 | S64: =_xlfn.XLOOKUP(D64,'g4'!D:D,'g4'!N:N) -> 5 | T64: =$N64-P64 -> -1 | U64: =$N64-Q64 -> -1 | V64: =$N64-R64 -> -1 | W64: =$N64-S64 -> -1 | X64: [{'aspect': 'classes', 'opinion': 'not enough classes', 'sentiment': 'negative'}, {'aspect': 'Bollywood music', 'opinion': 'always plays Bollywood music', 'sentiment': 'negative'}, {'aspect': 'Zumba', 'opinion': 'the only decent class', 'sentiment': 'positive'}, {'aspect': 'place', 'opinion': 'has gone downward since it opened', 'sentiment': 'negative'}, {'aspect': 'group', 'opinion': 'caters and focuses on a certain group', 'sentiment': 'negative'}] | Y64: =FIND("[{",K64) -> 43 | Z64: =FIND("category",K64) -> 63 | AA64: =Z64-Y64-2 -> 18 | AB64: music | AD64: =FIND("[{",X64) -> 1 | AE64: =FIND("opinion",X64) -> 25 | AF64: =AE64-AD64-2 -> 22 | AG64: classes | AH64: =AB64=AG64 -> FALSE
A65: 717 | B65: ChIJf5IXdrlbkWsRnW4ZA-IkcaU | C65: Chris | D65: ChIJf5IXdrlbkWsRnW4ZA-IkcaUChris | E65: 3 | F65: a year ago | G65: Very small gym. Nothing fantastic, but doesn't get particularly busy and has a small functional training area as well as cardio/machines/free weights. | H65: Zap Fitness 24/7 Camp Hill | I65: 33787 | J65: 2024-10-10 | K65: {"overall_sentiment":"neutral","aspects":[{"aspect":"gym size","category":"space","sentiment":"negative","evidence_span":"Very small"},{"aspect":"crowd","category":"crowd","sentiment":"positive","evidence_span":"particularly busy"},{"aspect":"training area","category":"facilities","sentiment":"neutral","evidence_span":"functional training"},{"aspect":"equipment","category":"facilities","sentiment":"positive","evidence_span":"free weights"}]} | L65: {'sentence': "Very small gym . Nothing fantastic , but doesn ' t get particularly busy and has a small functional training area as well as cardio / machines / free weights .", 'IOB': ['O', 'O', 'B-ASP', 'O', 'O', 'O', 'O', 'O', 'O', 'O', 'O', 'O', 'O', 'O', 'O', 'O', 'O', 'O', 'O', 'O', 'B-ASP', 'O', 'O', 'O', 'O', 'O', 'O', 'O', 'O', 'O', 'O'], 'tokens': ['Very', 'small', 'gym', '.', 'Nothing', 'fantastic', ',', 'but', 'doesn', "'", 't', 'get', 'particularly', 'busy', 'and', 'has', 'a', 'small', 'functional', 'training', 'area', 'as', 'well', 'as', 'cardio', '/', 'machines', '/', 'free', 'weights', '.'], 'aspect': ['gym', 'area'], 'position': [[2], [20]], 'sentiment': ['Neutral', 'Negative'], 'probs': [[0.016294855624437332, 0.9831994771957397, 0.0005056858062744141], [0.9673461318016052, 0.032117001712322235, 0.0005369383143261075]], 'confidence': [0.9832, 0.9673]} | M65: 1 | N65: =LEN(K65)-LEN(SUBSTITUTE(K65,"{",""))-1 -> 4 | O65: 2 | P65: =_xlfn.XLOOKUP(B65,'g1'!B:B,'g1'!R:R) -> 5 | Q65: =_xlfn.XLOOKUP(B65,'g2'!B:B,'g2'!U:U) -> 5 | R65: =_xlfn.XLOOKUP(B65,'g3'!B:B,'g3'!R:R) -> 5 | S65: =_xlfn.XLOOKUP(D65,'g4'!D:D,'g4'!N:N) -> 5 | T65: =$N65-P65 -> -1 | U65: =$N65-Q65 -> -1 | V65: =$N65-R65 -> -1 | W65: =$N65-S65 -> -1 | X65: [{'aspect': 'gym size', 'opinion': 'very small', 'sentiment': 'negative'}, {'aspect': 'functional training area', 'opinion': 'small functional', 'sentiment': 'neutral'}, {'aspect': 'crowd levels', 'opinion': "doesn't get particularly busy", 'sentiment': 'positive'}, {'aspect': 'equipment', 'opinion': 'cardio/machines/free weights', 'sentiment': 'positive'}, {'aspect': 'overall quality', 'opinion': 'nothing fantastic', 'sentiment': 'negative'}] | Y65: =FIND("[{",K65) -> 42 | Z65: =FIND("category",K65) -> 65 | AA65: =Z65-Y65-2 -> 21 | AB65: size | AD65: =FIND("[{",X65) -> 1 | AE65: =FIND("opinion",X65) -> 26 | AF65: =AE65-AD65-2 -> 23 | AG65: gym size | AH65: =AB65=AG65 -> FALSE
A66: 727 | B66: ChIJh-ATGPtJzWoRGaIwZgx1viQ | C66: Karl Schaffarczyk | D66: ChIJh-ATGPtJzWoRGaIwZgx1viQKarl Schaffarczyk | E66: 5 | F66: 4 years ago on Google | G66: Cheap and cheerful. It’s a small place so book early to be assured of a spot. Family friendly. Basic, clean facilities. | H66: Koroit-Tower Hill Caravan Park | I66: 28291 | J66: 2021-10-11 | K66: {"overall_sentiment":"positive","aspects":[{"aspect":"price","category":"cost","sentiment":"positive","evidence_span":"Cheap"},{"aspect":"ambiance","category":"atmosphere","sentiment":"positive","evidence_span":"cheerful"},{"aspect":"family friendly","category":"atmosphere","sentiment":"positive","evidence_span":"Family friendly"},{"aspect":"facilities","category":"amenities","sentiment":"positive","evidence_span":"clean facilities"}]} | L66: {'sentence': 'Cheap and cheerful . It ’ s a small place so book early to be assured of a spot . Family friendly . Basic , clean facilities .', 'IOB': ['O', 'O', 'O', 'O', 'O', 'O', 'O', 'O', 'O', 'O', 'O', 'O', 'O', 'O', 'O', 'O', 'O', 'O', 'O', 'O', 'O', 'O', 'O', 'O', 'O', 'O', 'B-ASP', 'O'], 'tokens': ['Cheap', 'and', 'cheerful', '.', 'It', '’', 's', 'a', 'small', 'place', 'so', 'book', 'early', 'to', 'be', 'assured', 'of', 'a', 'spot', '.', 'Family', 'friendly', '.', 'Basic', ',', 'clean', 'facilities', '.'], 'aspect': ['facilities'], 'position': [[26]], 'sentiment': ['Positive'], 'probs': [[0.0007862444617785513, 0.001833240850828588, 0.9973804354667664]], 'confidence': [0.9974]} | M66: 1 | N66: =LEN(K66)-LEN(SUBSTITUTE(K66,"{",""))-1 -> 4 | O66: 1 | P66: =_xlfn.XLOOKUP(B66,'g1'!B:B,'g1'!R:R) -> 5 | Q66: =_xlfn.XLOOKUP(B66,'g2'!B:B,'g2'!U:U) -> 4 | R66: =_xlfn.XLOOKUP(B66,'g3'!B:B,'g3'!R:R) -> 5 | S66: =_xlfn.XLOOKUP(D66,'g4'!D:D,'g4'!N:N) -> 5 | T66: =$N66-P66 -> -1 | U66: =$N66-Q66 -> 0 | V66: =$N66-R66 -> -1 | W66: =$N66-S66 -> -1 | X66: [{'aspect': 'family-friendliness', 'opinion': 'family friendly', 'sentiment': 'positive'}, {'aspect': 'price', 'opinion': 'cheap and cheerful', 'sentiment': 'positive'}, {'aspect': 'atmosphere', 'opinion': 'small place', 'sentiment': 'neutral'}, {'aspect': 'size', 'opinion': 'small place', 'sentiment': 'neutral'}, {'aspect': 'facilities', 'opinion': 'basic, clean', 'sentiment': 'positive'}] | Y66: =FIND("[{",K66) -> 43 | Z66: =FIND("category",K66) -> 63 | AA66: =Z66-Y66-2 -> 18 | AB66: price | AD66: =FIND("[{",X66) -> 1 | AE66: =FIND("opinion",X66) -> 37 | AF66: =AE66-AD66-2 -> 34 | AG66: family-friendliness | AH66: =AB66=AG66 -> FALSE
